Workbook

Sheet Setup
A1: Premium Budget System — 2026 (26th–25th Periods)
A3: Income assumptions (net)
A4: FM payday amount (monthly) | B4: 3500
A5: McD payday amount (biweekly) | B5: 400
A6: Outlier payday amount (weekly) | B6: 100
A7: McD next payday date (seed) | B7: 46023
A8: Outlier next payday date (seed - Wed) | B8: 46029
A10: Targets (Aggressive Plan)
A11: Monthly savings transfer target | B11: 1050
A12: Variable cap per period (Food+Donations+Others+One-offs) | B12: 420
A15: Category list (dropdown source)
A16: Group | B16: Category
A17: INCOME | B17: Income - FM
A18: INCOME | B18: Income - McD
A19: INCOME | B19: Income - Outlier
A20: GIVING | B20: Tithe
A21: GIVING | B21: Offerings
A22: GIVING | B22: Charity - Perez Uni
A23: GIVING | B23: Charity - JPC Utilities
A24: GIVING | B24: Donations (Variable)
A25: FIXED | B25: Rent
A26: FIXED | B26: Insurance
A27: FIXED | B27: Road Tax
... A41: POT | B41: Buffer Top-Up
A46: Weekly Pay Yourself
A47: Weekly Allowance (£) | B47: 140
A48: Weeks per Period | B48: 4
A49: Monthly Living Pool (£) | B49: =B47*B48 -> 560
A52: One-Off Giving (Christmas / Special)
A53: Christmas Giving Target (£) | B53: 500
A54: Rule | B54: Fund only from new inflows (Outlier/McD); can be split.

Sheet Mental Allocations
A1: Mental Allocations
A2: This page shows what to mentally set aside when FM arrives. It updates from Setup + Bills Schedule.
A4: Selected Period | B4: =Dashboard!B4 -> 1 | D4: FM received (edit if different) | E4: =Setup!$B$4 -> 3500
A6: Allocation | B6: Amount
A7: Bills + Regular Giving (this period) | B7: =SUM('Bills Schedule'!$C$3:$C$200) -> 4715
A8: Weekly Living Pool (4 weeks) | B8: =Setup!B49 -> 560
A9: Buffer Top-Up (target £800–£1,000) | B9: =0 -> 0
A10: One-Off Giving Pot (Christmas target) | B10: =Setup!B53 -> 500
A11: Savings (sweep near period end) | B11: =0 -> 0
A12: Unassigned / Remaining | B12: =E4-SUM(B7:B11) -> -2275
A13: Notes
A14: • Buffer is NOT for spending. It protects timing gaps.
A15: • One-Off Giving is funded from new inflows (Outlier/McD).
A16: • Savings are a sweep at the end once liquidity is safe.

Sheet Periods 26-25
A1: Period | B1: Label | C1: Start | D1: End | E1: Next Start
A2: 1 | B2: P1: 22 Dec 2025–25 Jan 2026 | C2: 46013 | D2: 46047 | E2: 46048
A3: 2 | B3: P2: 26 Jan 2026–25 Feb 2026 | C3: 46048 | D3: 46078 | E3: 46079
A4: 3 | B4: P3: 26 Feb 2026–25 Mar 2026 | C4: 46079 | D4: 46106 | E4: 46107
A5: 4 | B5: P4: 26 Mar 2026–25 Apr 2026 | C5: 46107 | D5: 46137 | E5: 46138
A6: 5 | B6: P5: 26 Apr 2026–25 May 2026 | C6: 46138 | D6: 46167 | E6: 46168
A7: 6 | B7: P6: 26 May 2026–25 Jun 2026 | C7: 46168 | D7: 46198 | E7: 46199
A8: 7 | B8: P7: 26 Jun 2026–25 Jul 2026 | C8: 46199 | D8: 46228 | E8: 46229
A9: 8 | B9: P8: 26 Jul 2026–25 Aug 2026 | C9: 46229 | D9: 46259 | E9: 46260
A10: 9 | B10: P9: 26 Aug 2026–25 Sep 2026 | C10: 46260 | D10: 46290 | E10: 46291
A11: 10 | B11: P10: 26 Sep 2026–25 Oct 2026 | C11: 46291 | D11: 46320 | E11: 46321
A12: 11 | B12: P11: 26 Oct 2026–25 Nov 2026 | C12: 46321 | D12: 46351 | E12: 46352
A13: 12 | B13: P12: 26 Nov 2026–25 Dec 2026 | C13: 46352 | D13: 46381 | E13: 46382

Sheet Income Schedule
A1: Expected Income Schedule (based on your pay timelines) | G1: InWindow | H1: Key
A2: Date | B2: Source | C2: Expected Amount | D2: Period | E2: Notes
A3: 46013 | B3: FM (Christmas early) | C3: =Setup!$B$4 -> 3500 | D3: =MATCH(A3,'Periods 26-25'!$C$2:$C$13,1) -> 1 | E3: Paid early (Christmas) | G3: =AND($A3>='Upcoming Income'!$B$4,$A3<='Upcoming Income'!$B$4+'Upcoming Income'!$E$4) -> FALSE
A4: 46048 | B4: FM (26th) | C4: =Setup!$B$4 -> 3500 | D4: =MATCH(A3,'Periods 26-25'!$C$2:$C$13,1) -> 1 | E4: Latest by 26th | G4: =AND($A3>='Upcoming Income'!$B$4,$A3<='Upcoming Income'!$B$4+'Upcoming Income'!$E$4) -> FALSE | H4: =IF($G3,$A3+ROW()/100000,"")
A5: 46079 | B5: FM (26th) | C5: =Setup!$B$4 -> 3500 | D5: =MATCH(A4,'Periods 26-25'!$C$2:$C$13,1) -> 2 | E5: Latest by 26th | G5: =AND($A4>='Upcoming Income'!$B$4,$A4<='Upcoming Income'!$B$4+'Upcoming Income'!$E$4) -> TRUE | H5: =IF($G4,$A4+ROW()/100000,"")
A6: 46107 | B6: FM (26th) | C6: =Setup!$B$4 -> 3500 | D6: =MATCH(A5,'Periods 26-25'!$C$2:$C$13,1) -> 3 | E6: Latest by 26th | G6: =AND($A5>='Upcoming Income'!$B$4,$A5<='Upcoming Income'!$B$4+'Upcoming Income'!$E$4) -> FALSE | H6: =IF($G5,$A5+ROW()/100000,"") -> 46079
A7: 46138 | B7: FM (26th) | C7: =Setup!$B$4 -> 3500 | D7: =MATCH(A6,'Periods 26-25'!$C$2:$C$13,1) -> 4 | E7: Latest by 26th | G7: =AND($A6>='Upcoming Income'!$B$4,$A6<='Upcoming Income'!$B$4+'Upcoming Income'!$E$4) -> FALSE | H7: =IF($G6,$A6+ROW()/100000,"")
A8: 46168 | B8: FM (26th) | C8: =Setup!$B$4 -> 3500 | D8: =MATCH(A7,'Periods 26-25'!$C$2:$C$13,1) -> 5 | E8: Latest by 26th | G8: =AND($A7>='Upcoming Income'!$B$4,$A7<='Upcoming Income'!$B$4+'Upcoming Income'!$E$4) -> FALSE | H8: =IF($G7,$A7+ROW()/100000,"")
A9: 46199 | B9: FM (26th) | C9: =Setup!$B$4 -> 3500 | D9: =MATCH(A8,'Periods 26-25'!$C$2:$C$13,1) -> 6 | E9: Latest by 26th | G9: =AND($A8>='Upcoming Income'!$B$4,$A8<='Upcoming Income'!$B$4+'Upcoming Income'!$E$4) -> FALSE | H9: =IF($G8,$A8+ROW()/100000,"")
A10: 46229 | B10: FM (26th) | C10: =Setup!$B$4 -> 3500 | D10: =MATCH(A9,'Periods 26-25'!$C$2:$C$13,1) -> 7 | E10: Latest by 26th | G10: =AND($A9>='Upcoming Income'!$B$4,$A9<='Upcoming Income'!$B$4+'Upcoming Income'!$E$4) -> FALSE | H10: =IF($G9,$A9+ROW()/100000,"")
A11: 46260 | B11: FM (26th) | C11: =Setup!$B$4 -> 3500 | D11: =MATCH(A10,'Periods 26-25'!$C$2:$C$13,1) -> 8 | E11: Latest by 26th | G11: =AND($A10>='Upcoming Income'!$B$4,$A10<='Upcoming Income'!$B$4+'Upcoming Income'!$E$4) -> FALSE | H11: =IF($G10,$A10+ROW()/100000,"")
A12: 46291 | B12: FM (26th) | C12: =Setup!$B$4 -> 3500 | D12: =MATCH(A11,'Periods 26-25'!$C$2:$C$13,1) -> 9 | E12: Latest by 26th | G12: =AND($A11>='Upcoming Income'!$B$4,$A11<='Upcoming Income'!$B$4+'Upcoming Income'!$E$4) -> FALSE | H12: =IF($G11,$A11+ROW()/100000,"")
A13: 46321 | B13: FM (26th) | C13: =Setup!$B$4 -> 3500 | D13: =MATCH(A12,'Periods 26-25'!$C$2:$C$13,1) -> 10 | E13: Latest by 26th | G13: =AND($A12>='Upcoming Income'!$B$4,$A12<='Upcoming Income'!$B$4+'Upcoming Income'!$E$4) -> FALSE | H13: =IF($G12,$A12+ROW()/100000,"")
A14: 46352 | B14: FM (26th) | C14: =Setup!$B$4 -> 3500 | D14: =MATCH(A13,'Periods 26-25'!$C$2:$C$13,1) -> 11 | E14: Latest by 26th | G14: =AND($A13>='Upcoming Income'!$B$4,$A13<='Upcoming Income'!$B$4+'Upcoming Income'!$E$4) -> FALSE | H14: =IF($G13,$A13+ROW()/100000,"")
A15: 46382 | B15: FM (26th) | C15: =Setup!$B$4 -> 3500 | D15: =MATCH(A14,'Periods 26-25'!$C$2:$C$13,1) -> 12 | E15: Latest by 26th | G15: =AND($A14>='Upcoming Income'!$B$4,$A14<='Upcoming Income'!$B$4+'Upcoming Income'!$E$4) -> FALSE | H15: =IF($G14,$A14+ROW()/100000,"")
A16: 46023 | B16: McD (biweekly) | C16: =Setup!$B$5 -> 400 | D16: =MATCH(A15,'Periods 26-25'!$C$2:$C$13,1) -> 12 | E16: Every 2 weeks | G16: =AND($A15>='Upcoming Income'!$B$4,$A15<='Upcoming Income'!$B$4+'Upcoming Income'!$E$4) -> FALSE | H16: =IF($G15,$A15+ROW()/100000,"")
A17: 46037 | B17: McD (biweekly) | C17: =Setup!$B$5 -> 400 | D17: =MATCH(A16,'Periods 26-25'!$C$2:$C$13,1) -> 1 | E17: Every 2 weeks | G17: =AND($A16>='Upcoming Income'!$B$4,$A16<='Upcoming Income'!$B$4+'Upcoming Income'!$E$4) -> TRUE | H17: =IF($G16,$A16+ROW()/100000,"")
A18: 46051 | B18: McD (biweekly) | C18: =Setup!$B$5 -> 400 | D18: =MATCH(A17,'Periods 26-25'!$C$2:$C$13,1) -> 1 | E18: Every 2 weeks | G18: =AND($A17>='Upcoming Income'!$B$4,$A17<='Upcoming Income'!$B$4+'Upcoming Income'!$E$4) -> TRUE | H18: =IF($G17,$A17+ROW()/100000,"") -> 46037
A19: 46065 | B19: McD (biweekly) | C19: =Setup!$B$5 -> 400 | D19: =MATCH(A18,'Periods 26-25'!$C$2:$C$13,1) -> 2 | E19: Every 2 weeks | G19: =AND($A18>='Upcoming Income'!$B$4,$A18<='Upcoming Income'!$B$4+'Upcoming Income'!$E$4) -> FALSE | H19: =IF($G18,$A18+ROW()/100000,"") -> 46051
A20: 46079 | B20: McD (biweekly) | C20: =Setup!$B$5 -> 400 | D20: =MATCH(A19,'Periods 26-25'!$C$2:$C$13,1) -> 2 | E20: Every 2 weeks | G20: =AND($A19>='Upcoming Income'!$B$4,$A19<='Upcoming Income'!$B$4+'Upcoming Income'!$E$4) -> FALSE | H20: =IF($G19,$A19+ROW()/100000,"")
A21: 46093 | B21: McD (biweekly) | C21: =Setup!$B$5 -> 400 | D21: =MATCH(A20,'Periods 26-25'!$C$2:$C$13,1) -> 3 | E21: Every 2 weeks | G21: =AND($A20>='Upcoming Income'!$B$4,$A20<='Upcoming Income'!$B$4+'Upcoming Income'!$E$4) -> FALSE | H21: =IF($G20,$A20+ROW()/100000,"")
A22: 46107 | B22: McD (biweekly) | C22: =Setup!$B$5 -> 400 | D22: =MATCH(A21,'Periods 26-25'!$C$2:$C$13,1) -> 3 | E22: Every 2 weeks | G22: =AND($A21>='Upcoming Income'!$B$4,$A21<='Upcoming Income'!$B$4+'Upcoming Income'!$E$4) -> FALSE | H22: =IF($G21,$A21+ROW()/100000,"")
A23: 46121 | B23: McD (biweekly) | C23: =Setup!$B$5 -> 400 | D23: =MATCH(A22,'Periods 26-25'!$C$2:$C$13,1) -> 4 | E23: Every 2 weeks | G23: =AND($A22>='Upcoming Income'!$B$4,$A22<='Upcoming Income'!$B$4+'Upcoming Income'!$E$4) -> FALSE | H23: =IF($G22,$A22+ROW()/100000,"")
A24: 46135 | B24: McD (biweekly) | C24: =Setup!$B$5 -> 400 | D24: =MATCH(A23,'Periods 26-25'!$C$2:$C$13,1) -> 4 | E24: Every 2 weeks | G24: =AND($A23>='Upcoming Income'!$B$4,$A23<='Upcoming Income'!$B$4+'Upcoming Income'!$E$4) -> FALSE | H24: =IF($G23,$A23+ROW()/100000,"")
A25: 46149 | B25: McD (biweekly) | C25: =Setup!$B$5 -> 400 | D25: =MATCH(A24,'Periods 26-25'!$C$2:$C$13,1) -> 4 | E25: Every 2 weeks | G25: =AND($A24>='Upcoming Income'!$B$4,$A24<='Upcoming Income'!$B$4+'Upcoming Income'!$E$4) -> FALSE | H25: =IF($G24,$A24+ROW()/100000,"")
A26: 46163 | B26: McD (biweekly) | C26: =Setup!$B$5 -> 400 | D26: =MATCH(A25,'Periods 26-25'!$C$2:$C$13,1) -> 5 | E26: Every 2 weeks | G26: =AND($A25>='Upcoming Income'!$B$4,$A25<='Upcoming Income'!$B$4+'Upcoming Income'!$E$4) -> FALSE | H26: =IF($G25,$A25+ROW()/100000,"")
A27: 46177 | B27: McD (biweekly) | C27: =Setup!$B$5 -> 400 | D27: =MATCH(A26,'Periods 26-25'!$C$2:$C$13,1) -> 5 | E27: Every 2 weeks | G27: =AND($A26>='Upcoming Income'!$B$4,$A26<='Upcoming Income'!$B$4+'Upcoming Income'!$E$4) -> FALSE | H27: =IF($G26,$A26+ROW()/100000,"")
... A42: 46387 | B42: McD (biweekly) | C42: =Setup!$B$5 -> 400 | D42: =MATCH(A41,'Periods 26-25'!$C$2:$C$13,1) -> 12 | E42: Every 2 weeks | G42: =AND($A41>='Upcoming Income'!$B$4,$A41<='Upcoming Income'!$B$4+'Upcoming Income'!$E$4) -> FALSE | H42: =IF($G41,$A41+ROW()/100000,"")
A43: 46029 | B43: Outlier (weekly Wed) | C43: =Setup!$B$6 -> 100 | D43: =MATCH(A42,'Periods 26-25'!$C$2:$C$13,1) -> 12 | E43: Weekly Wednesday | G43: =AND($A42>='Upcoming Income'!$B$4,$A42<='Upcoming Income'!$B$4+'Upcoming Income'!$E$4) -> FALSE | H43: =IF($G42,$A42+ROW()/100000,"")
A44: 46036 | B44: Outlier (weekly Wed) | C44: =Setup!$B$6 -> 100 | D44: =MATCH(A43,'Periods 26-25'!$C$2:$C$13,1) -> 1 | E44: Weekly Wednesday | G44: =AND($A43>='Upcoming Income'!$B$4,$A43<='Upcoming Income'!$B$4+'Upcoming Income'!$E$4) -> TRUE | H44: =IF($G43,$A43+ROW()/100000,"")
A45: 46043 | B45: Outlier (weekly Wed) | C45: =Setup!$B$6 -> 100 | D45: =MATCH(A44,'Periods 26-25'!$C$2:$C$13,1) -> 1 | E45: Weekly Wednesday | G45: =AND($A44>='Upcoming Income'!$B$4,$A44<='Upcoming Income'!$B$4+'Upcoming Income'!$E$4) -> TRUE | H45: =IF($G44,$A44+ROW()/100000,"") -> 46036
A46: 46050 | B46: Outlier (weekly Wed) | C46: =Setup!$B$6 -> 100 | D46: =MATCH(A45,'Periods 26-25'!$C$2:$C$13,1) -> 1 | E46: Weekly Wednesday | G46: =AND($A45>='Upcoming Income'!$B$4,$A45<='Upcoming Income'!$B$4+'Upcoming Income'!$E$4) -> TRUE | H46: =IF($G45,$A45+ROW()/100000,"") -> 46043
A47: 46057 | B47: Outlier (weekly Wed) | C47: =Setup!$B$6 -> 100 | D47: =MATCH(A46,'Periods 26-25'!$C$2:$C$13,1) -> 2 | E47: Weekly Wednesday | G47: =AND($A46>='Upcoming Income'!$B$4,$A46<='Upcoming Income'!$B$4+'Upcoming Income'!$E$4) -> TRUE | H47: =IF($G46,$A46+ROW()/100000,"") -> 46050
A48: 46064 | B48: Outlier (weekly Wed) | C48: =Setup!$B$6 -> 100 | D48: =MATCH(A47,'Periods 26-25'!$C$2:$C$13,1) -> 2 | E48: Weekly Wednesday | G48: =AND($A47>='Upcoming Income'!$B$4,$A47<='Upcoming Income'!$B$4+'Upcoming Income'!$E$4) -> FALSE | H48: =IF($G47,$A47+ROW()/100000,"") -> 46057
A49: 46071 | B49: Outlier (weekly Wed) | C49: =Setup!$B$6 -> 100 | D49: =MATCH(A48,'Periods 26-25'!$C$2:$C$13,1) -> 2 | E49: Weekly Wednesday | G49: =AND($A48>='Upcoming Income'!$B$4,$A48<='Upcoming Income'!$B$4+'Upcoming Income'!$E$4) -> FALSE | H49: =IF($G48,$A48+ROW()/100000,"")
A50: 46078 | B50: Outlier (weekly Wed) | C50: =Setup!$B$6 -> 100 | D50: =MATCH(A49,'Periods 26-25'!$C$2:$C$13,1) -> 2 | E50: Weekly Wednesday | G50: =AND($A49>='Upcoming Income'!$B$4,$A49<='Upcoming Income'!$B$4+'Upcoming Income'!$E$4) -> FALSE | H50: =IF($G49,$A49+ROW()/100000,"")
A51: 46085 | B51: Outlier (weekly Wed) | C51: =Setup!$B$6 -> 100 | D51: =MATCH(A50,'Periods 26-25'!$C$2:$C$13,1) -> 2 | E51: Weekly Wednesday | G51: =AND($A50>='Upcoming Income'!$B$4,$A50<='Upcoming Income'!$B$4+'Upcoming Income'!$E$4) -> FALSE | H51: =IF($G50,$A50+ROW()/100000,"")
A52: 46092 | B52: Outlier (weekly Wed) | C52: =Setup!$B$6 -> 100 | D52: =MATCH(A51,'Periods 26-25'!$C$2:$C$13,1) -> 3 | E52: Weekly Wednesday | G52: =AND($A51>='Upcoming Income'!$B$4,$A51<='Upcoming Income'!$B$4+'Upcoming Income'!$E$4) -> FALSE | H52: =IF($G51,$A51+ROW()/100000,"")
A53: 46099 | B53: Outlier (weekly Wed) | C53: =Setup!$B$6 -> 100 | D53: =MATCH(A52,'Periods 26-25'!$C$2:$C$13,1) -> 3 | E53: Weekly Wednesday | G53: =AND($A52>='Upcoming Income'!$B$4,$A52<='Upcoming Income'!$B$4+'Upcoming Income'!$E$4) -> FALSE | H53: =IF($G52,$A52+ROW()/100000,"")
A54: 46106 | B54: Outlier (weekly Wed) | C54: =Setup!$B$6 -> 100 | D54: =MATCH(A53,'Periods 26-25'!$C$2:$C$13,1) -> 3 | E54: Weekly Wednesday | G54: =AND($A53>='Upcoming Income'!$B$4,$A53<='Upcoming Income'!$B$4+'Upcoming Income'!$E$4) -> FALSE | H54: =IF($G53,$A53+ROW()/100000,"")
... A94: 46386 | B94: Outlier (weekly Wed) | C94: =Setup!$B$6 -> 100 | D94: =MATCH(A93,'Periods 26-25'!$C$2:$C$13,1) -> 12 | E94: Weekly Wednesday | G94: =AND($A93>='Upcoming Income'!$B$4,$A93<='Upcoming Income'!$B$4+'Upcoming Income'!$E$4) -> FALSE | H94: =IF($G93,$A93+ROW()/100000,"")
A95: Additional Outlier payments before 2026 seed | G95: =AND($A94>='Upcoming Income'!$B$4,$A94<='Upcoming Income'!$B$4+'Upcoming Income'!$E$4) -> FALSE | H95: =IF($G94,$A94+ROW()/100000,"")
A96: 46015 | B96: Outlier (weekly Wed) | C96: =Setup!$B$6 -> 100 | E96: Before 2026 schedule | G96: =AND($A95>='Upcoming Income'!$B$4,$A95<='Upcoming Income'!$B$4+'Upcoming Income'!$E$4) -> FALSE | H96: =IF($G95,$A95+ROW()/100000,"")
A97: 46022 | B97: Outlier (weekly Wed) | C97: =Setup!$B$6 -> 100 | E97: Before 2026 schedule | G97: =AND($A96>='Upcoming Income'!$B$4,$A96<='Upcoming Income'!$B$4+'Upcoming Income'!$E$4) -> FALSE | H97: =IF($G96,$A96+ROW()/100000,"")

Sheet Transactions
A1: Date | B1: Type | C1: Category | D1: Description | E1: Amount (£) | F1: One-off? | G1: Payment Method | H1: Notes | I1: Period (auto)
A2: 46006 | B2: Expense | C2: Others | D2: Apple cloud subscription | E2: 2.99 | F2: No | G2: Direct Debit | H2: Cloud storage | I2: =IFERROR(MATCH(A2,'Periods 26-25'!$C$2:$C$13,1),"")
A3: 46007 | B3: Expense | C3: Electricity & Gas | D3: Electricity | E3: 10 | F3: No | G3: Apple Pay | H3: Electricity | I3: =IFERROR(MATCH(A3,'Periods 26-25'!$C$2:$C$13,1),"")
A4: 46008 | B4: Expense | C4: Electricity & Gas | D4: Electricity | E4: 10 | F4: No | G4: Apple Pay | H4: Gas | I4: =IFERROR(MATCH(A4,'Periods 26-25'!$C$2:$C$13,1),"")
A5: 46008 | B5: Expense | C5: Food | D5: Costco | E5: 45.6 | F5: No | G5: Apple Pay | H5: Food for the house | I5: =IFERROR(MATCH(A5,'Periods 26-25'!$C$2:$C$13,1),"")
A6: 46009 | B6: Expense | C6: Food | D6: Tesco | E6: 4.99 | F6: No | G6: Apple Pay | H6: water for the house | I6: =IFERROR(MATCH(A6,'Periods 26-25'!$C$2:$C$13,1),"")
A7: 46010 | B7: Expense | C7: Food | D7: Costco | E7: 4 | F7: No | G7: Apple Pay | H7: egg | I7: =IFERROR(MATCH(A7,'Periods 26-25'!$C$2:$C$13,1),"")
A8: 46007 | B8: Expense | C8: Others | D8: Transportation - TfL | E8: 7.2 | F8: No | G8: Apple Pay | H8: To the office | I8: =IFERROR(MATCH(A8,'Periods 26-25'!$C$2:$C$13,1),"")
A9: 46010 | B9: Expense | C9: Others | D9: Fuel | E9: 30.01 | F9: No | G9: Apple Pay | H9: for the week | I9: =IFERROR(MATCH(A9,'Periods 26-25'!$C$2:$C$13,1),"")
A10: 46011 | B10: Expense | C10: Others | D10: Transportation - TfL | E10: 10.1 | F10: No | G10: Apple Pay | H10: To Milton keynes - train disruption | I10: =IFERROR(MATCH(A10,'Periods 26-25'!$C$2:$C$13,1),"")
A11: 46011 | B11: Expense | C11: Others | D11: Transportation - TfL | E11: 4.97 | F11: No | G11: Apple Pay | H11: Uber to PKG address | I11: =IFERROR(MATCH(A11,'Periods 26-25'!$C$2:$C$13,1),"")
A12: 46012 | B12: Expense | C12: Others | D12: Tyre puncture | E12: 10 | F12: Yes | G12: Apple Pay | H12: flat tyre, puncture repaired | I12: =IFERROR(MATCH(A12,'Periods 26-25'!$C$2:$C$13,1),"")
A13: 46013 | B13: Income | C13: Income - FM | D13: December Salary | E13: 3700 | F13: No | G13: Bank transfer | H13: N/A | I13: =IFERROR(MATCH(A13,'Periods 26-25'!$C$2:$C$13,1),"") -> 1
... A20: 46014 | B20: Expense | C20: Offerings | D20: Thanksgiving Offering | E20: 60 | F20: No | G20: Bank transfer | H20: Offering for December - PJ | I20: =IFERROR(MATCH(A20,'Periods 26-25'!$C$2:$C$13,1),"") -> 1
A21: 46014 | B21: Expense | C21: Parents | D21: Mummy J and Mummy R | E21: =65+75 -> 140 | F21: No | G21: Bank transfer | H21: Allowance for December | I21: =IFERROR(MATCH(A21,'Periods 26-25'!$C$2:$C$13,1),"") -> 1
A22: 46015 | B22: Income | C22: Income - Outlier | D22: Outlier on 24/12/2025 | E22: 111.48 | F22: No | G22: Bank transfer | H22: Weekly allowance | I22: =IFERROR(MATCH(A22,'Periods 26-25'!$C$2:$C$13,1),"") -> 1
A23: 46015 | B23: Expense | C23: Tithe | D23: Outlier Tithe | E23: 12 | F23: No | G23: Bank transfer | H23: Tithe on Outlier | I23: =IFERROR(MATCH(A23,'Periods 26-25'!$C$2:$C$13,1),"") -> 1
A24: 46014 | B24: Expense | C24: House Keep | D24: Wipes | E24: 11.25 | F24: No | G24: Apple Pay | H24: wipes for Josh | I24: =IFERROR(MATCH(A24,'Periods 26-25'!$C$2:$C$13,1),"") -> 1
A25: 46013 | B25: Expense | C25: Credit Card Payment | D25: Monzo payment | E25: 295.21 | F25: No | G25: Apple Pay | H25: Monzo payment - Dec | I25: =IFERROR(MATCH(A25,'Periods 26-25'!$C$2:$C$13,1),"") -> 1
A26: 46013 | B26: Expense | C26: Charity - Perez Uni | D26: Sacrifice for Dec | E26: 50 | F26: No | G26: Bank transfer | H26: December contribution | I26: =IFERROR(MATCH(A26,'Periods 26-25'!$C$2:$C$13,1),"") -> 1
A27: 46013 | B27: Expense | C27: House Keep | D27: Lebara | E27: 9 | F27: No | G27: Apple Pay | H27: Data wifey | I27: =IFERROR(MATCH(A27,'Periods 26-25'!$C$2:$C$13,1),"") -> 1
A28: 46013 | B28: Expense | C28: House Keep | D28: Body wash | E28: 16.5 | F28: No | G28: Apple Pay | H28: Avon comestics | I28: =IFERROR(MATCH(A28,'Periods 26-25'!$C$2:$C$13,1),"") -> 1
A29: 46015 | B29: Expense | C29: One-Off Giving (Christmas) | D29: Gift to families | E29: 457.37 | F29: Yes | G29: Bank transfer | H29: Gift for the Christmas Season | I29: =IFERROR(MATCH(A29,'Periods 26-25'!$C$2:$C$13,1),"") -> 1
A30: 46015 | B30: Expense | C30: Electricity & Gas | D30: Electricity | E30: 10 | F30: No | G30: Apple Pay | H30: Electricity for the house | I30: =IFERROR(MATCH(A30,'Periods 26-25'!$C$2:$C$13,1),"") -> 1
A31: 46015 | B31: Expense | C31: House Keep | D31: Ingredients for cake | E31: 7.78 | F31: No | G31: Apple Pay | H31: Cake for Auntie Faith & Fam | I31: =IFERROR(MATCH(A31,'Periods 26-25'!$C$2:$C$13,1),"") -> 1
A32: 46015 | B32: Expense | C32: Fuel | D32: Fuel for Renault Scenic | E32: 30.17 | F32: No | G32: Apple Pay | H32: on the 24/12 - Fuel | I32: =IFERROR(MATCH(A32,'Periods 26-25'!$C$2:$C$13,1),"") -> 1
A33: 46017 | B33: Expense | C33: iPhone Payments | D33: payment for wifey's phone | E33: 29 | F33: No | G33: Bank transfer | H33: last payment for iphone 13 | I33: =IFERROR(MATCH(A33,'Periods 26-25'!$C$2:$C$13,1),"") -> 1
... A47: 46020 | B47: Expense | C47: Electricity & Gas | D47: Gas | E47: 10 | F47: No | G47: Apple Pay | H47: Gas for the house | I47: =IFERROR(MATCH(A47,'Periods 26-25'!$C$2:$C$13,1),"") -> 1
I48: =IFERROR(MATCH(A48,'Periods 26-25'!$C$2:$C$13,1),"")
I49: =IFERROR(MATCH(A49,'Periods 26-25'!$C$2:$C$13,1),"")
I50: =IFERROR(MATCH(A50,'Periods 26-25'!$C$2:$C$13,1),"")
I51: =IFERROR(MATCH(A51,'Periods 26-25'!$C$2:$C$13,1),"")
I52: =IFERROR(MATCH(A52,'Periods 26-25'!$C$2:$C$13,1),"")
I53: =IFERROR(MATCH(A53,'Periods 26-25'!$C$2:$C$13,1),"")
I54: =IFERROR(MATCH(A54,'Periods 26-25'!$C$2:$C$13,1),"")
I55: =IFERROR(MATCH(A55,'Periods 26-25'!$C$2:$C$13,1),"")
I56: =IFERROR(MATCH(A56,'Periods 26-25'!$C$2:$C$13,1),"")
I57: =IFERROR(MATCH(A57,'Periods 26-25'!$C$2:$C$13,1),"")
I58: =IFERROR(MATCH(A58,'Periods 26-25'!$C$2:$C$13,1),"")
I59: =IFERROR(MATCH(A59,'Periods 26-25'!$C$2:$C$13,1),"")
... I1200: =IFERROR(MATCH(A1200,'Periods 26-25'!$C$2:$C$13,1),"")

Sheet Bills Schedule
A1: Bills & Fixed Expenses Schedule (typically 26th–3rd)
A2: Bill | B2: Typical Due Day | C2: Budget / Period | D2: Paid? (tick) | E2: Period | F2: Actual Paid (auto) | G2: Variance | H2: Notes | O2: Monthly contribution
A3: Rent | B3: 28 | C3: 550 | E3: 1 | F3: =IF($E3="","",SUMIFS(Transactions!$E:$E,Transactions!$C:$C,$A3,Transactions!$B:$B,"Expense",Transactions!$I:$I,$E3)) -> 0 | G3: =F3-C3 -> -550 | K3: * To add transfers for prudential | O3: GhS | P3: £ | Q3: £
A4: Insurance | B4: 28 | C4: 175 | E4: 1 | F4: =IF($E4="","",SUMIFS(Transactions!$E:$E,Transactions!$C:$C,$A4,Transactions!$B:$B,"Expense",Transactions!$I:$I,$E4)) -> 0 | G4: =F4-C4 -> -175 | K4: - GhS 100k for children Education | O4: 516.63 | P4: =O4/15 -> 34.442 | Q4: 35 | R4: from April
A5: Road Tax | B5: 28 | C5: 34 | E5: 1 | F5: =IF($E5="","",SUMIFS(Transactions!$E:$E,Transactions!$C:$C,$A5,Transactions!$B:$B,"Expense",Transactions!$I:$I,$E5)) -> 0 | G5: =F5-C5 -> -34 | K5: - GhS 100K for Bishop at 60years | O5: 1346.83 | P5: =O5/15 -> 89.788667 | Q5: 90 | R5: from Dec
A6: Water Bill | B6: 28 | C6: 93 | E6: 1 | F6: =IF($E6="","",SUMIFS(Transactions!$E:$E,Transactions!$C:$C,$A6,Transactions!$B:$B,"Expense",Transactions!$I:$I,$E6)) -> 92.77 | G6: =F6-C6 -> -0.23 | K6: - GhS 12K for student loan | O6: 500 | P6: =O6/15 -> 33.333333 | Q6: 34 | R6: from Dec
A7: Community Fibre / Internet | B7: 26 | C7: 37 | E7: 1 | F7: =IF($E7="","",SUMIFS(Transactions!$E:$E,Transactions!$C:$C,$A7,Transactions!$B:$B,"Expense",Transactions!$I:$I,$E7)) -> 36.83 | G7: =F7-C7 -> -0.17 | K7: - GhS 50K for Mr Mensah | O7: 187.3 | P7: =O7/15 -> 12.486667 | Q7: 13 | R7: from Dec
A8: Electricity & Gas | B8: 26 | C8: 200 | E8: 1 | F8: =IF($E8="","",SUMIFS(Transactions!$E:$E,Transactions!$C:$C,$A8,Transactions!$B:$B,"Expense",Transactions!$I:$I,$E8)) -> 50 | G8: =F8-C8 -> -150 | O8: =SUM(O4:O7) -> 2550.76 | P8: =SUM(P4:P7) -> 170.05067 | Q8: =SUM(Q4:Q7) -> 172
A9: iPhone Payments | B9: 26 | C9: 108 | E9: 1 | F9: =IF($E9="","",SUMIFS(Transactions!$E:$E,Transactions!$C:$C,$A9,Transactions!$B:$B,"Expense",Transactions!$I:$I,$E9)) -> 53.95 | G9: =F9-C9 -> -54.05
A10: Parents | B10: 26 | C10: 140 | E10: 1 | F10: =IF($E10="","",SUMIFS(Transactions!$E:$E,Transactions!$C:$C,$A10,Transactions!$B:$B,"Expense",Transactions!$I:$I,$E10)) -> 140 | G10: =F10-C10 -> 0
A11: Credit Card Payment | B11: 26 | C11: 400 | E11: 1 | F11: =IF($E11="","",SUMIFS(Transactions!$E:$E,Transactions!$C:$C,$A11,Transactions!$B:$B,"Expense",Transactions!$I:$I,$E11)) -> 438.92 | G11: =F11-C11 -> 38.92 | Q11: 3500
A12: Fuel | B12: 26 | C12: 100 | E12: 1 | F12: =IF($E12="","",SUMIFS(Transactions!$E:$E,Transactions!$C:$C,$A12,Transactions!$B:$B,"Expense",Transactions!$I:$I,$E12)) -> 30.17 | G12: =F12-C12 -> -69.83 | Q12: 800
A13: Tithe | B13: 26 | C13: 410 | E13: 1 | F13: =IF($E13="","",SUMIFS(Transactions!$E:$E,Transactions!$C:$C,$A13,Transactions!$B:$B,"Expense",Transactions!$I:$I,$E13)) -> 383 | G13: =F13-C13 -> -27 | Q13: 400 | S13: =SUM(Q11:Q13) -> 4700
A14: Offerings | B14: 26 | C14: 165 | E14: 1 | F14: =IF($E14="","",SUMIFS(Transactions!$E:$E,Transactions!$C:$C,$A14,Transactions!$B:$B,"Expense",Transactions!$I:$I,$E14)) -> 140 | G14: =F14-C14 -> -25 | Q14: 3165 | S14: =S13-Q14 -> 1535 | T14: =S14/S13 -> 0.32659574
A15: Charity - Perez Uni | B15: 26 | C15: 50 | E15: 1 | F15: =IF($E15="","",SUMIFS(Transactions!$E:$E,Transactions!$C:$C,$A15,Transactions!$B:$B,"Expense",Transactions!$I:$I,$E15)) -> 50 | G15: =F15-C15 -> 0 | J15: 3163
A16: Charity - JPC Utilities | B16: 26 | C16: 100 | E16: 1 | F16: =IF($E16="","",SUMIFS(Transactions!$E:$E,Transactions!$C:$C,$A16,Transactions!$B:$B,"Expense",Transactions!$I:$I,$E16)) -> 100 | G16: =F16-C16 -> 0 | I16: 1104.62 | J16: 457.37 | K16: 130.68 | L16: =J16-K16 -> 326.69 | S16: 1050 | T16: =S16/S13 -> 0.22340426
A17: Savings Transfer | B17: 29 | C17: 1050 | E17: 1 | F17: =IF($E17="","",SUMIFS(Transactions!$E:$E,Transactions!$C:$C,$A17,Transactions!$B:$B,"Transfer",Transactions!$I:$I,$E17)) -> 0 | G17: =F17-C17 -> -1050 | J17: =SUM(J15:J16) -> 3620.37
A18: Laptop | B18: 29 | C18: 43 | E18: 1 | F18: =IF($E18="","",SUMIFS(Transactions!$E:$E,Transactions!$C:$C,$A18,Transactions!$B:$B,"Expense",Transactions!$I:$I,$E18)) -> 43 | G18: =F18-C18 -> 0 | J18: 3708 | S18: =S14-S16 -> 485
A19: House Keep | B19: 26 | C19: 560 | E19: 1 | F19: =IF($E19="","",SUMIFS(Transactions!$E:$E,Transactions!$C:$C,$A19,Transactions!$B:$B,"Expense",Transactions!$I:$I,$E19)) -> 129.97 | G19: =F19-C19 -> -430.03 | J19: =J18-J17 -> 87.63
A20: One-Off Giving (Christmas) | B20: 26 | C20: 500 | E20: 1 | F20: =IF($E20="","",SUMIFS(Transactions!$E:$E,Transactions!$C:$C,$A20,Transactions!$B:$B,"Expense",Transactions!$I:$I,$E20)) -> 457.37 | G20: =F20-C20 -> -42.63 | H20: One-Off
I21: =I16-J16+99 -> 746.25
I22: 550
I23: 111.62
I24: 32.09
I25: 25
A27: 735.39 | C27: Halifax | I27: =I21-SUM(I22:I25) -> 27.54
A28: =22.41+320 -> 342.41 | C28: Monzo
A29: =173.67+350.15+300+25.06 -> 848.88 | C29: Revolut
A30: 140

Sheet Budget by Period
A1: Budget vs Actual by Period (26th–25th) — auto from Transactions | B1: Items | D1: Budget | E1: Actuals | F1: Variance | G1: Budget | H1: Actuals | I1: Variance | J1: Budget | K1: Actuals | L1: Variance | M1: Budget | N1: Actuals | O1: Variance | P1: Budget | Q1: Actuals | R1: Variance | S1: Budget | T1: Actuals | U1: Variance | V1: Budget | W1: Actuals | X1: Variance | Y1: Budget | Z1: Actuals | AA1: Variance | AB1: Budget | AC1: Actuals | AD1: Variance | AE1: Budget | AF1: Actuals | AG1: Variance | AH1: Budget | AI1: Actuals | AJ1: Variance | AK1: Budget | AL1: Actuals | AM1: Variance
A2: INCOME | B2: Income - FM | C2: 3500 | D2: =$C2 -> 3500 | E2: =SUMIFS(Transactions!$E:$E,Transactions!$C:$C,$B2,Transactions!$B:$B,"Income",Transactions!$I:$I,1) -> 3700 | F2: =E2-D2 -> 200 | G2: =$C2 -> 3500 | H2: =SUMIFS(Transactions!$E:$E,Transactions!$C:$C,$B2,Transactions!$B:$B,"Income",Transactions!$I:$I,2) -> 0 | I2: =H2-G2 -> -3500 | J2: =$C2 -> 3500 | K2: =SUMIFS(Transactions!$E:$E,Transactions!$C:$C,$B2,Transactions!$B:$B,"Income",Transactions!$I:$I,3) -> 0 | L2: =K2-J2 -> -3500 | M2: =$C2 -> 3500 | N2: =SUMIFS(Transactions!$E:$E,Transactions!$C:$C,$B2,Transactions!$B:$B,"Income",Transactions!$I:$I,4) -> 0 | O2: =N2-M2 -> -3500 | P2: =$C2 -> 3500 | Q2: =SUMIFS(Transactions!$E:$E,Transactions!$C:$C,$B2,Transactions!$B:$B,"Income",Transactions!$I:$I,5) -> 0 | R2: =Q2-P2 -> -3500 | S2: =$C2 -> 3500 | T2: =SUMIFS(Transactions!$E:$E,Transactions!$C:$C,$B2,Transactions!$B:$B,"Income",Transactions!$I:$I,6) -> 0 | U2: =T2-S2 -> -3500 | V2: =$C2 -> 3500 | W2: =SUMIFS(Transactions!$E:$E,Transactions!$C:$C,$B2,Transactions!$B:$B,"Income",Transactions!$I:$I,7) -> 0 | X2: =W2-V2 -> -3500 | Y2: =$C2 -> 3500 | Z2: =SUMIFS(Transactions!$E:$E,Transactions!$C:$C,$B2,Transactions!$B:$B,"Income",Transactions!$I:$I,8) -> 0 | AA2: =Z2-Y2 -> -3500 | AB2: =$C2 -> 3500 | AC2: =SUMIFS(Transactions!$E:$E,Transactions!$C:$C,$B2,Transactions!$B:$B,"Income",Transactions!$I:$I,9) -> 0 | AD2: =AC2-AB2 -> -3500 | AE2: =$C2 -> 3500 | AF2: =SUMIFS(Transactions!$E:$E,Transactions!$C:$C,$B2,Transactions!$B:$B,"Income",Transactions!$I:$I,10) -> 0 | AG2: =AF2-AE2 -> -3500 | AH2: =$C2 -> 3500 | AI2: =SUMIFS(Transactions!$E:$E,Transactions!$C:$C,$B2,Transactions!$B:$B,"Income",Transactions!$I:$I,11) -> 0 | AJ2: =AI2-AH2 -> -3500 | AK2: =$C2 -> 3500 | AL2: =SUMIFS(Transactions!$E:$E,Transactions!$C:$C,$B2,Transactions!$B:$B,"Income",Transactions!$I:$I,12) -> 0 | AM2: =AL2-AK2 -> -3500
A3: INCOME | B3: Income - McD | C3: 800 | D3: =$C3 -> 800 | E3: =SUMIFS(Transactions!$E:$E,Transactions!$C:$C,$B3,Transactions!$B:$B,"Income",Transactions!$I:$I,1) -> 0 | F3: =E3-D3 -> -800 | G3: =$C3 -> 800 | H3: =SUMIFS(Transactions!$E:$E,Transactions!$C:$C,$B3,Transactions!$B:$B,"Income",Transactions!$I:$I,2) -> 0 | I3: =H3-G3 -> -800 | J3: =$C3 -> 800 | K3: =SUMIFS(Transactions!$E:$E,Transactions!$C:$C,$B3,Transactions!$B:$B,"Income",Transactions!$I:$I,3) -> 0 | L3: =K3-J3 -> -800 | M3: =$C3 -> 800 | N3: =SUMIFS(Transactions!$E:$E,Transactions!$C:$C,$B3,Transactions!$B:$B,"Income",Transactions!$I:$I,4) -> 0 | O3: =N3-M3 -> -800 | P3: =$C3 -> 800 | Q3: =SUMIFS(Transactions!$E:$E,Transactions!$C:$C,$B3,Transactions!$B:$B,"Income",Transactions!$I:$I,5) -> 0 | R3: =Q3-P3 -> -800 | S3: =$C3 -> 800 | T3: =SUMIFS(Transactions!$E:$E,Transactions!$C:$C,$B3,Transactions!$B:$B,"Income",Transactions!$I:$I,6) -> 0 | U3: =T3-S3 -> -800 | V3: =$C3 -> 800 | W3: =SUMIFS(Transactions!$E:$E,Transactions!$C:$C,$B3,Transactions!$B:$B,"Income",Transactions!$I:$I,7) -> 0 | X3: =W3-V3 -> -800 | Y3: =$C3 -> 800 | Z3: =SUMIFS(Transactions!$E:$E,Transactions!$C:$C,$B3,Transactions!$B:$B,"Income",Transactions!$I:$I,8) -> 0 | AA3: =Z3-Y3 -> -800 | AB3: =$C3 -> 800 | AC3: =SUMIFS(Transactions!$E:$E,Transactions!$C:$C,$B3,Transactions!$B:$B,"Income",Transactions!$I:$I,9) -> 0 | AD3: =AC3-AB3 -> -800 | AE3: =$C3 -> 800 | AF3: =SUMIFS(Transactions!$E:$E,Transactions!$C:$C,$B3,Transactions!$B:$B,"Income",Transactions!$I:$I,10) -> 0 | AG3: =AF3-AE3 -> -800 | AH3: =$C3 -> 800 | AI3: =SUMIFS(Transactions!$E:$E,Transactions!$C:$C,$B3,Transactions!$B:$B,"Income",Transactions!$I:$I,11) -> 0 | AJ3: =AI3-AH3 -> -800 | AK3: =$C3 -> 800 | AL3: =SUMIFS(Transactions!$E:$E,Transactions!$C:$C,$B3,Transactions!$B:$B,"Income",Transactions!$I:$I,12) -> 0 | AM3: =AL3-AK3 -> -800
A4: INCOME | B4: Income - Outlier | C4: 400 | D4: =$C4 -> 400 | E4: =SUMIFS(Transactions!$E:$E,Transactions!$C:$C,$B4,Transactions!$B:$B,"Income",Transactions!$I:$I,1) -> 111.48 | F4: =E4-D4 -> -288.52 | G4: =$C4 -> 400 | H4: =SUMIFS(Transactions!$E:$E,Transactions!$C:$C,$B4,Transactions!$B:$B,"Income",Transactions!$I:$I,2) -> 0 | I4: =H4-G4 -> -400 | J4: =$C4 -> 400 | K4: =SUMIFS(Transactions!$E:$E,Transactions!$C:$C,$B4,Transactions!$B:$B,"Income",Transactions!$I:$I,3) -> 0 | L4: =K4-J4 -> -400 | M4: =$C4 -> 400 | N4: =SUMIFS(Transactions!$E:$E,Transactions!$C:$C,$B4,Transactions!$B:$B,"Income",Transactions!$I:$I,4) -> 0 | O4: =N4-M4 -> -400 | P4: =$C4 -> 400 | Q4: =SUMIFS(Transactions!$E:$E,Transactions!$C:$C,$B4,Transactions!$B:$B,"Income",Transactions!$I:$I,5) -> 0 | R4: =Q4-P4 -> -400 | S4: =$C4 -> 400 | T4: =SUMIFS(Transactions!$E:$E,Transactions!$C:$C,$B4,Transactions!$B:$B,"Income",Transactions!$I:$I,6) -> 0 | U4: =T4-S4 -> -400 | V4: =$C4 -> 400 | W4: =SUMIFS(Transactions!$E:$E,Transactions!$C:$C,$B4,Transactions!$B:$B,"Income",Transactions!$I:$I,7) -> 0 | X4: =W4-V4 -> -400 | Y4: =$C4 -> 400 | Z4: =SUMIFS(Transactions!$E:$E,Transactions!$C:$C,$B4,Transactions!$B:$B,"Income",Transactions!$I:$I,8) -> 0 | AA4: =Z4-Y4 -> -400 | AB4: =$C4 -> 400 | AC4: =SUMIFS(Transactions!$E:$E,Transactions!$C:$C,$B4,Transactions!$B:$B,"Income",Transactions!$I:$I,9) -> 0 | AD4: =AC4-AB4 -> -400 | AE4: =$C4 -> 400 | AF4: =SUMIFS(Transactions!$E:$E,Transactions!$C:$C,$B4,Transactions!$B:$B,"Income",Transactions!$I:$I,10) -> 0 | AG4: =AF4-AE4 -> -400 | AH4: =$C4 -> 400 | AI4: =SUMIFS(Transactions!$E:$E,Transactions!$C:$C,$B4,Transactions!$B:$B,"Income",Transactions!$I:$I,11) -> 0 | AJ4: =AI4-AH4 -> -400 | AK4: =$C4 -> 400 | AL4: =SUMIFS(Transactions!$E:$E,Transactions!$C:$C,$B4,Transactions!$B:$B,"Income",Transactions!$I:$I,12) -> 0 | AM4: =AL4-AK4 -> -400
A5: GIVING | B5: Tithe | C5: 410 | D5: =$C5 -> 410 | E5: =SUMIFS(Transactions!$E:$E,Transactions!$C:$C,$B5,Transactions!$B:$B,"Expense",Transactions!$I:$I,1) -> 383 | F5: =E5-D5 -> -27 | G5: =$C5 -> 410 | H5: =SUMIFS(Transactions!$E:$E,Transactions!$C:$C,$B5,Transactions!$B:$B,"Expense",Transactions!$I:$I,2) -> 0 | I5: =H5-G5 -> -410 | J5: =$C5 -> 410 | K5: =SUMIFS(Transactions!$E:$E,Transactions!$C:$C,$B5,Transactions!$B:$B,"Expense",Transactions!$I:$I,3) -> 0 | L5: =K5-J5 -> -410 | M5: =$C5 -> 410 | N5: =SUMIFS(Transactions!$E:$E,Transactions!$C:$C,$B5,Transactions!$B:$B,"Expense",Transactions!$I:$I,4) -> 0 | O5: =N5-M5 -> -410 | P5: =$C5 -> 410 | Q5: =SUMIFS(Transactions!$E:$E,Transactions!$C:$C,$B5,Transactions!$B:$B,"Expense",Transactions!$I:$I,5) -> 0 | R5: =Q5-P5 -> -410 | S5: =$C5 -> 410 | T5: =SUMIFS(Transactions!$E:$E,Transactions!$C:$C,$B5,Transactions!$B:$B,"Expense",Transactions!$I:$I,6) -> 0 | U5: =T5-S5 -> -410 | V5: =$C5 -> 410 | W5: =SUMIFS(Transactions!$E:$E,Transactions!$C:$C,$B5,Transactions!$B:$B,"Expense",Transactions!$I:$I,7) -> 0 | X5: =W5-V5 -> -410 | Y5: =$C5 -> 410 | Z5: =SUMIFS(Transactions!$E:$E,Transactions!$C:$C,$B5,Transactions!$B:$B,"Expense",Transactions!$I:$I,8) -> 0 | AA5: =Z5-Y5 -> -410 | AB5: =$C5 -> 410 | AC5: =SUMIFS(Transactions!$E:$E,Transactions!$C:$C,$B5,Transactions!$B:$B,"Expense",Transactions!$I:$I,9) -> 0 | AD5: =AC5-AB5 -> -410 | AE5: =$C5 -> 410 | AF5: =SUMIFS(Transactions!$E:$E,Transactions!$C:$C,$B5,Transactions!$B:$B,"Expense",Transactions!$I:$I,10) -> 0 | AG5: =AF5-AE5 -> -410 | AH5: =$C5 -> 410 | AI5: =SUMIFS(Transactions!$E:$E,Transactions!$C:$C,$B5,Transactions!$B:$B,"Expense",Transactions!$I:$I,11) -> 0 | AJ5: =AI5-AH5 -> -410 | AK5: =$C5 -> 410 | AL5: =SUMIFS(Transactions!$E:$E,Transactions!$C:$C,$B5,Transactions!$B:$B,"Expense",Transactions!$I:$I,12) -> 0 | AM5: =AL5-AK5 -> -410
A6: GIVING | B6: Offerings | C6: 165 | D6: =$C6 -> 165 | E6: =SUMIFS(Transactions!$E:$E,Transactions!$C:$C,$B6,Transactions!$B:$B,"Expense",Transactions!$I:$I,1) -> 140 | F6: =E6-D6 -> -25 | G6: =$C6 -> 165 | H6: =SUMIFS(Transactions!$E:$E,Transactions!$C:$C,$B6,Transactions!$B:$B,"Expense",Transactions!$I:$I,2) -> 0 | I6: =H6-G6 -> -165 | J6: =$C6 -> 165 | K6: =SUMIFS(Transactions!$E:$E,Transactions!$C:$C,$B6,Transactions!$B:$B,"Expense",Transactions!$I:$I,3) -> 0 | L6: =K6-J6 -> -165 | M6: =$C6 -> 165 | N6: =SUMIFS(Transactions!$E:$E,Transactions!$C:$C,$B6,Transactions!$B:$B,"Expense",Transactions!$I:$I,4) -> 0 | O6: =N6-M6 -> -165 | P6: =$C6 -> 165 | Q6: =SUMIFS(Transactions!$E:$E,Transactions!$C:$C,$B6,Transactions!$B:$B,"Expense",Transactions!$I:$I,5) -> 0 | R6: =Q6-P6 -> -165 | S6: =$C6 -> 165 | T6: =SUMIFS(Transactions!$E:$E,Transactions!$C:$C,$B6,Transactions!$B:$B,"Expense",Transactions!$I:$I,6) -> 0 | U6: =T6-S6 -> -165 | V6: =$C6 -> 165 | W6: =SUMIFS(Transactions!$E:$E,Transactions!$C:$C,$B6,Transactions!$B:$B,"Expense",Transactions!$I:$I,7) -> 0 | X6: =W6-V6 -> -165 | Y6: =$C6 -> 165 | Z6: =SUMIFS(Transactions!$E:$E,Transactions!$C:$C,$B6,Transactions!$B:$B,"Expense",Transactions!$I:$I,8) -> 0 | AA6: =Z6-Y6 -> -165 | AB6: =$C6 -> 165 | AC6: =SUMIFS(Transactions!$E:$E,Transactions!$C:$C,$B6,Transactions!$B:$B,"Expense",Transactions!$I:$I,9) -> 0 | AD6: =AC6-AB6 -> -165 | AE6: =$C6 -> 165 | AF6: =SUMIFS(Transactions!$E:$E,Transactions!$C:$C,$B6,Transactions!$B:$B,"Expense",Transactions!$I:$I,10) -> 0 | AG6: =AF6-AE6 -> -165 | AH6: =$C6 -> 165 | AI6: =SUMIFS(Transactions!$E:$E,Transactions!$C:$C,$B6,Transactions!$B:$B,"Expense",Transactions!$I:$I,11) -> 0 | AJ6: =AI6-AH6 -> -165 | AK6: =$C6 -> 165 | AL6: =SUMIFS(Transactions!$E:$E,Transactions!$C:$C,$B6,Transactions!$B:$B,"Expense",Transactions!$I:$I,12) -> 0 | AM6: =AL6-AK6 -> -165
A7: GIVING | B7: Charity - Perez Uni | C7: 50 | D7: =$C7 -> 50 | E7: =SUMIFS(Transactions!$E:$E,Transactions!$C:$C,$B7,Transactions!$B:$B,"Expense",Transactions!$I:$I,1) -> 50 | F7: =E7-D7 -> 0 | G7: =$C7 -> 50 | H7: =SUMIFS(Transactions!$E:$E,Transactions!$C:$C,$B7,Transactions!$B:$B,"Expense",Transactions!$I:$I,2) -> 0 | I7: =H7-G7 -> -50 | J7: =$C7 -> 50 | K7: =SUMIFS(Transactions!$E:$E,Transactions!$C:$C,$B7,Transactions!$B:$B,"Expense",Transactions!$I:$I,3) -> 0 | L7: =K7-J7 -> -50 | M7: =$C7 -> 50 | N7: =SUMIFS(Transactions!$E:$E,Transactions!$C:$C,$B7,Transactions!$B:$B,"Expense",Transactions!$I:$I,4) -> 0 | O7: =N7-M7 -> -50 | P7: =$C7 -> 50 | Q7: =SUMIFS(Transactions!$E:$E,Transactions!$C:$C,$B7,Transactions!$B:$B,"Expense",Transactions!$I:$I,5) -> 0 | R7: =Q7-P7 -> -50 | S7: =$C7 -> 50 | T7: =SUMIFS(Transactions!$E:$E,Transactions!$C:$C,$B7,Transactions!$B:$B,"Expense",Transactions!$I:$I,6) -> 0 | U7: =T7-S7 -> -50 | V7: =$C7 -> 50 | W7: =SUMIFS(Transactions!$E:$E,Transactions!$C:$C,$B7,Transactions!$B:$B,"Expense",Transactions!$I:$I,7) -> 0 | X7: =W7-V7 -> -50 | Y7: =$C7 -> 50 | Z7: =SUMIFS(Transactions!$E:$E,Transactions!$C:$C,$B7,Transactions!$B:$B,"Expense",Transactions!$I:$I,8) -> 0 | AA7: =Z7-Y7 -> -50 | AB7: =$C7 -> 50 | AC7: =SUMIFS(Transactions!$E:$E,Transactions!$C:$C,$B7,Transactions!$B:$B,"Expense",Transactions!$I:$I,9) -> 0 | AD7: =AC7-AB7 -> -50 | AE7: =$C7 -> 50 | AF7: =SUMIFS(Transactions!$E:$E,Transactions!$C:$C,$B7,Transactions!$B:$B,"Expense",Transactions!$I:$I,10) -> 0 | AG7: =AF7-AE7 -> -50 | AH7: =$C7 -> 50 | AI7: =SUMIFS(Transactions!$E:$E,Transactions!$C:$C,$B7,Transactions!$B:$B,"Expense",Transactions!$I:$I,11) -> 0 | AJ7: =AI7-AH7 -> -50 | AK7: =$C7 -> 50 | AL7: =SUMIFS(Transactions!$E:$E,Transactions!$C:$C,$B7,Transactions!$B:$B,"Expense",Transactions!$I:$I,12) -> 0 | AM7: =AL7-AK7 -> -50
A8: GIVING | B8: Charity - JPC Utilities | C8: 100 | D8: =$C8 -> 100 | E8: =SUMIFS(Transactions!$E:$E,Transactions!$C:$C,$B8,Transactions!$B:$B,"Expense",Transactions!$I:$I,1) -> 100 | F8: =E8-D8 -> 0 | G8: =$C8 -> 100 | H8: =SUMIFS(Transactions!$E:$E,Transactions!$C:$C,$B8,Transactions!$B:$B,"Expense",Transactions!$I:$I,2) -> 0 | I8: =H8-G8 -> -100 | J8: =$C8 -> 100 | K8: =SUMIFS(Transactions!$E:$E,Transactions!$C:$C,$B8,Transactions!$B:$B,"Expense",Transactions!$I:$I,3) -> 0 | L8: =K8-J8 -> -100 | M8: =$C8 -> 100 | N8: =SUMIFS(Transactions!$E:$E,Transactions!$C:$C,$B8,Transactions!$B:$B,"Expense",Transactions!$I:$I,4) -> 0 | O8: =N8-M8 -> -100 | P8: =$C8 -> 100 | Q8: =SUMIFS(Transactions!$E:$E,Transactions!$C:$C,$B8,Transactions!$B:$B,"Expense",Transactions!$I:$I,5) -> 0 | R8: =Q8-P8 -> -100 | S8: =$C8 -> 100 | T8: =SUMIFS(Transactions!$E:$E,Transactions!$C:$C,$B8,Transactions!$B:$B,"Expense",Transactions!$I:$I,6) -> 0 | U8: =T8-S8 -> -100 | V8: =$C8 -> 100 | W8: =SUMIFS(Transactions!$E:$E,Transactions!$C:$C,$B8,Transactions!$B:$B,"Expense",Transactions!$I:$I,7) -> 0 | X8: =W8-V8 -> -100 | Y8: =$C8 -> 100 | Z8: =SUMIFS(Transactions!$E:$E,Transactions!$C:$C,$B8,Transactions!$B:$B,"Expense",Transactions!$I:$I,8) -> 0 | AA8: =Z8-Y8 -> -100 | AB8: =$C8 -> 100 | AC8: =SUMIFS(Transactions!$E:$E,Transactions!$C:$C,$B8,Transactions!$B:$B,"Expense",Transactions!$I:$I,9) -> 0 | AD8: =AC8-AB8 -> -100 | AE8: =$C8 -> 100 | AF8: =SUMIFS(Transactions!$E:$E,Transactions!$C:$C,$B8,Transactions!$B:$B,"Expense",Transactions!$I:$I,10) -> 0 | AG8: =AF8-AE8 -> -100 | AH8: =$C8 -> 100 | AI8: =SUMIFS(Transactions!$E:$E,Transactions!$C:$C,$B8,Transactions!$B:$B,"Expense",Transactions!$I:$I,11) -> 0 | AJ8: =AI8-AH8 -> -100 | AK8: =$C8 -> 100 | AL8: =SUMIFS(Transactions!$E:$E,Transactions!$C:$C,$B8,Transactions!$B:$B,"Expense",Transactions!$I:$I,12) -> 0 | AM8: =AL8-AK8 -> -100
A9: GIVING | B9: Donations (Variable) | C9: 90 | D9: =$C9 -> 90 | E9: =SUMIFS(Transactions!$E:$E,Transactions!$C:$C,$B9,Transactions!$B:$B,"Expense",Transactions!$I:$I,1) -> 34 | F9: =E9-D9 -> -56 | G9: =$C9 -> 90 | H9: =SUMIFS(Transactions!$E:$E,Transactions!$C:$C,$B9,Transactions!$B:$B,"Expense",Transactions!$I:$I,2) -> 0 | I9: =H9-G9 -> -90 | J9: =$C9 -> 90 | K9: =SUMIFS(Transactions!$E:$E,Transactions!$C:$C,$B9,Transactions!$B:$B,"Expense",Transactions!$I:$I,3) -> 0 | L9: =K9-J9 -> -90 | M9: =$C9 -> 90 | N9: =SUMIFS(Transactions!$E:$E,Transactions!$C:$C,$B9,Transactions!$B:$B,"Expense",Transactions!$I:$I,4) -> 0 | O9: =N9-M9 -> -90 | P9: =$C9 -> 90 | Q9: =SUMIFS(Transactions!$E:$E,Transactions!$C:$C,$B9,Transactions!$B:$B,"Expense",Transactions!$I:$I,5) -> 0 | R9: =Q9-P9 -> -90 | S9: =$C9 -> 90 | T9: =SUMIFS(Transactions!$E:$E,Transactions!$C:$C,$B9,Transactions!$B:$B,"Expense",Transactions!$I:$I,6) -> 0 | U9: =T9-S9 -> -90 | V9: =$C9 -> 90 | W9: =SUMIFS(Transactions!$E:$E,Transactions!$C:$C,$B9,Transactions!$B:$B,"Expense",Transactions!$I:$I,7) -> 0 | X9: =W9-V9 -> -90 | Y9: =$C9 -> 90 | Z9: =SUMIFS(Transactions!$E:$E,Transactions!$C:$C,$B9,Transactions!$B:$B,"Expense",Transactions!$I:$I,8) -> 0 | AA9: =Z9-Y9 -> -90 | AB9: =$C9 -> 90 | AC9: =SUMIFS(Transactions!$E:$E,Transactions!$C:$C,$B9,Transactions!$B:$B,"Expense",Transactions!$I:$I,9) -> 0 | AD9: =AC9-AB9 -> -90 | AE9: =$C9 -> 90 | AF9: =SUMIFS(Transactions!$E:$E,Transactions!$C:$C,$B9,Transactions!$B:$B,"Expense",Transactions!$I:$I,10) -> 0 | AG9: =AF9-AE9 -> -90 | AH9: =$C9 -> 90 | AI9: =SUMIFS(Transactions!$E:$E,Transactions!$C:$C,$B9,Transactions!$B:$B,"Expense",Transactions!$I:$I,11) -> 0 | AJ9: =AI9-AH9 -> -90 | AK9: =$C9 -> 90 | AL9: =SUMIFS(Transactions!$E:$E,Transactions!$C:$C,$B9,Transactions!$B:$B,"Expense",Transactions!$I:$I,12) -> 0 | AM9: =AL9-AK9 -> -90
A10: FIXED | B10: Rent | C10: 550 | D10: =$C10 -> 550 | E10: =SUMIFS(Transactions!$E:$E,Transactions!$C:$C,$B10,Transactions!$B:$B,"Expense",Transactions!$I:$I,1) -> 0 | F10: =E10-D10 -> -550 | G10: =$C10 -> 550 | H10: =SUMIFS(Transactions!$E:$E,Transactions!$C:$C,$B10,Transactions!$B:$B,"Expense",Transactions!$I:$I,2) -> 0 | I10: =H10-G10 -> -550 | J10: =$C10 -> 550 | K10: =SUMIFS(Transactions!$E:$E,Transactions!$C:$C,$B10,Transactions!$B:$B,"Expense",Transactions!$I:$I,3) -> 0 | L10: =K10-J10 -> -550 | M10: =$C10 -> 550 | N10: =SUMIFS(Transactions!$E:$E,Transactions!$C:$C,$B10,Transactions!$B:$B,"Expense",Transactions!$I:$I,4) -> 0 | O10: =N10-M10 -> -550 | P10: =$C10 -> 550 | Q10: =SUMIFS(Transactions!$E:$E,Transactions!$C:$C,$B10,Transactions!$B:$B,"Expense",Transactions!$I:$I,5) -> 0 | R10: =Q10-P10 -> -550 | S10: =$C10 -> 550 | T10: =SUMIFS(Transactions!$E:$E,Transactions!$C:$C,$B10,Transactions!$B:$B,"Expense",Transactions!$I:$I,6) -> 0 | U10: =T10-S10 -> -550 | V10: =$C10 -> 550 | W10: =SUMIFS(Transactions!$E:$E,Transactions!$C:$C,$B10,Transactions!$B:$B,"Expense",Transactions!$I:$I,7) -> 0 | X10: =W10-V10 -> -550 | Y10: =$C10 -> 550 | Z10: =SUMIFS(Transactions!$E:$E,Transactions!$C:$C,$B10,Transactions!$B:$B,"Expense",Transactions!$I:$I,8) -> 0 | AA10: =Z10-Y10 -> -550 | AB10: =$C10 -> 550 | AC10: =SUMIFS(Transactions!$E:$E,Transactions!$C:$C,$B10,Transactions!$B:$B,"Expense",Transactions!$I:$I,9) -> 0 | AD10: =AC10-AB10 -> -550 | AE10: =$C10 -> 550 | AF10: =SUMIFS(Transactions!$E:$E,Transactions!$C:$C,$B10,Transactions!$B:$B,"Expense",Transactions!$I:$I,10) -> 0 | AG10: =AF10-AE10 -> -550 | AH10: =$C10 -> 550 | AI10: =SUMIFS(Transactions!$E:$E,Transactions!$C:$C,$B10,Transactions!$B:$B,"Expense",Transactions!$I:$I,11) -> 0 | AJ10: =AI10-AH10 -> -550 | AK10: =$C10 -> 550 | AL10: =SUMIFS(Transactions!$E:$E,Transactions!$C:$C,$B10,Transactions!$B:$B,"Expense",Transactions!$I:$I,12) -> 0 | AM10: =AL10-AK10 -> -550
A11: FIXED | B11: Insurance | C11: 175 | D11: =$C11 -> 175 | E11: =SUMIFS(Transactions!$E:$E,Transactions!$C:$C,$B11,Transactions!$B:$B,"Expense",Transactions!$I:$I,1) -> 0 | F11: =E11-D11 -> -175 | G11: =$C11 -> 175 | H11: =SUMIFS(Transactions!$E:$E,Transactions!$C:$C,$B11,Transactions!$B:$B,"Expense",Transactions!$I:$I,2) -> 0 | I11: =H11-G11 -> -175 | J11: =$C11 -> 175 | K11: =SUMIFS(Transactions!$E:$E,Transactions!$C:$C,$B11,Transactions!$B:$B,"Expense",Transactions!$I:$I,3) -> 0 | L11: =K11-J11 -> -175 | M11: =$C11 -> 175 | N11: =SUMIFS(Transactions!$E:$E,Transactions!$C:$C,$B11,Transactions!$B:$B,"Expense",Transactions!$I:$I,4) -> 0 | O11: =N11-M11 -> -175 | P11: =$C11 -> 175 | Q11: =SUMIFS(Transactions!$E:$E,Transactions!$C:$C,$B11,Transactions!$B:$B,"Expense",Transactions!$I:$I,5) -> 0 | R11: =Q11-P11 -> -175 | S11: =$C11 -> 175 | T11: =SUMIFS(Transactions!$E:$E,Transactions!$C:$C,$B11,Transactions!$B:$B,"Expense",Transactions!$I:$I,6) -> 0 | U11: =T11-S11 -> -175 | V11: =$C11 -> 175 | W11: =SUMIFS(Transactions!$E:$E,Transactions!$C:$C,$B11,Transactions!$B:$B,"Expense",Transactions!$I:$I,7) -> 0 | X11: =W11-V11 -> -175 | Y11: =$C11 -> 175 | Z11: =SUMIFS(Transactions!$E:$E,Transactions!$C:$C,$B11,Transactions!$B:$B,"Expense",Transactions!$I:$I,8) -> 0 | AA11: =Z11-Y11 -> -175 | AB11: =$C11 -> 175 | AC11: =SUMIFS(Transactions!$E:$E,Transactions!$C:$C,$B11,Transactions!$B:$B,"Expense",Transactions!$I:$I,9) -> 0 | AD11: =AC11-AB11 -> -175 | AE11: =$C11 -> 175 | AF11: =SUMIFS(Transactions!$E:$E,Transactions!$C:$C,$B11,Transactions!$B:$B,"Expense",Transactions!$I:$I,10) -> 0 | AG11: =AF11-AE11 -> -175 | AH11: =$C11 -> 175 | AI11: =SUMIFS(Transactions!$E:$E,Transactions!$C:$C,$B11,Transactions!$B:$B,"Expense",Transactions!$I:$I,11) -> 0 | AJ11: =AI11-AH11 -> -175 | AK11: =$C11 -> 175 | AL11: =SUMIFS(Transactions!$E:$E,Transactions!$C:$C,$B11,Transactions!$B:$B,"Expense",Transactions!$I:$I,12) -> 0 | AM11: =AL11-AK11 -> -175
A12: FIXED | B12: Road Tax | C12: 34 | D12: =$C12 -> 34 | E12: =SUMIFS(Transactions!$E:$E,Transactions!$C:$C,$B12,Transactions!$B:$B,"Expense",Transactions!$I:$I,1) -> 0 | F12: =E12-D12 -> -34 | G12: =$C12 -> 34 | H12: =SUMIFS(Transactions!$E:$E,Transactions!$C:$C,$B12,Transactions!$B:$B,"Expense",Transactions!$I:$I,2) -> 0 | I12: =H12-G12 -> -34 | J12: =$C12 -> 34 | K12: =SUMIFS(Transactions!$E:$E,Transactions!$C:$C,$B12,Transactions!$B:$B,"Expense",Transactions!$I:$I,3) -> 0 | L12: =K12-J12 -> -34 | M12: =$C12 -> 34 | N12: =SUMIFS(Transactions!$E:$E,Transactions!$C:$C,$B12,Transactions!$B:$B,"Expense",Transactions!$I:$I,4) -> 0 | O12: =N12-M12 -> -34 | P12: =$C12 -> 34 | Q12: =SUMIFS(Transactions!$E:$E,Transactions!$C:$C,$B12,Transactions!$B:$B,"Expense",Transactions!$I:$I,5) -> 0 | R12: =Q12-P12 -> -34 | S12: =$C12 -> 34 | T12: =SUMIFS(Transactions!$E:$E,Transactions!$C:$C,$B12,Transactions!$B:$B,"Expense",Transactions!$I:$I,6) -> 0 | U12: =T12-S12 -> -34 | V12: =$C12 -> 34 | W12: =SUMIFS(Transactions!$E:$E,Transactions!$C:$C,$B12,Transactions!$B:$B,"Expense",Transactions!$I:$I,7) -> 0 | X12: =W12-V12 -> -34 | Y12: =$C12 -> 34 | Z12: =SUMIFS(Transactions!$E:$E,Transactions!$C:$C,$B12,Transactions!$B:$B,"Expense",Transactions!$I:$I,8) -> 0 | AA12: =Z12-Y12 -> -34 | AB12: =$C12 -> 34 | AC12: =SUMIFS(Transactions!$E:$E,Transactions!$C:$C,$B12,Transactions!$B:$B,"Expense",Transactions!$I:$I,9) -> 0 | AD12: =AC12-AB12 -> -34 | AE12: =$C12 -> 34 | AF12: =SUMIFS(Transactions!$E:$E,Transactions!$C:$C,$B12,Transactions!$B:$B,"Expense",Transactions!$I:$I,10) -> 0 | AG12: =AF12-AE12 -> -34 | AH12: =$C12 -> 34 | AI12: =SUMIFS(Transactions!$E:$E,Transactions!$C:$C,$B12,Transactions!$B:$B,"Expense",Transactions!$I:$I,11) -> 0 | AJ12: =AI12-AH12 -> -34 | AK12: =$C12 -> 34 | AL12: =SUMIFS(Transactions!$E:$E,Transactions!$C:$C,$B12,Transactions!$B:$B,"Expense",Transactions!$I:$I,12) -> 0 | AM12: =AL12-AK12 -> -34
A13: FIXED | B13: Water Bill | C13: 93 | D13: =$C13 -> 93 | E13: =SUMIFS(Transactions!$E:$E,Transactions!$C:$C,$B13,Transactions!$B:$B,"Expense",Transactions!$I:$I,1) -> 92.77 | F13: =E13-D13 -> -0.23 | G13: =$C13 -> 93 | H13: =SUMIFS(Transactions!$E:$E,Transactions!$C:$C,$B13,Transactions!$B:$B,"Expense",Transactions!$I:$I,2) -> 0 | I13: =H13-G13 -> -93 | J13: =$C13 -> 93 | K13: =SUMIFS(Transactions!$E:$E,Transactions!$C:$C,$B13,Transactions!$B:$B,"Expense",Transactions!$I:$I,3) -> 0 | L13: =K13-J13 -> -93 | M13: =$C13 -> 93 | N13: =SUMIFS(Transactions!$E:$E,Transactions!$C:$C,$B13,Transactions!$B:$B,"Expense",Transactions!$I:$I,4) -> 0 | O13: =N13-M13 -> -93 | P13: =$C13 -> 93 | Q13: =SUMIFS(Transactions!$E:$E,Transactions!$C:$C,$B13,Transactions!$B:$B,"Expense",Transactions!$I:$I,5) -> 0 | R13: =Q13-P13 -> -93 | S13: =$C13 -> 93 | T13: =SUMIFS(Transactions!$E:$E,Transactions!$C:$C,$B13,Transactions!$B:$B,"Expense",Transactions!$I:$I,6) -> 0 | U13: =T13-S13 -> -93 | V13: =$C13 -> 93 | W13: =SUMIFS(Transactions!$E:$E,Transactions!$C:$C,$B13,Transactions!$B:$B,"Expense",Transactions!$I:$I,7) -> 0 | X13: =W13-V13 -> -93 | Y13: =$C13 -> 93 | Z13: =SUMIFS(Transactions!$E:$E,Transactions!$C:$C,$B13,Transactions!$B:$B,"Expense",Transactions!$I:$I,8) -> 0 | AA13: =Z13-Y13 -> -93 | AB13: =$C13 -> 93 | AC13: =SUMIFS(Transactions!$E:$E,Transactions!$C:$C,$B13,Transactions!$B:$B,"Expense",Transactions!$I:$I,9) -> 0 | AD13: =AC13-AB13 -> -93 | AE13: =$C13 -> 93 | AF13: =SUMIFS(Transactions!$E:$E,Transactions!$C:$C,$B13,Transactions!$B:$B,"Expense",Transactions!$I:$I,10) -> 0 | AG13: =AF13-AE13 -> -93 | AH13: =$C13 -> 93 | AI13: =SUMIFS(Transactions!$E:$E,Transactions!$C:$C,$B13,Transactions!$B:$B,"Expense",Transactions!$I:$I,11) -> 0 | AJ13: =AI13-AH13 -> -93 | AK13: =$C13 -> 93 | AL13: =SUMIFS(Transactions!$E:$E,Transactions!$C:$C,$B13,Transactions!$B:$B,"Expense",Transactions!$I:$I,12) -> 0 | AM13: =AL13-AK13 -> -93
A14: FIXED | B14: Electricity & Gas | C14: 200 | D14: =$C14 -> 200 | E14: =SUMIFS(Transactions!$E:$E,Transactions!$C:$C,$B14,Transactions!$B:$B,"Expense",Transactions!$I:$I,1) -> 50 | F14: =E14-D14 -> -150 | G14: =$C14 -> 200 | H14: =SUMIFS(Transactions!$E:$E,Transactions!$C:$C,$B14,Transactions!$B:$B,"Expense",Transactions!$I:$I,2) -> 0 | I14: =H14-G14 -> -200 | J14: =$C14 -> 200 | K14: =SUMIFS(Transactions!$E:$E,Transactions!$C:$C,$B14,Transactions!$B:$B,"Expense",Transactions!$I:$I,3) -> 0 | L14: =K14-J14 -> -200 | M14: =$C14 -> 200 | N14: =SUMIFS(Transactions!$E:$E,Transactions!$C:$C,$B14,Transactions!$B:$B,"Expense",Transactions!$I:$I,4) -> 0 | O14: =N14-M14 -> -200 | P14: =$C14 -> 200 | Q14: =SUMIFS(Transactions!$E:$E,Transactions!$C:$C,$B14,Transactions!$B:$B,"Expense",Transactions!$I:$I,5) -> 0 | R14: =Q14-P14 -> -200 | S14: =$C14 -> 200 | T14: =SUMIFS(Transactions!$E:$E,Transactions!$C:$C,$B14,Transactions!$B:$B,"Expense",Transactions!$I:$I,6) -> 0 | U14: =T14-S14 -> -200 | V14: =$C14 -> 200 | W14: =SUMIFS(Transactions!$E:$E,Transactions!$C:$C,$B14,Transactions!$B:$B,"Expense",Transactions!$I:$I,7) -> 0 | X14: =W14-V14 -> -200 | Y14: =$C14 -> 200 | Z14: =SUMIFS(Transactions!$E:$E,Transactions!$C:$C,$B14,Transactions!$B:$B,"Expense",Transactions!$I:$I,8) -> 0 | AA14: =Z14-Y14 -> -200 | AB14: =$C14 -> 200 | AC14: =SUMIFS(Transactions!$E:$E,Transactions!$C:$C,$B14,Transactions!$B:$B,"Expense",Transactions!$I:$I,9) -> 0 | AD14: =AC14-AB14 -> -200 | AE14: =$C14 -> 200 | AF14: =SUMIFS(Transactions!$E:$E,Transactions!$C:$C,$B14,Transactions!$B:$B,"Expense",Transactions!$I:$I,10) -> 0 | AG14: =AF14-AE14 -> -200 | AH14: =$C14 -> 200 | AI14: =SUMIFS(Transactions!$E:$E,Transactions!$C:$C,$B14,Transactions!$B:$B,"Expense",Transactions!$I:$I,11) -> 0 | AJ14: =AI14-AH14 -> -200 | AK14: =$C14 -> 200 | AL14: =SUMIFS(Transactions!$E:$E,Transactions!$C:$C,$B14,Transactions!$B:$B,"Expense",Transactions!$I:$I,12) -> 0 | AM14: =AL14-AK14 -> -200
A15: FIXED | B15: Community Fibre / Internet | C15: 37 | D15: =$C15 -> 37 | E15: =SUMIFS(Transactions!$E:$E,Transactions!$C:$C,$B15,Transactions!$B:$B,"Expense",Transactions!$I:$I,1) -> 36.83 | F15: =E15-D15 -> -0.17 | G15: =$C15 -> 37 | H15: =SUMIFS(Transactions!$E:$E,Transactions!$C:$C,$B15,Transactions!$B:$B,"Expense",Transactions!$I:$I,2) -> 0 | I15: =H15-G15 -> -37 | J15: =$C15 -> 37 | K15: =SUMIFS(Transactions!$E:$E,Transactions!$C:$C,$B15,Transactions!$B:$B,"Expense",Transactions!$I:$I,3) -> 0 | L15: =K15-J15 -> -37 | M15: =$C15 -> 37 | N15: =SUMIFS(Transactions!$E:$E,Transactions!$C:$C,$B15,Transactions!$B:$B,"Expense",Transactions!$I:$I,4) -> 0 | O15: =N15-M15 -> -37 | P15: =$C15 -> 37 | Q15: =SUMIFS(Transactions!$E:$E,Transactions!$C:$C,$B15,Transactions!$B:$B,"Expense",Transactions!$I:$I,5) -> 0 | R15: =Q15-P15 -> -37 | S15: =$C15 -> 37 | T15: =SUMIFS(Transactions!$E:$E,Transactions!$C:$C,$B15,Transactions!$B:$B,"Expense",Transactions!$I:$I,6) -> 0 | U15: =T15-S15 -> -37 | V15: =$C15 -> 37 | W15: =SUMIFS(Transactions!$E:$E,Transactions!$C:$C,$B15,Transactions!$B:$B,"Expense",Transactions!$I:$I,7) -> 0 | X15: =W15-V15 -> -37 | Y15: =$C15 -> 37 | Z15: =SUMIFS(Transactions!$E:$E,Transactions!$C:$C,$B15,Transactions!$B:$B,"Expense",Transactions!$I:$I,8) -> 0 | AA15: =Z15-Y15 -> -37 | AB15: =$C15 -> 37 | AC15: =SUMIFS(Transactions!$E:$E,Transactions!$C:$C,$B15,Transactions!$B:$B,"Expense",Transactions!$I:$I,9) -> 0 | AD15: =AC15-AB15 -> -37 | AE15: =$C15 -> 37 | AF15: =SUMIFS(Transactions!$E:$E,Transactions!$C:$C,$B15,Transactions!$B:$B,"Expense",Transactions!$I:$I,10) -> 0 | AG15: =AF15-AE15 -> -37 | AH15: =$C15 -> 37 | AI15: =SUMIFS(Transactions!$E:$E,Transactions!$C:$C,$B15,Transactions!$B:$B,"Expense",Transactions!$I:$I,11) -> 0 | AJ15: =AI15-AH15 -> -37 | AK15: =$C15 -> 37 | AL15: =SUMIFS(Transactions!$E:$E,Transactions!$C:$C,$B15,Transactions!$B:$B,"Expense",Transactions!$I:$I,12) -> 0 | AM15: =AL15-AK15 -> -37
A16: FIXED | B16: iPhone Payments | C16: 108 | D16: =$C16 -> 108 | E16: =SUMIFS(Transactions!$E:$E,Transactions!$C:$C,$B16,Transactions!$B:$B,"Expense",Transactions!$I:$I,1) -> 53.95 | F16: =E16-D16 -> -54.05 | G16: =$C16 -> 108 | H16: =SUMIFS(Transactions!$E:$E,Transactions!$C:$C,$B16,Transactions!$B:$B,"Expense",Transactions!$I:$I,2) -> 0 | I16: =H16-G16 -> -108 | J16: =$C16 -> 108 | K16: =SUMIFS(Transactions!$E:$E,Transactions!$C:$C,$B16,Transactions!$B:$B,"Expense",Transactions!$I:$I,3) -> 0 | L16: =K16-J16 -> -108 | M16: =$C16 -> 108 | N16: =SUMIFS(Transactions!$E:$E,Transactions!$C:$C,$B16,Transactions!$B:$B,"Expense",Transactions!$I:$I,4) -> 0 | O16: =N16-M16 -> -108 | P16: =$C16 -> 108 | Q16: =SUMIFS(Transactions!$E:$E,Transactions!$C:$C,$B16,Transactions!$B:$B,"Expense",Transactions!$I:$I,5) -> 0 | R16: =Q16-P16 -> -108 | S16: =$C16 -> 108 | T16: =SUMIFS(Transactions!$E:$E,Transactions!$C:$C,$B16,Transactions!$B:$B,"Expense",Transactions!$I:$I,6) -> 0 | U16: =T16-S16 -> -108 | V16: =$C16 -> 108 | W16: =SUMIFS(Transactions!$E:$E,Transactions!$C:$C,$B16,Transactions!$B:$B,"Expense",Transactions!$I:$I,7) -> 0 | X16: =W16-V16 -> -108 | Y16: =$C16 -> 108 | Z16: =SUMIFS(Transactions!$E:$E,Transactions!$C:$C,$B16,Transactions!$B:$B,"Expense",Transactions!$I:$I,8) -> 0 | AA16: =Z16-Y16 -> -108 | AB16: =$C16 -> 108 | AC16: =SUMIFS(Transactions!$E:$E,Transactions!$C:$C,$B16,Transactions!$B:$B,"Expense",Transactions!$I:$I,9) -> 0 | AD16: =AC16-AB16 -> -108 | AE16: =$C16 -> 108 | AF16: =SUMIFS(Transactions!$E:$E,Transactions!$C:$C,$B16,Transactions!$B:$B,"Expense",Transactions!$I:$I,10) -> 0 | AG16: =AF16-AE16 -> -108 | AH16: =$C16 -> 108 | AI16: =SUMIFS(Transactions!$E:$E,Transactions!$C:$C,$B16,Transactions!$B:$B,"Expense",Transactions!$I:$I,11) -> 0 | AJ16: =AI16-AH16 -> -108 | AK16: =$C16 -> 108 | AL16: =SUMIFS(Transactions!$E:$E,Transactions!$C:$C,$B16,Transactions!$B:$B,"Expense",Transactions!$I:$I,12) -> 0 | AM16: =AL16-AK16 -> -108
... A21: FIXED | B21: Laptop | C21: 43 | D21: =$C21 -> 43 | E21: =SUMIFS(Transactions!$E:$E,Transactions!$C:$C,$B21,Transactions!$B:$B,"Expense",Transactions!$I:$I,1) -> 43 | F21: =E21-D21 -> 0 | G21: =$C21 -> 43 | H21: =SUMIFS(Transactions!$E:$E,Transactions!$C:$C,$B21,Transactions!$B:$B,"Expense",Transactions!$I:$I,2) -> 0 | I21: =H21-G21 -> -43 | J21: =$C21 -> 43 | K21: =SUMIFS(Transactions!$E:$E,Transactions!$C:$C,$B21,Transactions!$B:$B,"Expense",Transactions!$I:$I,3) -> 0 | L21: =K21-J21 -> -43 | M21: =$C21 -> 43 | N21: =SUMIFS(Transactions!$E:$E,Transactions!$C:$C,$B21,Transactions!$B:$B,"Expense",Transactions!$I:$I,4) -> 0 | O21: =N21-M21 -> -43 | P21: =$C21 -> 43 | Q21: =SUMIFS(Transactions!$E:$E,Transactions!$C:$C,$B21,Transactions!$B:$B,"Expense",Transactions!$I:$I,5) -> 0 | R21: =Q21-P21 -> -43 | S21: =$C21 -> 43 | T21: =SUMIFS(Transactions!$E:$E,Transactions!$C:$C,$B21,Transactions!$B:$B,"Expense",Transactions!$I:$I,6) -> 0 | U21: =T21-S21 -> -43 | V21: =$C21 -> 43 | W21: =SUMIFS(Transactions!$E:$E,Transactions!$C:$C,$B21,Transactions!$B:$B,"Expense",Transactions!$I:$I,7) -> 0 | X21: =W21-V21 -> -43 | Y21: =$C21 -> 43 | Z21: =SUMIFS(Transactions!$E:$E,Transactions!$C:$C,$B21,Transactions!$B:$B,"Expense",Transactions!$I:$I,8) -> 0 | AA21: =Z21-Y21 -> -43 | AB21: =$C21 -> 43 | AC21: =SUMIFS(Transactions!$E:$E,Transactions!$C:$C,$B21,Transactions!$B:$B,"Expense",Transactions!$I:$I,9) -> 0 | AD21: =AC21-AB21 -> -43 | AE21: =$C21 -> 43 | AF21: =SUMIFS(Transactions!$E:$E,Transactions!$C:$C,$B21,Transactions!$B:$B,"Expense",Transactions!$I:$I,10) -> 0 | AG21: =AF21-AE21 -> -43 | AH21: =$C21 -> 43 | AI21: =SUMIFS(Transactions!$E:$E,Transactions!$C:$C,$B21,Transactions!$B:$B,"Expense",Transactions!$I:$I,11) -> 0 | AJ21: =AI21-AH21 -> -43 | AK21: =$C21 -> 43 | AL21: =SUMIFS(Transactions!$E:$E,Transactions!$C:$C,$B21,Transactions!$B:$B,"Expense",Transactions!$I:$I,12) -> 0 | AM21: =AL21-AK21 -> -43
A22: FIXED | B22: One-Off Giving (Christmas) | C22: 500 | D22: =$C22 -> 500 | E22: =SUMIFS(Transactions!$E:$E,Transactions!$C:$C,$B22,Transactions!$B:$B,"Expense",Transactions!$I:$I,1) -> 457.37 | F22: =E22-D22 -> -42.63
A23: VARIABLE | B23: Food | C23: 150 | D23: =$C23 -> 150 | E23: =SUMIFS(Transactions!$E:$E,Transactions!$C:$C,$B23,Transactions!$B:$B,"Expense",Transactions!$I:$I,1) -> 0 | F23: =E23-D23 -> -150 | G23: =$C23 -> 150 | H23: =SUMIFS(Transactions!$E:$E,Transactions!$C:$C,$B23,Transactions!$B:$B,"Expense",Transactions!$I:$I,2) -> 0 | I23: =H23-G23 -> -150 | J23: =$C23 -> 150 | K23: =SUMIFS(Transactions!$E:$E,Transactions!$C:$C,$B23,Transactions!$B:$B,"Expense",Transactions!$I:$I,3) -> 0 | L23: =K23-J23 -> -150 | M23: =$C23 -> 150 | N23: =SUMIFS(Transactions!$E:$E,Transactions!$C:$C,$B23,Transactions!$B:$B,"Expense",Transactions!$I:$I,4) -> 0 | O23: =N23-M23 -> -150 | P23: =$C23 -> 150 | Q23: =SUMIFS(Transactions!$E:$E,Transactions!$C:$C,$B23,Transactions!$B:$B,"Expense",Transactions!$I:$I,5) -> 0 | R23: =Q23-P23 -> -150 | S23: =$C23 -> 150 | T23: =SUMIFS(Transactions!$E:$E,Transactions!$C:$C,$B23,Transactions!$B:$B,"Expense",Transactions!$I:$I,6) -> 0 | U23: =T23-S23 -> -150 | V23: =$C23 -> 150 | W23: =SUMIFS(Transactions!$E:$E,Transactions!$C:$C,$B23,Transactions!$B:$B,"Expense",Transactions!$I:$I,7) -> 0 | X23: =W23-V23 -> -150 | Y23: =$C23 -> 150 | Z23: =SUMIFS(Transactions!$E:$E,Transactions!$C:$C,$B23,Transactions!$B:$B,"Expense",Transactions!$I:$I,8) -> 0 | AA23: =Z23-Y23 -> -150 | AB23: =$C23 -> 150 | AC23: =SUMIFS(Transactions!$E:$E,Transactions!$C:$C,$B23,Transactions!$B:$B,"Expense",Transactions!$I:$I,9) -> 0 | AD23: =AC23-AB23 -> -150 | AE23: =$C23 -> 150 | AF23: =SUMIFS(Transactions!$E:$E,Transactions!$C:$C,$B23,Transactions!$B:$B,"Expense",Transactions!$I:$I,10) -> 0 | AG23: =AF23-AE23 -> -150 | AH23: =$C23 -> 150 | AI23: =SUMIFS(Transactions!$E:$E,Transactions!$C:$C,$B23,Transactions!$B:$B,"Expense",Transactions!$I:$I,11) -> 0 | AJ23: =AI23-AH23 -> -150 | AK23: =$C23 -> 150 | AL23: =SUMIFS(Transactions!$E:$E,Transactions!$C:$C,$B23,Transactions!$B:$B,"Expense",Transactions!$I:$I,12) -> 0 | AM23: =AL23-AK23 -> -150
A24: VARIABLE | B24: Others | C24: 150 | D24: =$C24 -> 150 | E24: =SUMIFS(Transactions!$E:$E,Transactions!$C:$C,$B24,Transactions!$B:$B,"Expense",Transactions!$I:$I,1) -> 0 | F24: =E24-D24 -> -150 | G24: =$C24 -> 150 | H24: =SUMIFS(Transactions!$E:$E,Transactions!$C:$C,$B24,Transactions!$B:$B,"Expense",Transactions!$I:$I,2) -> 0 | I24: =H24-G24 -> -150 | J24: =$C24 -> 150 | K24: =SUMIFS(Transactions!$E:$E,Transactions!$C:$C,$B24,Transactions!$B:$B,"Expense",Transactions!$I:$I,3) -> 0 | L24: =K24-J24 -> -150 | M24: =$C24 -> 150 | N24: =SUMIFS(Transactions!$E:$E,Transactions!$C:$C,$B24,Transactions!$B:$B,"Expense",Transactions!$I:$I,4) -> 0 | O24: =N24-M24 -> -150 | P24: =$C24 -> 150 | Q24: =SUMIFS(Transactions!$E:$E,Transactions!$C:$C,$B24,Transactions!$B:$B,"Expense",Transactions!$I:$I,5) -> 0 | R24: =Q24-P24 -> -150 | S24: =$C24 -> 150 | T24: =SUMIFS(Transactions!$E:$E,Transactions!$C:$C,$B24,Transactions!$B:$B,"Expense",Transactions!$I:$I,6) -> 0 | U24: =T24-S24 -> -150 | V24: =$C24 -> 150 | W24: =SUMIFS(Transactions!$E:$E,Transactions!$C:$C,$B24,Transactions!$B:$B,"Expense",Transactions!$I:$I,7) -> 0 | X24: =W24-V24 -> -150 | Y24: =$C24 -> 150 | Z24: =SUMIFS(Transactions!$E:$E,Transactions!$C:$C,$B24,Transactions!$B:$B,"Expense",Transactions!$I:$I,8) -> 0 | AA24: =Z24-Y24 -> -150 | AB24: =$C24 -> 150 | AC24: =SUMIFS(Transactions!$E:$E,Transactions!$C:$C,$B24,Transactions!$B:$B,"Expense",Transactions!$I:$I,9) -> 0 | AD24: =AC24-AB24 -> -150 | AE24: =$C24 -> 150 | AF24: =SUMIFS(Transactions!$E:$E,Transactions!$C:$C,$B24,Transactions!$B:$B,"Expense",Transactions!$I:$I,10) -> 0 | AG24: =AF24-AE24 -> -150 | AH24: =$C24 -> 150 | AI24: =SUMIFS(Transactions!$E:$E,Transactions!$C:$C,$B24,Transactions!$B:$B,"Expense",Transactions!$I:$I,11) -> 0 | AJ24: =AI24-AH24 -> -150 | AK24: =$C24 -> 150 | AL24: =SUMIFS(Transactions!$E:$E,Transactions!$C:$C,$B24,Transactions!$B:$B,"Expense",Transactions!$I:$I,12) -> 0 | AM24: =AL24-AK24 -> -150
A25: SAVINGS | B25: Savings Transfer | C25: 1050 | D25: =$C25 -> 1050 | E25: =SUMIFS(Transactions!$E:$E,Transactions!$C:$C,$B25,Transactions!$B:$B,"Transfer",Transactions!$I:$I,1) -> 0 | F25: =E25-D25 -> -1050 | G25: =$C25 -> 1050 | H25: =SUMIFS(Transactions!$E:$E,Transactions!$C:$C,$B25,Transactions!$B:$B,"Transfer",Transactions!$I:$I,2) -> 0 | I25: =H25-G25 -> -1050 | J25: =$C25 -> 1050 | K25: =SUMIFS(Transactions!$E:$E,Transactions!$C:$C,$B25,Transactions!$B:$B,"Transfer",Transactions!$I:$I,3) -> 0 | L25: =K25-J25 -> -1050 | M25: =$C25 -> 1050 | N25: =SUMIFS(Transactions!$E:$E,Transactions!$C:$C,$B25,Transactions!$B:$B,"Transfer",Transactions!$I:$I,4) -> 0 | O25: =N25-M25 -> -1050 | P25: =$C25 -> 1050 | Q25: =SUMIFS(Transactions!$E:$E,Transactions!$C:$C,$B25,Transactions!$B:$B,"Transfer",Transactions!$I:$I,5) -> 0 | R25: =Q25-P25 -> -1050 | S25: =$C25 -> 1050 | T25: =SUMIFS(Transactions!$E:$E,Transactions!$C:$C,$B25,Transactions!$B:$B,"Transfer",Transactions!$I:$I,6) -> 0 | U25: =T25-S25 -> -1050 | V25: =$C25 -> 1050 | W25: =SUMIFS(Transactions!$E:$E,Transactions!$C:$C,$B25,Transactions!$B:$B,"Transfer",Transactions!$I:$I,7) -> 0 | X25: =W25-V25 -> -1050 | Y25: =$C25 -> 1050 | Z25: =SUMIFS(Transactions!$E:$E,Transactions!$C:$C,$B25,Transactions!$B:$B,"Transfer",Transactions!$I:$I,8) -> 0 | AA25: =Z25-Y25 -> -1050 | AB25: =$C25 -> 1050 | AC25: =SUMIFS(Transactions!$E:$E,Transactions!$C:$C,$B25,Transactions!$B:$B,"Transfer",Transactions!$I:$I,9) -> 0 | AD25: =AC25-AB25 -> -1050 | AE25: =$C25 -> 1050 | AF25: =SUMIFS(Transactions!$E:$E,Transactions!$C:$C,$B25,Transactions!$B:$B,"Transfer",Transactions!$I:$I,10) -> 0 | AG25: =AF25-AE25 -> -1050 | AH25: =$C25 -> 1050 | AI25: =SUMIFS(Transactions!$E:$E,Transactions!$C:$C,$B25,Transactions!$B:$B,"Transfer",Transactions!$I:$I,11) -> 0 | AJ25: =AI25-AH25 -> -1050 | AK25: =$C25 -> 1050 | AL25: =SUMIFS(Transactions!$E:$E,Transactions!$C:$C,$B25,Transactions!$B:$B,"Transfer",Transactions!$I:$I,12) -> 0 | AM25: =AL25-AK25 -> -1050

Sheet Dashboard
A1: Finance
A2: Household • 2026 • Periods run 26th → 25th
A3: Budget Income / Period | B3: =Setup!B4 + (Setup!B5*2) + (Setup!B6*4) -> 4700
A4: Selected period | B4: 1 | C4: Change this to view one period | D4: As of date | E4: 46020 | F4: Change to today when reviewing
A5: =SUMIF('Budget by Period'!$A:$A,"INCOME",'Budget by Period'!$C:$C) -> 4700 | B5: =Setup!B11 -> 1050 | D5: =SUMIFS('Budget by Period'!$C:$C,'Budget by Period'!$A:$A,"<>INCOME",'Budget by Period'!$A:$A,"<>SAVINGS") -> 4055
A6: Income (selected period) | B6: =B3-B4-B5 -> 3649 | E6: Spending (selected period) | I6: Savings (selected period) | M6: Leftover (selected period)
A7: =INDEX($B$64:$B$75,$B$4) -> 3811.48 | D7: Planned Leftover / Period | E7: =INDEX($C$64:$C$75,$B$4) -> 2179.98 | I7: =INDEX($D$64:$D$75,$B$4) -> 0 | M7: =INDEX($E$64:$E$75,$B$4) -> 1631.5
A8: =Setup!B11 -> 1050 | D8: =B5-B6-B7 -> -2599
A9: Period | B9: Start | C9: End | D9: Income (Actual) | E9: Expenses (Actual) | F9: Savings (Actual) | G9: Leftover (Actual)
A10: Budgets (per period) | B10: =INDEX('Periods 26-25'!$C:$C, MATCH($B$4, 'Periods 26-25'!$A:$A, 0)) -> 46013 | C10: =INDEX('Periods 26-25'!$D:$D, MATCH($B$4, 'Periods 26-25'!$A:$A, 0)) -> 46047 | D10: =SUMIF('Budget by Period'!$A:$A,"INCOME",'Budget by Period'!$E:$E) -> 3811.48 | E10: =SUM('Bills Schedule'!$C$3:$C$200) -> 4715 | F10: =SUMIF('Budget by Period'!$A:$A,"SAVINGS",'Budget by Period'!$E:$E) -> 0 | G10: =D10-E10-F10 -> -903.52 | K10: =Setup!B11 -> 1050
A11: Budget income / period | B11: Start | C11: End | D11: Income (Actual) | E11: Budget spend / period | F11: Savings (Actual) | G11: Leftover (Actual) | I11: Savings target / period | M11: Planned leftover / period
A12: =SUMIF('Budget by Period'!$A:$A,"INCOME",'Budget by Period'!$C:$C) -> 4700 | B12: 46079 | C12: 46106 | D12: =SUMIF('Budget by Period'!$A:$A,"INCOME",'Budget by Period'!$K:$K) -> 0 | E12: =SUMIFS('Budget by Period'!$C:$C,'Budget by Period'!$A:$A,"<>INCOME",'Budget by Period'!$A:$A,"<>SAVINGS") -> 4055 | F12: =SUMIF('Budget by Period'!$A:$A,"SAVINGS",'Budget by Period'!$K:$K) -> 0 | G12: =D12-E12-F12 -> -4055 | I12: =Setup!B11 -> 1050 | M12: =SUMIF('Budget by Period'!$A:$A,"INCOME",'Budget by Period'!$C:$C)-SUMIFS('Budget by Period'!$C:$C,'Budget by Period'!$A:$A,"<>INCOME",'Budget by Period'!$A:$A,"<>SAVINGS")-Setup!B11 -> -405
A13: P4 | B13: 46107 | C13: 46137 | D13: =SUMIF('Budget by Period'!$A:$A,"INCOME",'Budget by Period'!$N:$N) -> 0 | E13: =SUMIFS('Budget by Period'!$N:$N,'Budget by Period'!$A:$A,"<>INCOME",'Budget by Period'!$A:$A,"<>SAVINGS") -> 0 | F13: =SUMIF('Budget by Period'!$A:$A,"SAVINGS",'Budget by Period'!$N:$N) -> 0 | G13: =D13-E13-F13 -> 0
A14: See Upcoming Bills → | B14: Go to tab: Upcoming Bills | C14: 46167 | D14: =SUMIF('Budget by Period'!$A:$A,"INCOME",'Budget by Period'!$Q:$Q) -> 0 | E14: =SUMIFS('Budget by Period'!$Q:$Q,'Budget by Period'!$A:$A,"<>INCOME",'Budget by Period'!$A:$A,"<>SAVINGS") -> 0 | F14: =SUMIF('Budget by Period'!$A:$A,"SAVINGS",'Budget by Period'!$Q:$Q) -> 0 | G14: =D14-E14-F14 -> 0
A15: See Upcoming Income → | B15: Go to tab: Upcoming Income | C15: 46198 | D15: =SUMIF('Budget by Period'!$A:$A,"INCOME",'Budget by Period'!$T:$T) -> 0 | E15: =SUMIFS('Budget by Period'!$T:$T,'Budget by Period'!$A:$A,"<>INCOME",'Budget by Period'!$A:$A,"<>SAVINGS") -> 0 | F15: =SUMIF('Budget by Period'!$A:$A,"SAVINGS",'Budget by Period'!$T:$T) -> 0 | G15: =D15-E15-F15 -> 0
A16: See Cashflow Timeline → | B16: Go to tab: Cashflow Timeline | C16: 46228 | D16: =SUMIF('Budget by Period'!$A:$A,"INCOME",'Budget by Period'!$W:$W) -> 0 | E16: =SUMIFS('Budget by Period'!$W:$W,'Budget by Period'!$A:$A,"<>INCOME",'Budget by Period'!$A:$A,"<>SAVINGS") -> 0 | F16: =SUMIF('Budget by Period'!$A:$A,"SAVINGS",'Budget by Period'!$W:$W) -> 0 | G16: =D16-E16-F16 -> 0
A17: Minimum Balance Alert → | B17: See tab: Cashflow Timeline (row 9) | C17: 46259 | D17: =SUMIF('Budget by Period'!$A:$A,"INCOME",'Budget by Period'!$Z:$Z) -> 0 | E17: =SUMIFS('Budget by Period'!$Z:$Z,'Budget by Period'!$A:$A,"<>INCOME",'Budget by Period'!$A:$A,"<>SAVINGS") -> 0 | F17: =SUMIF('Budget by Period'!$A:$A,"SAVINGS",'Budget by Period'!$Z:$Z) -> 0 | G17: =D17-E17-F17 -> 0
A18: P9 | B18: 46260 | C18: 46290 | D18: =SUMIF('Budget by Period'!$A:$A,"INCOME",'Budget by Period'!$AC:$AC) -> 0 | E18: =SUMIFS('Budget by Period'!$AC:$AC,'Budget by Period'!$A:$A,"<>INCOME",'Budget by Period'!$A:$A,"<>SAVINGS") -> 0 | F18: =SUMIF('Budget by Period'!$A:$A,"SAVINGS",'Budget by Period'!$AC:$AC) -> 0 | G18: =D18-E18-F18 -> 0
A19: P10 | B19: 46291 | C19: 46320 | D19: =SUMIF('Budget by Period'!$A:$A,"INCOME",'Budget by Period'!$AF:$AF) -> 0 | E19: =SUMIFS('Budget by Period'!$AF:$AF,'Budget by Period'!$A:$A,"<>INCOME",'Budget by Period'!$A:$A,"<>SAVINGS") -> 0 | F19: =SUMIF('Budget by Period'!$A:$A,"SAVINGS",'Budget by Period'!$AF:$AF) -> 0 | G19: =D19-E19-F19 -> 0
A20: P11 | B20: 46321 | C20: 46351 | D20: =SUMIF('Budget by Period'!$A:$A,"INCOME",'Budget by Period'!$AI:$AI) -> 0 | E20: =SUMIFS('Budget by Period'!$AI:$AI,'Budget by Period'!$A:$A,"<>INCOME",'Budget by Period'!$A:$A,"<>SAVINGS") -> 0 | F20: =SUMIF('Budget by Period'!$A:$A,"SAVINGS",'Budget by Period'!$AI:$AI) -> 0 | G20: =D20-E20-F20 -> 0
A21: P12 | B21: 46352 | C21: 46381 | D21: =SUMIF('Budget by Period'!$A:$A,"INCOME",'Budget by Period'!$AL:$AL) -> 0 | E21: =SUMIFS('Budget by Period'!$AL:$AL,'Budget by Period'!$A:$A,"<>INCOME",'Budget by Period'!$A:$A,"<>SAVINGS") -> 0 | F21: =SUMIF('Budget by Period'!$A:$A,"SAVINGS",'Budget by Period'!$AL:$AL) -> 0 | G21: =D21-E21-F21 -> 0
A60: Helper (do not edit) | H60: Spending Breakdown (selected period)
A61: ActualCol | B61: =5+(B4-1)*3 -> 5 | H61: Category | I61: Actual
H62: Food | I62: =IFERROR(INDEX('Budget by Period'!$A:$ZZ, MATCH("Food",'Budget by Period'!$B:$B,0), 5+($B$4-1)*3),0) -> 0
A63: Period | B63: Income | C63: Expenses | D63: Savings | E63: Leftover | H63: Others | I63: =IFERROR(INDEX('Budget by Period'!$A:$ZZ, MATCH("Others",'Budget by Period'!$B:$B,0), 5+($B$4-1)*3),0) -> 0
A64: 1 | B64: =SUMIF('Budget by Period'!$A:$A,"INCOME",'Budget by Period'!$E:$E) -> 3811.48 | C64: =SUMIFS('Budget by Period'!$E:$E,'Budget by Period'!$A:$A,"<>INCOME",'Budget by Period'!$A:$A,"<>SAVINGS") -> 2179.98 | D64: =SUMIF('Budget by Period'!$A:$A,"SAVINGS",'Budget by Period'!$E:$E) -> 0 | E64: =B64-C64-D64 -> 1631.5 | H64: Donations (Variable) | I64: =IFERROR(INDEX('Budget by Period'!$A:$ZZ, MATCH("Donations (Variable)",'Budget by Period'!$B:$B,0), 5+($B$4-1)*3),0) -> 34
A65: 2 | B65: =SUMIF('Budget by Period'!$A:$A,"INCOME",'Budget by Period'!$H:$H) -> 0 | C65: =SUMIFS('Budget by Period'!$H:$H,'Budget by Period'!$A:$A,"<>INCOME",'Budget by Period'!$A:$A,"<>SAVINGS") -> 0 | D65: =SUMIF('Budget by Period'!$A:$A,"SAVINGS",'Budget by Period'!$H:$H) -> 0 | E65: =B65-C65-D65 -> 0 | H65: Tithe | I65: =IFERROR(INDEX('Budget by Period'!$A:$ZZ, MATCH("Tithe",'Budget by Period'!$B:$B,0), 5+($B$4-1)*3),0) -> 383
A66: 3 | B66: =SUMIF('Budget by Period'!$A:$A,"INCOME",'Budget by Period'!$K:$K) -> 0 | C66: =SUMIFS('Budget by Period'!$K:$K,'Budget by Period'!$A:$A,"<>INCOME",'Budget by Period'!$A:$A,"<>SAVINGS") -> 0 | D66: =SUMIF('Budget by Period'!$A:$A,"SAVINGS",'Budget by Period'!$K:$K) -> 0 | E66: =B66-C66-D66 -> 0 | H66: Offerings | I66: =IFERROR(INDEX('Budget by Period'!$A:$ZZ, MATCH("Offerings",'Budget by Period'!$B:$B,0), 5+($B$4-1)*3),0) -> 140
A67: 4 | B67: =SUMIF('Budget by Period'!$A:$A,"INCOME",'Budget by Period'!$N:$N) -> 0 | C67: =SUMIFS('Budget by Period'!$N:$N,'Budget by Period'!$A:$A,"<>INCOME",'Budget by Period'!$A:$A,"<>SAVINGS") -> 0 | D67: =SUMIF('Budget by Period'!$A:$A,"SAVINGS",'Budget by Period'!$N:$N) -> 0 | E67: =B67-C67-D67 -> 0 | H67: Rent | I67: =IFERROR(INDEX('Budget by Period'!$A:$ZZ, MATCH("Rent",'Budget by Period'!$B:$B,0), 5+($B$4-1)*3),0) -> 0
A68: 5 | B68: =SUMIF('Budget by Period'!$A:$A,"INCOME",'Budget by Period'!$Q:$Q) -> 0 | C68: =SUMIFS('Budget by Period'!$Q:$Q,'Budget by Period'!$A:$A,"<>INCOME",'Budget by Period'!$A:$A,"<>SAVINGS") -> 0 | D68: =SUMIF('Budget by Period'!$A:$A,"SAVINGS",'Budget by Period'!$Q:$Q) -> 0 | E68: =B68-C68-D68 -> 0 | H68: Credit Card | I68: =IFERROR(INDEX('Budget by Period'!$A:$ZZ, MATCH("Credit Card",'Budget by Period'!$B:$B,0), 5+($B$4-1)*3),0) -> 0
A69: 6 | B69: =SUMIF('Budget by Period'!$A:$A,"INCOME",'Budget by Period'!$T:$T) -> 0 | C69: =SUMIFS('Budget by Period'!$T:$T,'Budget by Period'!$A:$A,"<>INCOME",'Budget by Period'!$A:$A,"<>SAVINGS") -> 0 | D69: =SUMIF('Budget by Period'!$A:$A,"SAVINGS",'Budget by Period'!$T:$T) -> 0 | E69: =B69-C69-D69 -> 0 | H69: Fuel | I69: =IFERROR(INDEX('Budget by Period'!$A:$ZZ, MATCH("Fuel",'Budget by Period'!$B:$B,0), 5+($B$4-1)*3),0) -> 30.17
A70: 7 | B70: =SUMIF('Budget by Period'!$A:$A,"INCOME",'Budget by Period'!$W:$W) -> 0 | C70: =SUMIFS('Budget by Period'!$W:$W,'Budget by Period'!$A:$A,"<>INCOME",'Budget by Period'!$A:$A,"<>SAVINGS") -> 0 | D70: =SUMIF('Budget by Period'!$A:$A,"SAVINGS",'Budget by Period'!$W:$W) -> 0 | E70: =B70-C70-D70 -> 0
A71: 8 | B71: =SUMIF('Budget by Period'!$A:$A,"INCOME",'Budget by Period'!$Z:$Z) -> 0 | C71: =SUMIFS('Budget by Period'!$Z:$Z,'Budget by Period'!$A:$A,"<>INCOME",'Budget by Period'!$A:$A,"<>SAVINGS") -> 0 | D71: =SUMIF('Budget by Period'!$A:$A,"SAVINGS",'Budget by Period'!$Z:$Z) -> 0 | E71: =B71-C71-D71 -> 0
A72: 9 | B72: =SUMIF('Budget by Period'!$A:$A,"INCOME",'Budget by Period'!$AC:$AC) -> 0 | C72: =SUMIFS('Budget by Period'!$AC:$AC,'Budget by Period'!$A:$A,"<>INCOME",'Budget by Period'!$A:$A,"<>SAVINGS") -> 0 | D72: =SUMIF('Budget by Period'!$A:$A,"SAVINGS",'Budget by Period'!$AC:$AC) -> 0 | E72: =B72-C72-D72 -> 0
A73: 10 | B73: =SUMIF('Budget by Period'!$A:$A,"INCOME",'Budget by Period'!$AF:$AF) -> 0 | C73: =SUMIFS('Budget by Period'!$AF:$AF,'Budget by Period'!$A:$A,"<>INCOME",'Budget by Period'!$A:$A,"<>SAVINGS") -> 0 | D73: =SUMIF('Budget by Period'!$A:$A,"SAVINGS",'Budget by Period'!$AF:$AF) -> 0 | E73: =B73-C73-D73 -> 0
A74: 11 | B74: =SUMIF('Budget by Period'!$A:$A,"INCOME",'Budget by Period'!$AI:$AI) -> 0 | C74: =SUMIFS('Budget by Period'!$AI:$AI,'Budget by Period'!$A:$A,"<>INCOME",'Budget by Period'!$A:$A,"<>SAVINGS") -> 0 | D74: =SUMIF('Budget by Period'!$A:$A,"SAVINGS",'Budget by Period'!$AI:$AI) -> 0 | E74: =B74-C74-D74 -> 0
A75: 12 | B75: =SUMIF('Budget by Period'!$A:$A,"INCOME",'Budget by Period'!$AL:$AL) -> 0 | C75: =SUMIFS('Budget by Period'!$AL:$AL,'Budget by Period'!$A:$A,"<>INCOME",'Budget by Period'!$A:$A,"<>SAVINGS") -> 0 | D75: =SUMIF('Budget by Period'!$A:$A,"SAVINGS",'Budget by Period'!$AL:$AL) -> 0 | E75: =B75-C75-D75 -> 0

Sheet How to Use
A1: How to Use (Pay timelines + 26th–25th periods)
A3: • 1) Setup: Adjust any amounts (FM monthly, McD per-pay, Outlier per-pay) and targets.
A4: • 2) Periods: Your budgeting month is 26th–25th. This is already built for 2026 (P1..P12).
A5: • 3) Transactions: Log everything. Period auto-fills from the Date.
A6: • 4) Budget by Period: Budgets are prefilled from your breakdown; Actuals + Variance update automatically.
A7: • 5) Bills Schedule: Set the Period number you’re reviewing (e.g., 1) and it will pull actual payments for that period.
A8: • 6) Dashboard: Review performance per period and watch the charts.
A9: • Tip: For McD/Outlier variability, track actual income via Transactions — budgets stay as averages.

Sheet Upcoming Bills
A1: Upcoming Bills
A2: Finance-style view • Uses your 26th→3rd bills window • Updates from Transactions | I2: *Until the fill amount goes out, it doesn't change to "paid" even though it has been paid, eg is One-Off Givivng (Christmas), where amounts paid was £457.37 instead of the initially planned amount of £500.
A4: Selected Period | B4: =Dashboard!B4 -> 1 | D4: As of date | E4: =Dashboard!E4 -> 46020
A6: Period Start | B6: =INDEX('Periods 26-25'!$C:$C, MATCH($B$4, 'Periods 26-25'!$A:$A, 0)) -> 46013 | D6: Period End | E6: =INDEX('Periods 26-25'!$D:$D, MATCH($B$4, 'Periods 26-25'!$A:$A, 0)) -> 46047 | J6: =500*0.91 -> 455
A9: Bill | B9: Due date (this period) | C9: Budget | D9: Actual paid | E9: Remaining | F9: Status | G9: Notes
A10: Rent | B10: =IF(INDEX('Bills Schedule'!$B$3:$B$200, MATCH($A10, 'Bills Schedule'!$A$3:$A$200,0))="","",IF(INDEX('Bills Schedule'!$B$3:$B$200, MATCH($A10, 'Bills Schedule'!$A$3:$A$200,0))>=26,DATE(YEAR($B$6),MONTH($B$6),INDEX('Bills Schedule'!$B$3:$B$200, MATCH($A10, 'Bills Schedule'!$A$3:$A$200,0))),DATE(YEAR(EDATE($B$6,1)),MONTH(EDATE($B$6,1)),INDEX('Bills Schedule'!$B$3:$B$200, MATCH($A10, 'Bills Schedule'!$A$3:$A$200,0))))) -> 46019 | C10: =INDEX('Bills Schedule'!$C$3:$C$200, MATCH($A10, 'Bills Schedule'!$A$3:$A$200,0)) -> 550 | D10: =IF($A10="Savings Transfer",SUMIFS(Transactions!$E:$E,Transactions!$B:$B,"Transfer",Transactions!$C:$C,$A10,Transactions!$I:$I,$B$4),SUMIFS(Transactions!$E:$E,Transactions!$B:$B,"Expense",Transactions!$C:$C,$A10,Transactions!$I:$I,$B$4)) -> 0 | E10: =C10-D10 -> 550 | F10: =IF(D10>=C10*0.98,"Paid",IF(AND($E$4>B10,E10>0),"Overdue",IF(AND(B10-$E$4<=7,B10-$E$4>=0,E10>0),"Due soon","Upcoming"))) -> Overdue | G10: =IFERROR(INDEX('Bills Schedule'!$H$3:$H$200, MATCH($A10, 'Bills Schedule'!$A$3:$A$200,0)),"") -> 0
A11: Insurance | B11: =IF(INDEX('Bills Schedule'!$B$3:$B$200, MATCH($A11, 'Bills Schedule'!$A$3:$A$200,0))="","",IF(INDEX('Bills Schedule'!$B$3:$B$200, MATCH($A11, 'Bills Schedule'!$A$3:$A$200,0))>=26,DATE(YEAR($B$6),MONTH($B$6),INDEX('Bills Schedule'!$B$3:$B$200, MATCH($A11, 'Bills Schedule'!$A$3:$A$200,0))),DATE(YEAR(EDATE($B$6,1)),MONTH(EDATE($B$6,1)),INDEX('Bills Schedule'!$B$3:$B$200, MATCH($A11, 'Bills Schedule'!$A$3:$A$200,0))))) -> 46019 | C11: =INDEX('Bills Schedule'!$C$3:$C$200, MATCH($A11, 'Bills Schedule'!$A$3:$A$200,0)) -> 175 | D11: =IF($A11="Savings Transfer",SUMIFS(Transactions!$E:$E,Transactions!$B:$B,"Transfer",Transactions!$C:$C,$A11,Transactions!$I:$I,$B$4),SUMIFS(Transactions!$E:$E,Transactions!$B:$B,"Expense",Transactions!$C:$C,$A11,Transactions!$I:$I,$B$4)) -> 0 | E11: =C11-D11 -> 175 | F11: =IF(D11>=C11*0.98,"Paid",IF(AND($E$4>B11,E11>0),"Overdue",IF(AND(B11-$E$4<=7,B11-$E$4>=0,E11>0),"Due soon","Upcoming"))) -> Overdue | G11: =IFERROR(INDEX('Bills Schedule'!$H$3:$H$200, MATCH($A11, 'Bills Schedule'!$A$3:$A$200,0)),"") -> 0
A12: Road Tax | B12: =IF(INDEX('Bills Schedule'!$B$3:$B$200, MATCH($A12, 'Bills Schedule'!$A$3:$A$200,0))="","",IF(INDEX('Bills Schedule'!$B$3:$B$200, MATCH($A12, 'Bills Schedule'!$A$3:$A$200,0))>=26,DATE(YEAR($B$6),MONTH($B$6),INDEX('Bills Schedule'!$B$3:$B$200, MATCH($A12, 'Bills Schedule'!$A$3:$A$200,0))),DATE(YEAR(EDATE($B$6,1)),MONTH(EDATE($B$6,1)),INDEX('Bills Schedule'!$B$3:$B$200, MATCH($A12, 'Bills Schedule'!$A$3:$A$200,0))))) -> 46019 | C12: =INDEX('Bills Schedule'!$C$3:$C$200, MATCH($A12, 'Bills Schedule'!$A$3:$A$200,0)) -> 34 | D12: =IF($A12="Savings Transfer",SUMIFS(Transactions!$E:$E,Transactions!$B:$B,"Transfer",Transactions!$C:$C,$A12,Transactions!$I:$I,$B$4),SUMIFS(Transactions!$E:$E,Transactions!$B:$B,"Expense",Transactions!$C:$C,$A12,Transactions!$I:$I,$B$4)) -> 0 | E12: =C12-D12 -> 34 | F12: =IF(D12>=C12*0.98,"Paid",IF(AND($E$4>B12,E12>0),"Overdue",IF(AND(B12-$E$4<=7,B12-$E$4>=0,E12>0),"Due soon","Upcoming"))) -> Overdue | G12: =IFERROR(INDEX('Bills Schedule'!$H$3:$H$200, MATCH($A12, 'Bills Schedule'!$A$3:$A$200,0)),"") -> 0
A13: Water Bill | B13: =IF(INDEX('Bills Schedule'!$B$3:$B$200, MATCH($A13, 'Bills Schedule'!$A$3:$A$200,0))="","",IF(INDEX('Bills Schedule'!$B$3:$B$200, MATCH($A13, 'Bills Schedule'!$A$3:$A$200,0))>=26,DATE(YEAR($B$6),MONTH($B$6),INDEX('Bills Schedule'!$B$3:$B$200, MATCH($A13, 'Bills Schedule'!$A$3:$A$200,0))),DATE(YEAR(EDATE($B$6,1)),MONTH(EDATE($B$6,1)),INDEX('Bills Schedule'!$B$3:$B$200, MATCH($A13, 'Bills Schedule'!$A$3:$A$200,0))))) -> 46019 | C13: =INDEX('Bills Schedule'!$C$3:$C$200, MATCH($A13, 'Bills Schedule'!$A$3:$A$200,0)) -> 93 | D13: =IF($A13="Savings Transfer",SUMIFS(Transactions!$E:$E,Transactions!$B:$B,"Transfer",Transactions!$C:$C,$A13,Transactions!$I:$I,$B$4),SUMIFS(Transactions!$E:$E,Transactions!$B:$B,"Expense",Transactions!$C:$C,$A13,Transactions!$I:$I,$B$4)) -> 92.77 | E13: =C13-D13 -> 0.23 | F13: =IF(D13>=C13*0.98,"Paid",IF(AND($E$4>B13,E13>0),"Overdue",IF(AND(B13-$E$4<=7,B13-$E$4>=0,E13>0),"Due soon","Upcoming"))) -> Paid | G13: =IFERROR(INDEX('Bills Schedule'!$H$3:$H$200, MATCH($A13, 'Bills Schedule'!$A$3:$A$200,0)),"") -> 0
A14: Community Fibre / Internet | B14: =IF(INDEX('Bills Schedule'!$B$3:$B$200, MATCH($A14, 'Bills Schedule'!$A$3:$A$200,0))="","",IF(INDEX('Bills Schedule'!$B$3:$B$200, MATCH($A14, 'Bills Schedule'!$A$3:$A$200,0))>=26,DATE(YEAR($B$6),MONTH($B$6),INDEX('Bills Schedule'!$B$3:$B$200, MATCH($A14, 'Bills Schedule'!$A$3:$A$200,0))),DATE(YEAR(EDATE($B$6,1)),MONTH(EDATE($B$6,1)),INDEX('Bills Schedule'!$B$3:$B$200, MATCH($A14, 'Bills Schedule'!$A$3:$A$200,0))))) -> 46017 | C14: =INDEX('Bills Schedule'!$C$3:$C$200, MATCH($A14, 'Bills Schedule'!$A$3:$A$200,0)) -> 37 | D14: =IF($A14="Savings Transfer",SUMIFS(Transactions!$E:$E,Transactions!$B:$B,"Transfer",Transactions!$C:$C,$A14,Transactions!$I:$I,$B$4),SUMIFS(Transactions!$E:$E,Transactions!$B:$B,"Expense",Transactions!$C:$C,$A14,Transactions!$I:$I,$B$4)) -> 36.83 | E14: =C14-D14 -> 0.17 | F14: =IF(D14>=C14*0.98,"Paid",IF(AND($E$4>B14,E14>0),"Overdue",IF(AND(B14-$E$4<=7,B14-$E$4>=0,E14>0),"Due soon","Upcoming"))) -> Paid | G14: =IFERROR(INDEX('Bills Schedule'!$H$3:$H$200, MATCH($A14, 'Bills Schedule'!$A$3:$A$200,0)),"") -> 0
A15: Electricity & Gas | B15: =IF(INDEX('Bills Schedule'!$B$3:$B$200, MATCH($A15, 'Bills Schedule'!$A$3:$A$200,0))="","",IF(INDEX('Bills Schedule'!$B$3:$B$200, MATCH($A15, 'Bills Schedule'!$A$3:$A$200,0))>=26,DATE(YEAR($B$6),MONTH($B$6),INDEX('Bills Schedule'!$B$3:$B$200, MATCH($A15, 'Bills Schedule'!$A$3:$A$200,0))),DATE(YEAR(EDATE($B$6,1)),MONTH(EDATE($B$6,1)),INDEX('Bills Schedule'!$B$3:$B$200, MATCH($A15, 'Bills Schedule'!$A$3:$A$200,0))))) -> 46017 | C15: =INDEX('Bills Schedule'!$C$3:$C$200, MATCH($A15, 'Bills Schedule'!$A$3:$A$200,0)) -> 200 | D15: =IF($A15="Savings Transfer",SUMIFS(Transactions!$E:$E,Transactions!$B:$B,"Transfer",Transactions!$C:$C,$A15,Transactions!$I:$I,$B$4),SUMIFS(Transactions!$E:$E,Transactions!$B:$B,"Expense",Transactions!$C:$C,$A15,Transactions!$I:$I,$B$4)) -> 50 | E15: =C15-D15 -> 150 | F15: =IF(D15>=C15*0.98,"Paid",IF(AND($E$4>B15,E15>0),"Overdue",IF(AND(B15-$E$4<=7,B15-$E$4>=0,E15>0),"Due soon","Upcoming"))) -> Overdue | G15: =IFERROR(INDEX('Bills Schedule'!$H$3:$H$200, MATCH($A15, 'Bills Schedule'!$A$3:$A$200,0)),"") -> 0
A16: iPhone Payments | B16: =IF(INDEX('Bills Schedule'!$B$3:$B$200, MATCH($A16, 'Bills Schedule'!$A$3:$A$200,0))="","",IF(INDEX('Bills Schedule'!$B$3:$B$200, MATCH($A16, 'Bills Schedule'!$A$3:$A$200,0))>=26,DATE(YEAR($B$6),MONTH($B$6),INDEX('Bills Schedule'!$B$3:$B$200, MATCH($A16, 'Bills Schedule'!$A$3:$A$200,0))),DATE(YEAR(EDATE($B$6,1)),MONTH(EDATE($B$6,1)),INDEX('Bills Schedule'!$B$3:$B$200, MATCH($A16, 'Bills Schedule'!$A$3:$A$200,0))))) -> 46017 | C16: =INDEX('Bills Schedule'!$C$3:$C$200, MATCH($A16, 'Bills Schedule'!$A$3:$A$200,0)) -> 108 | D16: =IF($A16="Savings Transfer",SUMIFS(Transactions!$E:$E,Transactions!$B:$B,"Transfer",Transactions!$C:$C,$A16,Transactions!$I:$I,$B$4),SUMIFS(Transactions!$E:$E,Transactions!$B:$B,"Expense",Transactions!$C:$C,$A16,Transactions!$I:$I,$B$4)) -> 53.95 | E16: =C16-D16 -> 54.05 | F16: =IF(D16>=C16*0.98,"Paid",IF(AND($E$4>B16,E16>0),"Overdue",IF(AND(B16-$E$4<=7,B16-$E$4>=0,E16>0),"Due soon","Upcoming"))) -> Overdue | G16: =IFERROR(INDEX('Bills Schedule'!$H$3:$H$200, MATCH($A16, 'Bills Schedule'!$A$3:$A$200,0)),"") -> 0
A17: Parents | B17: =IF(INDEX('Bills Schedule'!$B$3:$B$200, MATCH($A17, 'Bills Schedule'!$A$3:$A$200,0))="","",IF(INDEX('Bills Schedule'!$B$3:$B$200, MATCH($A17, 'Bills Schedule'!$A$3:$A$200,0))>=26,DATE(YEAR($B$6),MONTH($B$6),INDEX('Bills Schedule'!$B$3:$B$200, MATCH($A17, 'Bills Schedule'!$A$3:$A$200,0))),DATE(YEAR(EDATE($B$6,1)),MONTH(EDATE($B$6,1)),INDEX('Bills Schedule'!$B$3:$B$200, MATCH($A17, 'Bills Schedule'!$A$3:$A$200,0))))) -> 46017 | C17: =INDEX('Bills Schedule'!$C$3:$C$200, MATCH($A17, 'Bills Schedule'!$A$3:$A$200,0)) -> 140 | D17: =IF($A17="Savings Transfer",SUMIFS(Transactions!$E:$E,Transactions!$B:$B,"Transfer",Transactions!$C:$C,$A17,Transactions!$I:$I,$B$4),SUMIFS(Transactions!$E:$E,Transactions!$B:$B,"Expense",Transactions!$C:$C,$A17,Transactions!$I:$I,$B$4)) -> 140 | E17: =C17-D17 -> 0 | F17: =IF(D17>=C17*0.98,"Paid",IF(AND($E$4>B17,E17>0),"Overdue",IF(AND(B17-$E$4<=7,B17-$E$4>=0,E17>0),"Due soon","Upcoming"))) -> Paid | G17: =IFERROR(INDEX('Bills Schedule'!$H$3:$H$200, MATCH($A17, 'Bills Schedule'!$A$3:$A$200,0)),"") -> 0
A18: Credit Card Payment | B18: =IF(INDEX('Bills Schedule'!$B$3:$B$200, MATCH($A18, 'Bills Schedule'!$A$3:$A$200,0))="","",IF(INDEX('Bills Schedule'!$B$3:$B$200, MATCH($A18, 'Bills Schedule'!$A$3:$A$200,0))>=26,DATE(YEAR($B$6),MONTH($B$6),INDEX('Bills Schedule'!$B$3:$B$200, MATCH($A18, 'Bills Schedule'!$A$3:$A$200,0))),DATE(YEAR(EDATE($B$6,1)),MONTH(EDATE($B$6,1)),INDEX('Bills Schedule'!$B$3:$B$200, MATCH($A18, 'Bills Schedule'!$A$3:$A$200,0))))) -> 46017 | C18: =INDEX('Bills Schedule'!$C$3:$C$200, MATCH($A18, 'Bills Schedule'!$A$3:$A$200,0)) -> 400 | D18: =IF($A18="Savings Transfer",SUMIFS(Transactions!$E:$E,Transactions!$B:$B,"Transfer",Transactions!$C:$C,$A18,Transactions!$I:$I,$B$4),SUMIFS(Transactions!$E:$E,Transactions!$B:$B,"Expense",Transactions!$C:$C,$A18,Transactions!$I:$I,$B$4)) -> 438.92 | E18: =C18-D18 -> -38.92 | F18: =IF(D18>=C18*0.98,"Paid",IF(AND($E$4>B18,E18>0),"Overdue",IF(AND(B18-$E$4<=7,B18-$E$4>=0,E18>0),"Due soon","Upcoming"))) -> Paid | G18: =IFERROR(INDEX('Bills Schedule'!$H$3:$H$200, MATCH($A18, 'Bills Schedule'!$A$3:$A$200,0)),"") -> 0
A19: Fuel | B19: =IF(INDEX('Bills Schedule'!$B$3:$B$200, MATCH($A19, 'Bills Schedule'!$A$3:$A$200,0))="","",IF(INDEX('Bills Schedule'!$B$3:$B$200, MATCH($A19, 'Bills Schedule'!$A$3:$A$200,0))>=26,DATE(YEAR($B$6),MONTH($B$6),INDEX('Bills Schedule'!$B$3:$B$200, MATCH($A19, 'Bills Schedule'!$A$3:$A$200,0))),DATE(YEAR(EDATE($B$6,1)),MONTH(EDATE($B$6,1)),INDEX('Bills Schedule'!$B$3:$B$200, MATCH($A19, 'Bills Schedule'!$A$3:$A$200,0))))) -> 46017 | C19: =INDEX('Bills Schedule'!$C$3:$C$200, MATCH($A19, 'Bills Schedule'!$A$3:$A$200,0)) -> 100 | D19: =IF($A19="Savings Transfer",SUMIFS(Transactions!$E:$E,Transactions!$B:$B,"Transfer",Transactions!$C:$C,$A19,Transactions!$I:$I,$B$4),SUMIFS(Transactions!$E:$E,Transactions!$B:$B,"Expense",Transactions!$C:$C,$A19,Transactions!$I:$I,$B$4)) -> 30.17 | E19: =C19-D19 -> 69.83 | F19: =IF(D19>=C19*0.98,"Paid",IF(AND($E$4>B19,E19>0),"Overdue",IF(AND(B19-$E$4<=7,B19-$E$4>=0,E19>0),"Due soon","Upcoming"))) -> Overdue | G19: =IFERROR(INDEX('Bills Schedule'!$H$3:$H$200, MATCH($A19, 'Bills Schedule'!$A$3:$A$200,0)),"") -> 0
A20: Tithe | B20: =IF(INDEX('Bills Schedule'!$B$3:$B$200, MATCH($A20, 'Bills Schedule'!$A$3:$A$200,0))="","",IF(INDEX('Bills Schedule'!$B$3:$B$200, MATCH($A20, 'Bills Schedule'!$A$3:$A$200,0))>=26,DATE(YEAR($B$6),MONTH($B$6),INDEX('Bills Schedule'!$B$3:$B$200, MATCH($A20, 'Bills Schedule'!$A$3:$A$200,0))),DATE(YEAR(EDATE($B$6,1)),MONTH(EDATE($B$6,1)),INDEX('Bills Schedule'!$B$3:$B$200, MATCH($A20, 'Bills Schedule'!$A$3:$A$200,0))))) -> 46017 | C20: =INDEX('Bills Schedule'!$C$3:$C$200, MATCH($A20, 'Bills Schedule'!$A$3:$A$200,0)) -> 410 | D20: =IF($A20="Savings Transfer",SUMIFS(Transactions!$E:$E,Transactions!$B:$B,"Transfer",Transactions!$C:$C,$A20,Transactions!$I:$I,$B$4),SUMIFS(Transactions!$E:$E,Transactions!$B:$B,"Expense",Transactions!$C:$C,$A20,Transactions!$I:$I,$B$4)) -> 383 | E20: =C20-D20 -> 27 | F20: =IF(D20>=C20*0.98,"Paid",IF(AND($E$4>B20,E20>0),"Overdue",IF(AND(B20-$E$4<=7,B20-$E$4>=0,E20>0),"Due soon","Upcoming"))) -> Overdue | G20: =IFERROR(INDEX('Bills Schedule'!$H$3:$H$200, MATCH($A20, 'Bills Schedule'!$A$3:$A$200,0)),"") -> 0
A21: Offerings | B21: =IF(INDEX('Bills Schedule'!$B$3:$B$200, MATCH($A21, 'Bills Schedule'!$A$3:$A$200,0))="","",IF(INDEX('Bills Schedule'!$B$3:$B$200, MATCH($A21, 'Bills Schedule'!$A$3:$A$200,0))>=26,DATE(YEAR($B$6),MONTH($B$6),INDEX('Bills Schedule'!$B$3:$B$200, MATCH($A21, 'Bills Schedule'!$A$3:$A$200,0))),DATE(YEAR(EDATE($B$6,1)),MONTH(EDATE($B$6,1)),INDEX('Bills Schedule'!$B$3:$B$200, MATCH($A21, 'Bills Schedule'!$A$3:$A$200,0))))) -> 46017 | C21: =INDEX('Bills Schedule'!$C$3:$C$200, MATCH($A21, 'Bills Schedule'!$A$3:$A$200,0)) -> 165 | D21: =IF($A21="Savings Transfer",SUMIFS(Transactions!$E:$E,Transactions!$B:$B,"Transfer",Transactions!$C:$C,$A21,Transactions!$I:$I,$B$4),SUMIFS(Transactions!$E:$E,Transactions!$B:$B,"Expense",Transactions!$C:$C,$A21,Transactions!$I:$I,$B$4)) -> 140 | E21: =C21-D21 -> 25 | F21: =IF(D21>=C21*0.98,"Paid",IF(AND($E$4>B21,E21>0),"Overdue",IF(AND(B21-$E$4<=7,B21-$E$4>=0,E21>0),"Due soon","Upcoming"))) -> Overdue | G21: =IFERROR(INDEX('Bills Schedule'!$H$3:$H$200, MATCH($A21, 'Bills Schedule'!$A$3:$A$200,0)),"") -> 0
... A26: House Keep | B26: =IF(INDEX('Bills Schedule'!$B$3:$B$200, MATCH($A26, 'Bills Schedule'!$A$3:$A$200,0))="","",IF(INDEX('Bills Schedule'!$B$3:$B$200, MATCH($A26, 'Bills Schedule'!$A$3:$A$200,0))>=26,DATE(YEAR($B$6),MONTH($B$6),INDEX('Bills Schedule'!$B$3:$B$200, MATCH($A26, 'Bills Schedule'!$A$3:$A$200,0))),DATE(YEAR(EDATE($B$6,1)),MONTH(EDATE($B$6,1)),INDEX('Bills Schedule'!$B$3:$B$200, MATCH($A26, 'Bills Schedule'!$A$3:$A$200,0))))) -> 46017 | C26: =INDEX('Bills Schedule'!$C$3:$C$200, MATCH($A26, 'Bills Schedule'!$A$3:$A$200,0)) -> 560 | D26: =IF($A26="Savings Transfer",SUMIFS(Transactions!$E:$E,Transactions!$B:$B,"Transfer",Transactions!$C:$C,$A26,Transactions!$I:$I,$B$4),SUMIFS(Transactions!$E:$E,Transactions!$B:$B,"Expense",Transactions!$C:$C,$A26,Transactions!$I:$I,$B$4)) -> 129.97 | E26: =C26-D26 -> 430.03 | F26: =IF(D26>=C26*0.98,"Paid",IF(AND($E$4>B26,E26>0),"Overdue",IF(AND(B26-$E$4<=7,B26-$E$4>=0,E26>0),"Due soon","Upcoming"))) -> Overdue | G26: =IFERROR(INDEX('Bills Schedule'!$H$3:$H$200, MATCH($A26, 'Bills Schedule'!$A$3:$A$200,0)),"") -> 0
A27: One-Off Giving (Christmas) | B27: =IF(INDEX('Bills Schedule'!$B$3:$B$200, MATCH($A27, 'Bills Schedule'!$A$3:$A$200,0))="","",IF(INDEX('Bills Schedule'!$B$3:$B$200, MATCH($A27, 'Bills Schedule'!$A$3:$A$200,0))>=26,DATE(YEAR($B$6),MONTH($B$6),INDEX('Bills Schedule'!$B$3:$B$200, MATCH($A27, 'Bills Schedule'!$A$3:$A$200,0))),DATE(YEAR(EDATE($B$6,1)),MONTH(EDATE($B$6,1)),INDEX('Bills Schedule'!$B$3:$B$200, MATCH($A27, 'Bills Schedule'!$A$3:$A$200,0))))) -> 46017 | C27: =INDEX('Bills Schedule'!$C$3:$C$200, MATCH($A27, 'Bills Schedule'!$A$3:$A$200,0)) -> 500 | D27: =IF($A27="Savings Transfer",SUMIFS(Transactions!$E:$E,Transactions!$B:$B,"Transfer",Transactions!$C:$C,$A27,Transactions!$I:$I,$B$4),SUMIFS(Transactions!$E:$E,Transactions!$B:$B,"Expense",Transactions!$C:$C,$A27,Transactions!$I:$I,$B$4)) -> 457.37 | E27: =C27-D27 -> 42.63 | F27: =IF(D27>=C27*0.91,"Paid",IF(AND($E$4>B27,E27>0),"Overdue",IF(AND(B27-$E$4<=7,B27-$E$4>=0,E27>0),"Due soon","Upcoming"))) -> Paid | G27: =IFERROR(INDEX('Bills Schedule'!$H$3:$H$200, MATCH($A27, 'Bills Schedule'!$A$3:$A$200,0)),"") -> One-Off

Sheet Upcoming Income
A1: Upcoming Income
A2: Finance-style view • Uses Income Schedule • Change As-of date to see next 7/14/30 days
A4: As of date | B4: =Dashboard!E4 -> 46020 | D4: Window (days) | E4: 30 | F4: Try 7 / 14 / 30
A6: Expected (next window) | H6: Source | I6: Amount
A7: FM | E7: McD | H7: FM | I7: =B8 -> 0 | M7: Total
A8: =SUMIFS('Income Schedule'!$C:$C,'Income Schedule'!$B:$B,"FM (26th)",'Income Schedule'!$A:$A,">="&$B$4,'Income Schedule'!$A:$A,"<="&$B$4+$E$4) -> 3500 | E8: =SUMIFS('Income Schedule'!$C:$C,'Income Schedule'!$B:$B,"McD (biweekly)",'Income Schedule'!$A:$A,">="&$B$4,'Income Schedule'!$A:$A,"<="&$B$4+$E$4) -> 800 | H8: McD | I8: =F8 -> 0 | M8: =B8+F8+J8 -> 0
H9: Outlier | I9: =J8 -> 0
A12: Date | B12: Source | C12: Expected | D12: Days away | E12: Period | F12: Notes
A13: =IFERROR(SMALL('Income Schedule'!$H$3:$H$96,1),"") -> 46036 | B13: =IF($A13="","",INDEX('Income Schedule'!$B:$B, MATCH($A13, 'Income Schedule'!$H:$H, 0))) -> Outlier (weekly Wed) | C13: =IF($A13="","",INDEX('Income Schedule'!$C:$C, MATCH($A13, 'Income Schedule'!$H:$H, 0))) -> 100 | D13: =IF($A13="","",$A13-$B$4) -> 16.00045 | E13: =IF($A13="","",INDEX('Income Schedule'!$D:$D, MATCH($A13, 'Income Schedule'!$H:$H, 0))) -> 1 | F13: =IF($A13="","",INDEX('Income Schedule'!$E:$E, MATCH($A13, 'Income Schedule'!$H:$H, 0))) -> Weekly Wednesday
A14: =IFERROR(SMALL('Income Schedule'!$H$3:$H$96,2),"") -> 46037 | B14: =IF($A14="","",INDEX('Income Schedule'!$B:$B, MATCH($A14, 'Income Schedule'!$H:$H, 0))) -> McD (biweekly) | C14: =IF($A14="","",INDEX('Income Schedule'!$C:$C, MATCH($A14, 'Income Schedule'!$H:$H, 0))) -> 400 | D14: =IF($A14="","",$A14-$B$4) -> 17.00018 | E14: =IF($A14="","",INDEX('Income Schedule'!$D:$D, MATCH($A14, 'Income Schedule'!$H:$H, 0))) -> 1 | F14: =IF($A14="","",INDEX('Income Schedule'!$E:$E, MATCH($A14, 'Income Schedule'!$H:$H, 0))) -> Every 2 weeks
A15: =IFERROR(SMALL('Income Schedule'!$H$3:$H$96,3),"") -> 46043 | B15: =IF($A15="","",INDEX('Income Schedule'!$B:$B, MATCH($A15, 'Income Schedule'!$H:$H, 0))) -> Outlier (weekly Wed) | C15: =IF($A15="","",INDEX('Income Schedule'!$C:$C, MATCH($A15, 'Income Schedule'!$H:$H, 0))) -> 100 | D15: =IF($A15="","",$A15-$B$4) -> 23.00046 | E15: =IF($A15="","",INDEX('Income Schedule'!$D:$D, MATCH($A15, 'Income Schedule'!$H:$H, 0))) -> 1 | F15: =IF($A15="","",INDEX('Income Schedule'!$E:$E, MATCH($A15, 'Income Schedule'!$H:$H, 0))) -> Weekly Wednesday
A16: =IFERROR(SMALL('Income Schedule'!$H$3:$H$96,4),"") -> 46050 | B16: =IF($A16="","",INDEX('Income Schedule'!$B:$B, MATCH($A16, 'Income Schedule'!$H:$H, 0))) -> Outlier (weekly Wed) | C16: =IF($A16="","",INDEX('Income Schedule'!$C:$C, MATCH($A16, 'Income Schedule'!$H:$H, 0))) -> 100 | D16: =IF($A16="","",$A16-$B$4) -> 30.00047 | E16: =IF($A16="","",INDEX('Income Schedule'!$D:$D, MATCH($A16, 'Income Schedule'!$H:$H, 0))) -> 2 | F16: =IF($A16="","",INDEX('Income Schedule'!$E:$E, MATCH($A16, 'Income Schedule'!$H:$H, 0))) -> Weekly Wednesday
A17: =IFERROR(SMALL('Income Schedule'!$H$3:$H$96,5),"") -> 46051 | B17: =IF($A17="","",INDEX('Income Schedule'!$B:$B, MATCH($A17, 'Income Schedule'!$H:$H, 0))) -> McD (biweekly) | C17: =IF($A17="","",INDEX('Income Schedule'!$C:$C, MATCH($A17, 'Income Schedule'!$H:$H, 0))) -> 400 | D17: =IF($A17="","",$A17-$B$4) -> 31.00019 | E17: =IF($A17="","",INDEX('Income Schedule'!$D:$D, MATCH($A17, 'Income Schedule'!$H:$H, 0))) -> 2 | F17: =IF($A17="","",INDEX('Income Schedule'!$E:$E, MATCH($A17, 'Income Schedule'!$H:$H, 0))) -> Every 2 weeks
A18: =IFERROR(SMALL('Income Schedule'!$H$3:$H$96,6),"") -> 46057 | B18: =IF($A18="","",INDEX('Income Schedule'!$B:$B, MATCH($A18, 'Income Schedule'!$H:$H, 0))) -> Outlier (weekly Wed) | C18: =IF($A18="","",INDEX('Income Schedule'!$C:$C, MATCH($A18, 'Income Schedule'!$H:$H, 0))) -> 100 | D18: =IF($A18="","",$A18-$B$4) -> 37.00048 | E18: =IF($A18="","",INDEX('Income Schedule'!$D:$D, MATCH($A18, 'Income Schedule'!$H:$H, 0))) -> 2 | F18: =IF($A18="","",INDEX('Income Schedule'!$E:$E, MATCH($A18, 'Income Schedule'!$H:$H, 0))) -> Weekly Wednesday
A19: =IFERROR(SMALL('Income Schedule'!$H$3:$H$96,7),"") -> 46079 | B19: =IF($A19="","",INDEX('Income Schedule'!$B:$B, MATCH($A19, 'Income Schedule'!$H:$H, 0))) -> FM (26th) | C19: =IF($A19="","",INDEX('Income Schedule'!$C:$C, MATCH($A19, 'Income Schedule'!$H:$H, 0))) -> 3500 | D19: =IF($A19="","",$A19-$B$4) -> 59.00006 | E19: =IF($A19="","",INDEX('Income Schedule'!$D:$D, MATCH($A19, 'Income Schedule'!$H:$H, 0))) -> 3 | F19: =IF($A19="","",INDEX('Income Schedule'!$E:$E, MATCH($A19, 'Income Schedule'!$H:$H, 0))) -> Latest by 26th
A20: =IFERROR(SMALL('Income Schedule'!$H$3:$H$96,8),"") | B20: =IF($A20="","",INDEX('Income Schedule'!$B:$B, MATCH($A20, 'Income Schedule'!$H:$H, 0))) | C20: =IF($A20="","",INDEX('Income Schedule'!$C:$C, MATCH($A20, 'Income Schedule'!$H:$H, 0))) | D20: =IF($A20="","",$A20-$B$4) | E20: =IF($A20="","",INDEX('Income Schedule'!$D:$D, MATCH($A20, 'Income Schedule'!$H:$H, 0))) | F20: =IF($A20="","",INDEX('Income Schedule'!$E:$E, MATCH($A20, 'Income Schedule'!$H:$H, 0)))
A21: =IFERROR(SMALL('Income Schedule'!$H$3:$H$96,9),"") | B21: =IF($A21="","",INDEX('Income Schedule'!$B:$B, MATCH($A21, 'Income Schedule'!$H:$H, 0))) | C21: =IF($A21="","",INDEX('Income Schedule'!$C:$C, MATCH($A21, 'Income Schedule'!$H:$H, 0))) | D21: =IF($A21="","",$A21-$B$4) | E21: =IF($A21="","",INDEX('Income Schedule'!$D:$D, MATCH($A21, 'Income Schedule'!$H:$H, 0))) | F21: =IF($A21="","",INDEX('Income Schedule'!$E:$E, MATCH($A21, 'Income Schedule'!$H:$H, 0)))
A22: =IFERROR(SMALL('Income Schedule'!$H$3:$H$96,10),"") | B22: =IF($A22="","",INDEX('Income Schedule'!$B:$B, MATCH($A22, 'Income Schedule'!$H:$H, 0))) | C22: =IF($A22="","",INDEX('Income Schedule'!$C:$C, MATCH($A22, 'Income Schedule'!$H:$H, 0))) | D22: =IF($A22="","",$A22-$B$4) | E22: =IF($A22="","",INDEX('Income Schedule'!$D:$D, MATCH($A22, 'Income Schedule'!$H:$H, 0))) | F22: =IF($A22="","",INDEX('Income Schedule'!$E:$E, MATCH($A22, 'Income Schedule'!$H:$H, 0)))
A23: =IFERROR(SMALL('Income Schedule'!$H$3:$H$96,11),"") | B23: =IF($A23="","",INDEX('Income Schedule'!$B:$B, MATCH($A23, 'Income Schedule'!$H:$H, 0))) | C23: =IF($A23="","",INDEX('Income Schedule'!$C:$C, MATCH($A23, 'Income Schedule'!$H:$H, 0))) | D23: =IF($A23="","",$A23-$B$4) | E23: =IF($A23="","",INDEX('Income Schedule'!$D:$D, MATCH($A23, 'Income Schedule'!$H:$H, 0))) | F23: =IF($A23="","",INDEX('Income Schedule'!$E:$E, MATCH($A23, 'Income Schedule'!$H:$H, 0)))
A24: =IFERROR(SMALL('Income Schedule'!$H$3:$H$96,12),"") | B24: =IF($A24="","",INDEX('Income Schedule'!$B:$B, MATCH($A24, 'Income Schedule'!$H:$H, 0))) | C24: =IF($A24="","",INDEX('Income Schedule'!$C:$C, MATCH($A24, 'Income Schedule'!$H:$H, 0))) | D24: =IF($A24="","",$A24-$B$4) | E24: =IF($A24="","",INDEX('Income Schedule'!$D:$D, MATCH($A24, 'Income Schedule'!$H:$H, 0))) | F24: =IF($A24="","",INDEX('Income Schedule'!$E:$E, MATCH($A24, 'Income Schedule'!$H:$H, 0)))
A25: =IFERROR(SMALL('Income Schedule'!$H$3:$H$96,13),"") | B25: =IF($A25="","",INDEX('Income Schedule'!$B:$B, MATCH($A25, 'Income Schedule'!$H:$H, 0))) | C25: =IF($A25="","",INDEX('Income Schedule'!$C:$C, MATCH($A25, 'Income Schedule'!$H:$H, 0))) | D25: =IF($A25="","",$A25-$B$4) | E25: =IF($A25="","",INDEX('Income Schedule'!$D:$D, MATCH($A25, 'Income Schedule'!$H:$H, 0))) | F25: =IF($A25="","",INDEX('Income Schedule'!$E:$E, MATCH($A25, 'Income Schedule'!$H:$H, 0)))
A26: =IFERROR(SMALL('Income Schedule'!$H$3:$H$96,14),"") | B26: =IF($A26="","",INDEX('Income Schedule'!$B:$B, MATCH($A26, 'Income Schedule'!$H:$H, 0))) | C26: =IF($A26="","",INDEX('Income Schedule'!$C:$C, MATCH($A26, 'Income Schedule'!$H:$H, 0))) | D26: =IF($A26="","",$A26-$B$4) | E26: =IF($A26="","",INDEX('Income Schedule'!$D:$D, MATCH($A26, 'Income Schedule'!$H:$H, 0))) | F26: =IF($A26="","",INDEX('Income Schedule'!$E:$E, MATCH($A26, 'Income Schedule'!$H:$H, 0)))
A27: =IFERROR(SMALL('Income Schedule'!$H$3:$H$96,15),"") | B27: =IF($A27="","",INDEX('Income Schedule'!$B:$B, MATCH($A27, 'Income Schedule'!$H:$H, 0))) | C27: =IF($A27="","",INDEX('Income Schedule'!$C:$C, MATCH($A27, 'Income Schedule'!$H:$H, 0))) | D27: =IF($A27="","",$A27-$B$4) | E27: =IF($A27="","",INDEX('Income Schedule'!$D:$D, MATCH($A27, 'Income Schedule'!$H:$H, 0))) | F27: =IF($A27="","",INDEX('Income Schedule'!$E:$E, MATCH($A27, 'Income Schedule'!$H:$H, 0)))
A28: =IFERROR(SMALL('Income Schedule'!$H$3:$H$96,16),"") | B28: =IF($A28="","",INDEX('Income Schedule'!$B:$B, MATCH($A28, 'Income Schedule'!$H:$H, 0))) | C28: =IF($A28="","",INDEX('Income Schedule'!$C:$C, MATCH($A28, 'Income Schedule'!$H:$H, 0))) | D28: =IF($A28="","",$A28-$B$4) | E28: =IF($A28="","",INDEX('Income Schedule'!$D:$D, MATCH($A28, 'Income Schedule'!$H:$H, 0))) | F28: =IF($A28="","",INDEX('Income Schedule'!$E:$E, MATCH($A28, 'Income Schedule'!$H:$H, 0)))
A29: =IFERROR(SMALL('Income Schedule'!$H$3:$H$96,17),"") | B29: =IF($A29="","",INDEX('Income Schedule'!$B:$B, MATCH($A29, 'Income Schedule'!$H:$H, 0))) | C29: =IF($A29="","",INDEX('Income Schedule'!$C:$C, MATCH($A29, 'Income Schedule'!$H:$H, 0))) | D29: =IF($A29="","",$A29-$B$4) | E29: =IF($A29="","",INDEX('Income Schedule'!$D:$D, MATCH($A29, 'Income Schedule'!$H:$H, 0))) | F29: =IF($A29="","",INDEX('Income Schedule'!$E:$E, MATCH($A29, 'Income Schedule'!$H:$H, 0)))
A30: =IFERROR(SMALL('Income Schedule'!$H$3:$H$96,18),"") | B30: =IF($A30="","",INDEX('Income Schedule'!$B:$B, MATCH($A30, 'Income Schedule'!$H:$H, 0))) | C30: =IF($A30="","",INDEX('Income Schedule'!$C:$C, MATCH($A30, 'Income Schedule'!$H:$H, 0))) | D30: =IF($A30="","",$A30-$B$4) | E30: =IF($A30="","",INDEX('Income Schedule'!$D:$D, MATCH($A30, 'Income Schedule'!$H:$H, 0))) | F30: =IF($A30="","",INDEX('Income Schedule'!$E:$E, MATCH($A30, 'Income Schedule'!$H:$H, 0)))
A31: =IFERROR(SMALL('Income Schedule'!$H$3:$H$96,19),"") | B31: =IF($A31="","",INDEX('Income Schedule'!$B:$B, MATCH($A31, 'Income Schedule'!$H:$H, 0))) | C31: =IF($A31="","",INDEX('Income Schedule'!$C:$C, MATCH($A31, 'Income Schedule'!$H:$H, 0))) | D31: =IF($A31="","",$A31-$B$4) | E31: =IF($A31="","",INDEX('Income Schedule'!$D:$D, MATCH($A31, 'Income Schedule'!$H:$H, 0))) | F31: =IF($A31="","",INDEX('Income Schedule'!$E:$E, MATCH($A31, 'Income Schedule'!$H:$H, 0)))
A32: =IFERROR(SMALL('Income Schedule'!$H$3:$H$96,20),"") | B32: =IF($A32="","",INDEX('Income Schedule'!$B:$B, MATCH($A32, 'Income Schedule'!$H:$H, 0))) | C32: =IF($A32="","",INDEX('Income Schedule'!$C:$C, MATCH($A32, 'Income Schedule'!$H:$H, 0))) | D32: =IF($A32="","",$A32-$B$4) | E32: =IF($A32="","",INDEX('Income Schedule'!$D:$D, MATCH($A32, 'Income Schedule'!$H:$H, 0))) | F32: =IF($A32="","",INDEX('Income Schedule'!$E:$E, MATCH($A32, 'Income Schedule'!$H:$H, 0)))
A33: =IFERROR(SMALL('Income Schedule'!$H$3:$H$96,21),"") | B33: =IF($A33="","",INDEX('Income Schedule'!$B:$B, MATCH($A33, 'Income Schedule'!$H:$H, 0))) | C33: =IF($A33="","",INDEX('Income Schedule'!$C:$C, MATCH($A33, 'Income Schedule'!$H:$H, 0))) | D33: =IF($A33="","",$A33-$B$4) | E33: =IF($A33="","",INDEX('Income Schedule'!$D:$D, MATCH($A33, 'Income Schedule'!$H:$H, 0))) | F33: =IF($A33="","",INDEX('Income Schedule'!$E:$E, MATCH($A33, 'Income Schedule'!$H:$H, 0)))
A34: =IFERROR(SMALL('Income Schedule'!$H$3:$H$96,22),"") | B34: =IF($A34="","",INDEX('Income Schedule'!$B:$B, MATCH($A34, 'Income Schedule'!$H:$H, 0))) | C34: =IF($A34="","",INDEX('Income Schedule'!$C:$C, MATCH($A34, 'Income Schedule'!$H:$H, 0))) | D34: =IF($A34="","",$A34-$B$4) | E34: =IF($A34="","",INDEX('Income Schedule'!$D:$D, MATCH($A34, 'Income Schedule'!$H:$H, 0))) | F34: =IF($A34="","",INDEX('Income Schedule'!$E:$E, MATCH($A34, 'Income Schedule'!$H:$H, 0)))
A35: =IFERROR(SMALL('Income Schedule'!$H$3:$H$96,23),"") | B35: =IF($A35="","",INDEX('Income Schedule'!$B:$B, MATCH($A35, 'Income Schedule'!$H:$H, 0))) | C35: =IF($A35="","",INDEX('Income Schedule'!$C:$C, MATCH($A35, 'Income Schedule'!$H:$H, 0))) | D35: =IF($A35="","",$A35-$B$4) | E35: =IF($A35="","",INDEX('Income Schedule'!$D:$D, MATCH($A35, 'Income Schedule'!$H:$H, 0))) | F35: =IF($A35="","",INDEX('Income Schedule'!$E:$E, MATCH($A35, 'Income Schedule'!$H:$H, 0)))
A36: =IFERROR(SMALL('Income Schedule'!$H$3:$H$96,24),"") | B36: =IF($A36="","",INDEX('Income Schedule'!$B:$B, MATCH($A36, 'Income Schedule'!$H:$H, 0))) | C36: =IF($A36="","",INDEX('Income Schedule'!$C:$C, MATCH($A36, 'Income Schedule'!$H:$H, 0))) | D36: =IF($A36="","",$A36-$B$4) | E36: =IF($A36="","",INDEX('Income Schedule'!$D:$D, MATCH($A36, 'Income Schedule'!$H:$H, 0))) | F36: =IF($A36="","",INDEX('Income Schedule'!$E:$E, MATCH($A36, 'Income Schedule'!$H:$H, 0)))
A37: =IFERROR(SMALL('Income Schedule'!$H$3:$H$96,25),"") | B37: =IF($A37="","",INDEX('Income Schedule'!$B:$B, MATCH($A37, 'Income Schedule'!$H:$H, 0))) | C37: =IF($A37="","",INDEX('Income Schedule'!$C:$C, MATCH($A37, 'Income Schedule'!$H:$H, 0))) | D37: =IF($A37="","",$A37-$B$4) | E37: =IF($A37="","",INDEX('Income Schedule'!$D:$D, MATCH($A37, 'Income Schedule'!$H:$H, 0))) | F37: =IF($A37="","",INDEX('Income Schedule'!$E:$E, MATCH($A37, 'Income Schedule'!$H:$H, 0)))
A38: =IFERROR(SMALL('Income Schedule'!$H$3:$H$96,26),"") | B38: =IF($A38="","",INDEX('Income Schedule'!$B:$B, MATCH($A38, 'Income Schedule'!$H:$H, 0))) | C38: =IF($A38="","",INDEX('Income Schedule'!$C:$C, MATCH($A38, 'Income Schedule'!$H:$H, 0))) | D38: =IF($A38="","",$A38-$B$4) | E38: =IF($A38="","",INDEX('Income Schedule'!$D:$D, MATCH($A38, 'Income Schedule'!$H:$H, 0))) | F38: =IF($A38="","",INDEX('Income Schedule'!$E:$E, MATCH($A38, 'Income Schedule'!$H:$H, 0)))
A39: =IFERROR(SMALL('Income Schedule'!$H$3:$H$96,27),"") | B39: =IF($A39="","",INDEX('Income Schedule'!$B:$B, MATCH($A39, 'Income Schedule'!$H:$H, 0))) | C39: =IF($A39="","",INDEX('Income Schedule'!$C:$C, MATCH($A39, 'Income Schedule'!$H:$H, 0))) | D39: =IF($A39="","",$A39-$B$4) | E39: =IF($A39="","",INDEX('Income Schedule'!$D:$D, MATCH($A39, 'Income Schedule'!$H:$H, 0))) | F39: =IF($A39="","",INDEX('Income Schedule'!$E:$E, MATCH($A39, 'Income Schedule'!$H:$H, 0)))
A40: =IFERROR(SMALL('Income Schedule'!$H$3:$H$96,28),"") | B40: =IF($A40="","",INDEX('Income Schedule'!$B:$B, MATCH($A40, 'Income Schedule'!$H:$H, 0))) | C40: =IF($A40="","",INDEX('Income Schedule'!$C:$C, MATCH($A40, 'Income Schedule'!$H:$H, 0))) | D40: =IF($A40="","",$A40-$B$4) | E40: =IF($A40="","",INDEX('Income Schedule'!$D:$D, MATCH($A40, 'Income Schedule'!$H:$H, 0))) | F40: =IF($A40="","",INDEX('Income Schedule'!$E:$E, MATCH($A40, 'Income Schedule'!$H:$H, 0)))
A41: =IFERROR(SMALL('Income Schedule'!$H$3:$H$96,29),"") | B41: =IF($A41="","",INDEX('Income Schedule'!$B:$B, MATCH($A41, 'Income Schedule'!$H:$H, 0))) | C41: =IF($A41="","",INDEX('Income Schedule'!$C:$C, MATCH($A41, 'Income Schedule'!$H:$H, 0))) | D41: =IF($A41="","",$A41-$B$4) | E41: =IF($A41="","",INDEX('Income Schedule'!$D:$D, MATCH($A41, 'Income Schedule'!$H:$H, 0))) | F41: =IF($A41="","",INDEX('Income Schedule'!$E:$E, MATCH($A41, 'Income Schedule'!$H:$H, 0)))
A42: =IFERROR(SMALL('Income Schedule'!$H$3:$H$96,30),"") | B42: =IF($A42="","",INDEX('Income Schedule'!$B:$B, MATCH($A42, 'Income Schedule'!$H:$H, 0))) | C42: =IF($A42="","",INDEX('Income Schedule'!$C:$C, MATCH($A42, 'Income Schedule'!$H:$H, 0))) | D42: =IF($A42="","",$A42-$B$4) | E42: =IF($A42="","",INDEX('Income Schedule'!$D:$D, MATCH($A42, 'Income Schedule'!$H:$H, 0))) | F42: =IF($A42="","",INDEX('Income Schedule'!$E:$E, MATCH($A42, 'Income Schedule'!$H:$H, 0)))
A43: =IFERROR(SMALL('Income Schedule'!$H$3:$H$96,31),"") | B43: =IF($A43="","",INDEX('Income Schedule'!$B:$B, MATCH($A43, 'Income Schedule'!$H:$H, 0))) | C43: =IF($A43="","",INDEX('Income Schedule'!$C:$C, MATCH($A43, 'Income Schedule'!$H:$H, 0))) | D43: =IF($A43="","",$A43-$B$4) | E43: =IF($A43="","",INDEX('Income Schedule'!$D:$D, MATCH($A43, 'Income Schedule'!$H:$H, 0))) | F43: =IF($A43="","",INDEX('Income Schedule'!$E:$E, MATCH($A43, 'Income Schedule'!$H:$H, 0)))
A44: =IFERROR(SMALL('Income Schedule'!$H$3:$H$96,32),"") | B44: =IF($A44="","",INDEX('Income Schedule'!$B:$B, MATCH($A44, 'Income Schedule'!$H:$H, 0))) | C44: =IF($A44="","",INDEX('Income Schedule'!$C:$C, MATCH($A44, 'Income Schedule'!$H:$H, 0))) | D44: =IF($A44="","",$A44-$B$4) | E44: =IF($A44="","",INDEX('Income Schedule'!$D:$D, MATCH($A44, 'Income Schedule'!$H:$H, 0))) | F44: =IF($A44="","",INDEX('Income Schedule'!$E:$E, MATCH($A44, 'Income Schedule'!$H:$H, 0)))
A45: =IFERROR(SMALL('Income Schedule'!$H$3:$H$96,33),"") | B45: =IF($A45="","",INDEX('Income Schedule'!$B:$B, MATCH($A45, 'Income Schedule'!$H:$H, 0))) | C45: =IF($A45="","",INDEX('Income Schedule'!$C:$C, MATCH($A45, 'Income Schedule'!$H:$H, 0))) | D45: =IF($A45="","",$A45-$B$4) | E45: =IF($A45="","",INDEX('Income Schedule'!$D:$D, MATCH($A45, 'Income Schedule'!$H:$H, 0))) | F45: =IF($A45="","",INDEX('Income Schedule'!$E:$E, MATCH($A45, 'Income Schedule'!$H:$H, 0)))
A46: =IFERROR(SMALL('Income Schedule'!$H$3:$H$96,34),"") | B46: =IF($A46="","",INDEX('Income Schedule'!$B:$B, MATCH($A46, 'Income Schedule'!$H:$H, 0))) | C46: =IF($A46="","",INDEX('Income Schedule'!$C:$C, MATCH($A46, 'Income Schedule'!$H:$H, 0))) | D46: =IF($A46="","",$A46-$B$4) | E46: =IF($A46="","",INDEX('Income Schedule'!$D:$D, MATCH($A46, 'Income Schedule'!$H:$H, 0))) | F46: =IF($A46="","",INDEX('Income Schedule'!$E:$E, MATCH($A46, 'Income Schedule'!$H:$H, 0)))
A47: =IFERROR(SMALL('Income Schedule'!$H$3:$H$96,35),"") | B47: =IF($A47="","",INDEX('Income Schedule'!$B:$B, MATCH($A47, 'Income Schedule'!$H:$H, 0))) | C47: =IF($A47="","",INDEX('Income Schedule'!$C:$C, MATCH($A47, 'Income Schedule'!$H:$H, 0))) | D47: =IF($A47="","",$A47-$B$4) | E47: =IF($A47="","",INDEX('Income Schedule'!$D:$D, MATCH($A47, 'Income Schedule'!$H:$H, 0))) | F47: =IF($A47="","",INDEX('Income Schedule'!$E:$E, MATCH($A47, 'Income Schedule'!$H:$H, 0)))
A48: =IFERROR(SMALL('Income Schedule'!$H$3:$H$96,36),"") | B48: =IF($A48="","",INDEX('Income Schedule'!$B:$B, MATCH($A48, 'Income Schedule'!$H:$H, 0))) | C48: =IF($A48="","",INDEX('Income Schedule'!$C:$C, MATCH($A48, 'Income Schedule'!$H:$H, 0))) | D48: =IF($A48="","",$A48-$B$4) | E48: =IF($A48="","",INDEX('Income Schedule'!$D:$D, MATCH($A48, 'Income Schedule'!$H:$H, 0))) | F48: =IF($A48="","",INDEX('Income Schedule'!$E:$E, MATCH($A48, 'Income Schedule'!$H:$H, 0)))
A49: =IFERROR(SMALL('Income Schedule'!$H$3:$H$96,37),"") | B49: =IF($A49="","",INDEX('Income Schedule'!$B:$B, MATCH($A49, 'Income Schedule'!$H:$H, 0))) | C49: =IF($A49="","",INDEX('Income Schedule'!$C:$C, MATCH($A49, 'Income Schedule'!$H:$H, 0))) | D49: =IF($A49="","",$A49-$B$4) | E49: =IF($A49="","",INDEX('Income Schedule'!$D:$D, MATCH($A49, 'Income Schedule'!$H:$H, 0))) | F49: =IF($A49="","",INDEX('Income Schedule'!$E:$E, MATCH($A49, 'Income Schedule'!$H:$H, 0)))
A50: =IFERROR(SMALL('Income Schedule'!$H$3:$H$96,38),"") | B50: =IF($A50="","",INDEX('Income Schedule'!$B:$B, MATCH($A50, 'Income Schedule'!$H:$H, 0))) | C50: =IF($A50="","",INDEX('Income Schedule'!$C:$C, MATCH($A50, 'Income Schedule'!$H:$H, 0))) | D50: =IF($A50="","",$A50-$B$4) | E50: =IF($A50="","",INDEX('Income Schedule'!$D:$D, MATCH($A50, 'Income Schedule'!$H:$H, 0))) | F50: =IF($A50="","",INDEX('Income Schedule'!$E:$E, MATCH($A50, 'Income Schedule'!$H:$H, 0)))
A51: =IFERROR(SMALL('Income Schedule'!$H$3:$H$96,39),"") | B51: =IF($A51="","",INDEX('Income Schedule'!$B:$B, MATCH($A51, 'Income Schedule'!$H:$H, 0))) | C51: =IF($A51="","",INDEX('Income Schedule'!$C:$C, MATCH($A51, 'Income Schedule'!$H:$H, 0))) | D51: =IF($A51="","",$A51-$B$4) | E51: =IF($A51="","",INDEX('Income Schedule'!$D:$D, MATCH($A51, 'Income Schedule'!$H:$H, 0))) | F51: =IF($A51="","",INDEX('Income Schedule'!$E:$E, MATCH($A51, 'Income Schedule'!$H:$H, 0)))
A52: =IFERROR(SMALL('Income Schedule'!$H$3:$H$96,40),"") | B52: =IF($A52="","",INDEX('Income Schedule'!$B:$B, MATCH($A52, 'Income Schedule'!$H:$H, 0))) | C52: =IF($A52="","",INDEX('Income Schedule'!$C:$C, MATCH($A52, 'Income Schedule'!$H:$H, 0))) | D52: =IF($A52="","",$A52-$B$4) | E52: =IF($A52="","",INDEX('Income Schedule'!$D:$D, MATCH($A52, 'Income Schedule'!$H:$H, 0))) | F52: =IF($A52="","",INDEX('Income Schedule'!$E:$E, MATCH($A52, 'Income Schedule'!$H:$H, 0)))
A53: =IFERROR(SMALL('Income Schedule'!$H$3:$H$96,41),"") | B53: =IF($A53="","",INDEX('Income Schedule'!$B:$B, MATCH($A53, 'Income Schedule'!$H:$H, 0))) | C53: =IF($A53="","",INDEX('Income Schedule'!$C:$C, MATCH($A53, 'Income Schedule'!$H:$H, 0))) | D53: =IF($A53="","",$A53-$B$4) | E53: =IF($A53="","",INDEX('Income Schedule'!$D:$D, MATCH($A53, 'Income Schedule'!$H:$H, 0))) | F53: =IF($A53="","",INDEX('Income Schedule'!$E:$E, MATCH($A53, 'Income Schedule'!$H:$H, 0)))
A54: =IFERROR(SMALL('Income Schedule'!$H$3:$H$96,42),"") | B54: =IF($A54="","",INDEX('Income Schedule'!$B:$B, MATCH($A54, 'Income Schedule'!$H:$H, 0))) | C54: =IF($A54="","",INDEX('Income Schedule'!$C:$C, MATCH($A54, 'Income Schedule'!$H:$H, 0))) | D54: =IF($A54="","",$A54-$B$4) | E54: =IF($A54="","",INDEX('Income Schedule'!$D:$D, MATCH($A54, 'Income Schedule'!$H:$H, 0))) | F54: =IF($A54="","",INDEX('Income Schedule'!$E:$E, MATCH($A54, 'Income Schedule'!$H:$H, 0)))
A55: =IFERROR(SMALL('Income Schedule'!$H$3:$H$96,43),"") | B55: =IF($A55="","",INDEX('Income Schedule'!$B:$B, MATCH($A55, 'Income Schedule'!$H:$H, 0))) | C55: =IF($A55="","",INDEX('Income Schedule'!$C:$C, MATCH($A55, 'Income Schedule'!$H:$H, 0))) | D55: =IF($A55="","",$A55-$B$4) | E55: =IF($A55="","",INDEX('Income Schedule'!$D:$D, MATCH($A55, 'Income Schedule'!$H:$H, 0))) | F55: =IF($A55="","",INDEX('Income Schedule'!$E:$E, MATCH($A55, 'Income Schedule'!$H:$H, 0)))
A56: =IFERROR(SMALL('Income Schedule'!$H$3:$H$96,44),"") | B56: =IF($A56="","",INDEX('Income Schedule'!$B:$B, MATCH($A56, 'Income Schedule'!$H:$H, 0))) | C56: =IF($A56="","",INDEX('Income Schedule'!$C:$C, MATCH($A56, 'Income Schedule'!$H:$H, 0))) | D56: =IF($A56="","",$A56-$B$4) | E56: =IF($A56="","",INDEX('Income Schedule'!$D:$D, MATCH($A56, 'Income Schedule'!$H:$H, 0))) | F56: =IF($A56="","",INDEX('Income Schedule'!$E:$E, MATCH($A56, 'Income Schedule'!$H:$H, 0)))
A57: =IFERROR(SMALL('Income Schedule'!$H$3:$H$96,45),"") | B57: =IF($A57="","",INDEX('Income Schedule'!$B:$B, MATCH($A57, 'Income Schedule'!$H:$H, 0))) | C57: =IF($A57="","",INDEX('Income Schedule'!$C:$C, MATCH($A57, 'Income Schedule'!$H:$H, 0))) | D57: =IF($A57="","",$A57-$B$4) | E57: =IF($A57="","",INDEX('Income Schedule'!$D:$D, MATCH($A57, 'Income Schedule'!$H:$H, 0))) | F57: =IF($A57="","",INDEX('Income Schedule'!$E:$E, MATCH($A57, 'Income Schedule'!$H:$H, 0)))
A58: =IFERROR(SMALL('Income Schedule'!$H$3:$H$96,46),"") | B58: =IF($A58="","",INDEX('Income Schedule'!$B:$B, MATCH($A58, 'Income Schedule'!$H:$H, 0))) | C58: =IF($A58="","",INDEX('Income Schedule'!$C:$C, MATCH($A58, 'Income Schedule'!$H:$H, 0))) | D58: =IF($A58="","",$A58-$B$4) | E58: =IF($A58="","",INDEX('Income Schedule'!$D:$D, MATCH($A58, 'Income Schedule'!$H:$H, 0))) | F58: =IF($A58="","",INDEX('Income Schedule'!$E:$E, MATCH($A58, 'Income Schedule'!$H:$H, 0)))
A59: =IFERROR(SMALL('Income Schedule'!$H$3:$H$96,47),"") | B59: =IF($A59="","",INDEX('Income Schedule'!$B:$B, MATCH($A59, 'Income Schedule'!$H:$H, 0))) | C59: =IF($A59="","",INDEX('Income Schedule'!$C:$C, MATCH($A59, 'Income Schedule'!$H:$H, 0))) | D59: =IF($A59="","",$A59-$B$4) | E59: =IF($A59="","",INDEX('Income Schedule'!$D:$D, MATCH($A59, 'Income Schedule'!$H:$H, 0))) | F59: =IF($A59="","",INDEX('Income Schedule'!$E:$E, MATCH($A59, 'Income Schedule'!$H:$H, 0)))
A60: =IFERROR(SMALL('Income Schedule'!$H$3:$H$96,48),"") | B60: =IF($A60="","",INDEX('Income Schedule'!$B:$B, MATCH($A60, 'Income Schedule'!$H:$H, 0))) | C60: =IF($A60="","",INDEX('Income Schedule'!$C:$C, MATCH($A60, 'Income Schedule'!$H:$H, 0))) | D60: =IF($A60="","",$A60-$B$4) | E60: =IF($A60="","",INDEX('Income Schedule'!$D:$D, MATCH($A60, 'Income Schedule'!$H:$H, 0))) | F60: =IF($A60="","",INDEX('Income Schedule'!$E:$E, MATCH($A60, 'Income Schedule'!$H:$H, 0)))
A61: =IFERROR(SMALL('Income Schedule'!$H$3:$H$96,49),"") | B61: =IF($A61="","",INDEX('Income Schedule'!$B:$B, MATCH($A61, 'Income Schedule'!$H:$H, 0))) | C61: =IF($A61="","",INDEX('Income Schedule'!$C:$C, MATCH($A61, 'Income Schedule'!$H:$H, 0))) | D61: =IF($A61="","",$A61-$B$4) | E61: =IF($A61="","",INDEX('Income Schedule'!$D:$D, MATCH($A61, 'Income Schedule'!$H:$H, 0))) | F61: =IF($A61="","",INDEX('Income Schedule'!$E:$E, MATCH($A61, 'Income Schedule'!$H:$H, 0)))
A62: =IFERROR(SMALL('Income Schedule'!$H$3:$H$96,50),"") | B62: =IF($A62="","",INDEX('Income Schedule'!$B:$B, MATCH($A62, 'Income Schedule'!$H:$H, 0))) | C62: =IF($A62="","",INDEX('Income Schedule'!$C:$C, MATCH($A62, 'Income Schedule'!$H:$H, 0))) | D62: =IF($A62="","",$A62-$B$4) | E62: =IF($A62="","",INDEX('Income Schedule'!$D:$D, MATCH($A62, 'Income Schedule'!$H:$H, 0))) | F62: =IF($A62="","",INDEX('Income Schedule'!$E:$E, MATCH($A62, 'Income Schedule'!$H:$H, 0)))
A63: =IFERROR(SMALL('Income Schedule'!$H$3:$H$96,51),"") | B63: =IF($A63="","",INDEX('Income Schedule'!$B:$B, MATCH($A63, 'Income Schedule'!$H:$H, 0))) | C63: =IF($A63="","",INDEX('Income Schedule'!$C:$C, MATCH($A63, 'Income Schedule'!$H:$H, 0))) | D63: =IF($A63="","",$A63-$B$4) | E63: =IF($A63="","",INDEX('Income Schedule'!$D:$D, MATCH($A63, 'Income Schedule'!$H:$H, 0))) | F63: =IF($A63="","",INDEX('Income Schedule'!$E:$E, MATCH($A63, 'Income Schedule'!$H:$H, 0)))
A64: =IFERROR(SMALL('Income Schedule'!$H$3:$H$96,52),"") | B64: =IF($A64="","",INDEX('Income Schedule'!$B:$B, MATCH($A64, 'Income Schedule'!$H:$H, 0))) | C64: =IF($A64="","",INDEX('Income Schedule'!$C:$C, MATCH($A64, 'Income Schedule'!$H:$H, 0))) | D64: =IF($A64="","",$A64-$B$4) | E64: =IF($A64="","",INDEX('Income Schedule'!$D:$D, MATCH($A64, 'Income Schedule'!$H:$H, 0))) | F64: =IF($A64="","",INDEX('Income Schedule'!$E:$E, MATCH($A64, 'Income Schedule'!$H:$H, 0)))
A65: =IFERROR(SMALL('Income Schedule'!$H$3:$H$96,53),"") | B65: =IF($A65="","",INDEX('Income Schedule'!$B:$B, MATCH($A65, 'Income Schedule'!$H:$H, 0))) | C65: =IF($A65="","",INDEX('Income Schedule'!$C:$C, MATCH($A65, 'Income Schedule'!$H:$H, 0))) | D65: =IF($A65="","",$A65-$B$4) | E65: =IF($A65="","",INDEX('Income Schedule'!$D:$D, MATCH($A65, 'Income Schedule'!$H:$H, 0))) | F65: =IF($A65="","",INDEX('Income Schedule'!$E:$E, MATCH($A65, 'Income Schedule'!$H:$H, 0)))
A66: =IFERROR(SMALL('Income Schedule'!$H$3:$H$96,54),"") | B66: =IF($A66="","",INDEX('Income Schedule'!$B:$B, MATCH($A66, 'Income Schedule'!$H:$H, 0))) | C66: =IF($A66="","",INDEX('Income Schedule'!$C:$C, MATCH($A66, 'Income Schedule'!$H:$H, 0))) | D66: =IF($A66="","",$A66-$B$4) | E66: =IF($A66="","",INDEX('Income Schedule'!$D:$D, MATCH($A66, 'Income Schedule'!$H:$H, 0))) | F66: =IF($A66="","",INDEX('Income Schedule'!$E:$E, MATCH($A66, 'Income Schedule'!$H:$H, 0)))
A67: =IFERROR(SMALL('Income Schedule'!$H$3:$H$96,55),"") | B67: =IF($A67="","",INDEX('Income Schedule'!$B:$B, MATCH($A67, 'Income Schedule'!$H:$H, 0))) | C67: =IF($A67="","",INDEX('Income Schedule'!$C:$C, MATCH($A67, 'Income Schedule'!$H:$H, 0))) | D67: =IF($A67="","",$A67-$B$4) | E67: =IF($A67="","",INDEX('Income Schedule'!$D:$D, MATCH($A67, 'Income Schedule'!$H:$H, 0))) | F67: =IF($A67="","",INDEX('Income Schedule'!$E:$E, MATCH($A67, 'Income Schedule'!$H:$H, 0)))
A68: =IFERROR(SMALL('Income Schedule'!$H$3:$H$96,56),"") | B68: =IF($A68="","",INDEX('Income Schedule'!$B:$B, MATCH($A68, 'Income Schedule'!$H:$H, 0))) | C68: =IF($A68="","",INDEX('Income Schedule'!$C:$C, MATCH($A68, 'Income Schedule'!$H:$H, 0))) | D68: =IF($A68="","",$A68-$B$4) | E68: =IF($A68="","",INDEX('Income Schedule'!$D:$D, MATCH($A68, 'Income Schedule'!$H:$H, 0))) | F68: =IF($A68="","",INDEX('Income Schedule'!$E:$E, MATCH($A68, 'Income Schedule'!$H:$H, 0)))
A69: =IFERROR(SMALL('Income Schedule'!$H$3:$H$96,57),"") | B69: =IF($A69="","",INDEX('Income Schedule'!$B:$B, MATCH($A69, 'Income Schedule'!$H:$H, 0))) | C69: =IF($A69="","",INDEX('Income Schedule'!$C:$C, MATCH($A69, 'Income Schedule'!$H:$H, 0))) | D69: =IF($A69="","",$A69-$B$4) | E69: =IF($A69="","",INDEX('Income Schedule'!$D:$D, MATCH($A69, 'Income Schedule'!$H:$H, 0))) | F69: =IF($A69="","",INDEX('Income Schedule'!$E:$E, MATCH($A69, 'Income Schedule'!$H:$H, 0)))
A70: =IFERROR(SMALL('Income Schedule'!$H$3:$H$96,58),"") | B70: =IF($A70="","",INDEX('Income Schedule'!$B:$B, MATCH($A70, 'Income Schedule'!$H:$H, 0))) | C70: =IF($A70="","",INDEX('Income Schedule'!$C:$C, MATCH($A70, 'Income Schedule'!$H:$H, 0))) | D70: =IF($A70="","",$A70-$B$4) | E70: =IF($A70="","",INDEX('Income Schedule'!$D:$D, MATCH($A70, 'Income Schedule'!$H:$H, 0))) | F70: =IF($A70="","",INDEX('Income Schedule'!$E:$E, MATCH($A70, 'Income Schedule'!$H:$H, 0)))
A71: =IFERROR(SMALL('Income Schedule'!$H$3:$H$96,59),"") | B71: =IF($A71="","",INDEX('Income Schedule'!$B:$B, MATCH($A71, 'Income Schedule'!$H:$H, 0))) | C71: =IF($A71="","",INDEX('Income Schedule'!$C:$C, MATCH($A71, 'Income Schedule'!$H:$H, 0))) | D71: =IF($A71="","",$A71-$B$4) | E71: =IF($A71="","",INDEX('Income Schedule'!$D:$D, MATCH($A71, 'Income Schedule'!$H:$H, 0))) | F71: =IF($A71="","",INDEX('Income Schedule'!$E:$E, MATCH($A71, 'Income Schedule'!$H:$H, 0)))
A72: =IFERROR(SMALL('Income Schedule'!$H$3:$H$96,60),"") | B72: =IF($A72="","",INDEX('Income Schedule'!$B:$B, MATCH($A72, 'Income Schedule'!$H:$H, 0))) | C72: =IF($A72="","",INDEX('Income Schedule'!$C:$C, MATCH($A72, 'Income Schedule'!$H:$H, 0))) | D72: =IF($A72="","",$A72-$B$4) | E72: =IF($A72="","",INDEX('Income Schedule'!$D:$D, MATCH($A72, 'Income Schedule'!$H:$H, 0))) | F72: =IF($A72="","",INDEX('Income Schedule'!$E:$E, MATCH($A72, 'Income Schedule'!$H:$H, 0)))

Sheet Cashflow Timeline
A1: Cashflow Timeline
A2: Apple Finance style • Expected balance movement (income schedule + bills due) • Set start balance + window
A4: As of date | B4: =Dashboard!E4 -> 46020 | D4: Window (days) | E4: ='Upcoming Income'!E4 -> 30 | G4: Starting balance (£) | H4: 0
A6: Expected net change (window) | E6: Expected ending balance | I6: Expected income (window) | M6: Expected bills (window)
A7: =SUM(E12:E500) -> 3607 | E7: =H4+SUM(E12:E500) -> 3607 | I7: =SUM(C12:C500) -> 4700 | M7: =SUM(D12:D500) -> 1093
A9: Expected minimum balance (window) | E9: Date of minimum balance | I9: Days until minimum | M9: Alert
A10: =_xludf.AGGREGATE(15,6,$H$12:$H$131,1) -> #NAME? | E10: =IFERROR(INDEX($A$12:$A$131, MATCH(_xludf.AGGREGATE(15,6,$H$12:$H$131,1), $H$12:$H$131, 0)),"") | I10: =IF($E$10="","",$E$10-$B$4) | M10: =IF(_xludf.AGGREGATE(15,6,$H$12:$H$131,1)<0,"ALERT: projected below £0","OK: stays above £0") -> #NAME?
A11: Date | B11: Day | C11: Expected Income | D11: Expected Bills | E11: Net Flow | F11: Running Balance | G11: Notes | H11: Balance_for_Min
A12: =IF(1>$E$4,"",$B$4+1-1) -> 46020 | B12: =IF($A12="","",TEXT($A12,"ddd")) -> Mon | C12: =IF($A12="","",SUMIFS('Income Schedule'!$C:$C,'Income Schedule'!$A:$A,$A12)) -> 0 | D12: =IF($A12="","",SUMIFS('Upcoming Bills'!$C:$C,'Upcoming Bills'!$B:$B,$A12)) -> 1093 | E12: =IF($A12="","",C12-D12) -> -1093 | F12: =IF($A12="","",$H$4+E12) -> -1093 | G12: =IF($A12="","",IF(C12>0,"Income","")&IF(AND(C12>0,D12>0)," • ","")&IF(D12>0,"Bills","")) -> Bills | H12: =IF($A12="",NA(),$F12) -> -1093
A13: =IF(2>$E$4,"",$B$4+2-1) -> 46021 | B13: =IF($A13="","",TEXT($A13,"ddd")) -> Tue | C13: =IF($A13="","",SUMIFS('Income Schedule'!$C:$C,'Income Schedule'!$A:$A,$A13)) -> 0 | D13: =IF($A13="","",SUMIFS('Upcoming Bills'!$C:$C,'Upcoming Bills'!$B:$B,$A13)) -> 0 | E13: =IF($A13="","",C13-D13) -> 0 | F13: =IF($A13="","",F12+E13) -> -1093 | G13: =IF($A13="","",IF(C13>0,"Income","")&IF(AND(C13>0,D13>0)," • ","")&IF(D13>0,"Bills","")) | H13: =IF($A13="",NA(),$F13) -> -1093
A14: =IF(3>$E$4,"",$B$4+3-1) -> 46022 | B14: =IF($A14="","",TEXT($A14,"ddd")) -> Wed | C14: =IF($A14="","",SUMIFS('Income Schedule'!$C:$C,'Income Schedule'!$A:$A,$A14)) -> 100 | D14: =IF($A14="","",SUMIFS('Upcoming Bills'!$C:$C,'Upcoming Bills'!$B:$B,$A14)) -> 0 | E14: =IF($A14="","",C14-D14) -> 100 | F14: =IF($A14="","",F13+E14) -> -993 | G14: =IF($A14="","",IF(C14>0,"Income","")&IF(AND(C14>0,D14>0)," • ","")&IF(D14>0,"Bills","")) -> Income | H14: =IF($A14="",NA(),$F14) -> -993
A15: =IF(4>$E$4,"",$B$4+4-1) -> 46023 | B15: =IF($A15="","",TEXT($A15,"ddd")) -> Thu | C15: =IF($A15="","",SUMIFS('Income Schedule'!$C:$C,'Income Schedule'!$A:$A,$A15)) -> 400 | D15: =IF($A15="","",SUMIFS('Upcoming Bills'!$C:$C,'Upcoming Bills'!$B:$B,$A15)) -> 0 | E15: =IF($A15="","",C15-D15) -> 400 | F15: =IF($A15="","",F14+E15) -> -593 | G15: =IF($A15="","",IF(C15>0,"Income","")&IF(AND(C15>0,D15>0)," • ","")&IF(D15>0,"Bills","")) -> Income | H15: =IF($A15="",NA(),$F15) -> -593
A16: =IF(5>$E$4,"",$B$4+5-1) -> 46024 | B16: =IF($A16="","",TEXT($A16,"ddd")) -> Fri | C16: =IF($A16="","",SUMIFS('Income Schedule'!$C:$C,'Income Schedule'!$A:$A,$A16)) -> 0 | D16: =IF($A16="","",SUMIFS('Upcoming Bills'!$C:$C,'Upcoming Bills'!$B:$B,$A16)) -> 0 | E16: =IF($A16="","",C16-D16) -> 0 | F16: =IF($A16="","",F15+E16) -> -593 | G16: =IF($A16="","",IF(C16>0,"Income","")&IF(AND(C16>0,D16>0)," • ","")&IF(D16>0,"Bills","")) | H16: =IF($A16="",NA(),$F16) -> -593
A17: =IF(6>$E$4,"",$B$4+6-1) -> 46025 | B17: =IF($A17="","",TEXT($A17,"ddd")) -> Sat | C17: =IF($A17="","",SUMIFS('Income Schedule'!$C:$C,'Income Schedule'!$A:$A,$A17)) -> 0 | D17: =IF($A17="","",SUMIFS('Upcoming Bills'!$C:$C,'Upcoming Bills'!$B:$B,$A17)) -> 0 | E17: =IF($A17="","",C17-D17) -> 0 | F17: =IF($A17="","",F16+E17) -> -593 | G17: =IF($A17="","",IF(C17>0,"Income","")&IF(AND(C17>0,D17>0)," • ","")&IF(D17>0,"Bills","")) | H17: =IF($A17="",NA(),$F17) -> -593
A18: =IF(7>$E$4,"",$B$4+7-1) -> 46026 | B18: =IF($A18="","",TEXT($A18,"ddd")) -> Sun | C18: =IF($A18="","",SUMIFS('Income Schedule'!$C:$C,'Income Schedule'!$A:$A,$A18)) -> 0 | D18: =IF($A18="","",SUMIFS('Upcoming Bills'!$C:$C,'Upcoming Bills'!$B:$B,$A18)) -> 0 | E18: =IF($A18="","",C18-D18) -> 0 | F18: =IF($A18="","",F17+E18) -> -593 | G18: =IF($A18="","",IF(C18>0,"Income","")&IF(AND(C18>0,D18>0)," • ","")&IF(D18>0,"Bills","")) | H18: =IF($A18="",NA(),$F18) -> -593
A19: =IF(8>$E$4,"",$B$4+8-1) -> 46027 | B19: =IF($A19="","",TEXT($A19,"ddd")) -> Mon | C19: =IF($A19="","",SUMIFS('Income Schedule'!$C:$C,'Income Schedule'!$A:$A,$A19)) -> 0 | D19: =IF($A19="","",SUMIFS('Upcoming Bills'!$C:$C,'Upcoming Bills'!$B:$B,$A19)) -> 0 | E19: =IF($A19="","",C19-D19) -> 0 | F19: =IF($A19="","",F18+E19) -> -593 | G19: =IF($A19="","",IF(C19>0,"Income","")&IF(AND(C19>0,D19>0)," • ","")&IF(D19>0,"Bills","")) | H19: =IF($A19="",NA(),$F19) -> -593
A20: =IF(9>$E$4,"",$B$4+9-1) -> 46028 | B20: =IF($A20="","",TEXT($A20,"ddd")) -> Tue | C20: =IF($A20="","",SUMIFS('Income Schedule'!$C:$C,'Income Schedule'!$A:$A,$A20)) -> 0 | D20: =IF($A20="","",SUMIFS('Upcoming Bills'!$C:$C,'Upcoming Bills'!$B:$B,$A20)) -> 0 | E20: =IF($A20="","",C20-D20) -> 0 | F20: =IF($A20="","",F19+E20) -> -593 | G20: =IF($A20="","",IF(C20>0,"Income","")&IF(AND(C20>0,D20>0)," • ","")&IF(D20>0,"Bills","")) | H20: =IF($A20="",NA(),$F20) -> -593
A21: =IF(10>$E$4,"",$B$4+10-1) -> 46029 | B21: =IF($A21="","",TEXT($A21,"ddd")) -> Wed | C21: =IF($A21="","",SUMIFS('Income Schedule'!$C:$C,'Income Schedule'!$A:$A,$A21)) -> 100 | D21: =IF($A21="","",SUMIFS('Upcoming Bills'!$C:$C,'Upcoming Bills'!$B:$B,$A21)) -> 0 | E21: =IF($A21="","",C21-D21) -> 100 | F21: =IF($A21="","",F20+E21) -> -493 | G21: =IF($A21="","",IF(C21>0,"Income","")&IF(AND(C21>0,D21>0)," • ","")&IF(D21>0,"Bills","")) -> Income | H21: =IF($A21="",NA(),$F21) -> -493
A22: =IF(11>$E$4,"",$B$4+11-1) -> 46030 | B22: =IF($A22="","",TEXT($A22,"ddd")) -> Thu | C22: =IF($A22="","",SUMIFS('Income Schedule'!$C:$C,'Income Schedule'!$A:$A,$A22)) -> 0 | D22: =IF($A22="","",SUMIFS('Upcoming Bills'!$C:$C,'Upcoming Bills'!$B:$B,$A22)) -> 0 | E22: =IF($A22="","",C22-D22) -> 0 | F22: =IF($A22="","",F21+E22) -> -493 | G22: =IF($A22="","",IF(C22>0,"Income","")&IF(AND(C22>0,D22>0)," • ","")&IF(D22>0,"Bills","")) | H22: =IF($A22="",NA(),$F22) -> -493
A23: =IF(12>$E$4,"",$B$4+12-1) -> 46031 | B23: =IF($A23="","",TEXT($A23,"ddd")) -> Fri | C23: =IF($A23="","",SUMIFS('Income Schedule'!$C:$C,'Income Schedule'!$A:$A,$A23)) -> 0 | D23: =IF($A23="","",SUMIFS('Upcoming Bills'!$C:$C,'Upcoming Bills'!$B:$B,$A23)) -> 0 | E23: =IF($A23="","",C23-D23) -> 0 | F23: =IF($A23="","",F22+E23) -> -493 | G23: =IF($A23="","",IF(C23>0,"Income","")&IF(AND(C23>0,D23>0)," • ","")&IF(D23>0,"Bills","")) | H23: =IF($A23="",NA(),$F23) -> -493
A24: =IF(13>$E$4,"",$B$4+13-1) -> 46032 | B24: =IF($A24="","",TEXT($A24,"ddd")) -> Sat | C24: =IF($A24="","",SUMIFS('Income Schedule'!$C:$C,'Income Schedule'!$A:$A,$A24)) -> 0 | D24: =IF($A24="","",SUMIFS('Upcoming Bills'!$C:$C,'Upcoming Bills'!$B:$B,$A24)) -> 0 | E24: =IF($A24="","",C24-D24) -> 0 | F24: =IF($A24="","",F23+E24) -> -493 | G24: =IF($A24="","",IF(C24>0,"Income","")&IF(AND(C24>0,D24>0)," • ","")&IF(D24>0,"Bills","")) | H24: =IF($A24="",NA(),$F24) -> -493
A25: =IF(14>$E$4,"",$B$4+14-1) -> 46033 | B25: =IF($A25="","",TEXT($A25,"ddd")) -> Sun | C25: =IF($A25="","",SUMIFS('Income Schedule'!$C:$C,'Income Schedule'!$A:$A,$A25)) -> 0 | D25: =IF($A25="","",SUMIFS('Upcoming Bills'!$C:$C,'Upcoming Bills'!$B:$B,$A25)) -> 0 | E25: =IF($A25="","",C25-D25) -> 0 | F25: =IF($A25="","",F24+E25) -> -493 | G25: =IF($A25="","",IF(C25>0,"Income","")&IF(AND(C25>0,D25>0)," • ","")&IF(D25>0,"Bills","")) | H25: =IF($A25="",NA(),$F25) -> -493
A26: =IF(15>$E$4,"",$B$4+15-1) -> 46034 | B26: =IF($A26="","",TEXT($A26,"ddd")) -> Mon | C26: =IF($A26="","",SUMIFS('Income Schedule'!$C:$C,'Income Schedule'!$A:$A,$A26)) -> 0 | D26: =IF($A26="","",SUMIFS('Upcoming Bills'!$C:$C,'Upcoming Bills'!$B:$B,$A26)) -> 0 | E26: =IF($A26="","",C26-D26) -> 0 | F26: =IF($A26="","",F25+E26) -> -493 | G26: =IF($A26="","",IF(C26>0,"Income","")&IF(AND(C26>0,D26>0)," • ","")&IF(D26>0,"Bills","")) | H26: =IF($A26="",NA(),$F26) -> -493
A27: =IF(16>$E$4,"",$B$4+16-1) -> 46035 | B27: =IF($A27="","",TEXT($A27,"ddd")) -> Tue | C27: =IF($A27="","",SUMIFS('Income Schedule'!$C:$C,'Income Schedule'!$A:$A,$A27)) -> 0 | D27: =IF($A27="","",SUMIFS('Upcoming Bills'!$C:$C,'Upcoming Bills'!$B:$B,$A27)) -> 0 | E27: =IF($A27="","",C27-D27) -> 0 | F27: =IF($A27="","",F26+E27) -> -493 | G27: =IF($A27="","",IF(C27>0,"Income","")&IF(AND(C27>0,D27>0)," • ","")&IF(D27>0,"Bills","")) | H27: =IF($A27="",NA(),$F27) -> -493
A28: =IF(17>$E$4,"",$B$4+17-1) -> 46036 | B28: =IF($A28="","",TEXT($A28,"ddd")) -> Wed | C28: =IF($A28="","",SUMIFS('Income Schedule'!$C:$C,'Income Schedule'!$A:$A,$A28)) -> 100 | D28: =IF($A28="","",SUMIFS('Upcoming Bills'!$C:$C,'Upcoming Bills'!$B:$B,$A28)) -> 0 | E28: =IF($A28="","",C28-D28) -> 100 | F28: =IF($A28="","",F27+E28) -> -393 | G28: =IF($A28="","",IF(C28>0,"Income","")&IF(AND(C28>0,D28>0)," • ","")&IF(D28>0,"Bills","")) -> Income | H28: =IF($A28="",NA(),$F28) -> -393
A29: =IF(18>$E$4,"",$B$4+18-1) -> 46037 | B29: =IF($A29="","",TEXT($A29,"ddd")) -> Thu | C29: =IF($A29="","",SUMIFS('Income Schedule'!$C:$C,'Income Schedule'!$A:$A,$A29)) -> 400 | D29: =IF($A29="","",SUMIFS('Upcoming Bills'!$C:$C,'Upcoming Bills'!$B:$B,$A29)) -> 0 | E29: =IF($A29="","",C29-D29) -> 400 | F29: =IF($A29="","",F28+E29) -> 7 | G29: =IF($A29="","",IF(C29>0,"Income","")&IF(AND(C29>0,D29>0)," • ","")&IF(D29>0,"Bills","")) -> Income | H29: =IF($A29="",NA(),$F29) -> 7
A30: =IF(19>$E$4,"",$B$4+19-1) -> 46038 | B30: =IF($A30="","",TEXT($A30,"ddd")) -> Fri | C30: =IF($A30="","",SUMIFS('Income Schedule'!$C:$C,'Income Schedule'!$A:$A,$A30)) -> 0 | D30: =IF($A30="","",SUMIFS('Upcoming Bills'!$C:$C,'Upcoming Bills'!$B:$B,$A30)) -> 0 | E30: =IF($A30="","",C30-D30) -> 0 | F30: =IF($A30="","",F29+E30) -> 7 | G30: =IF($A30="","",IF(C30>0,"Income","")&IF(AND(C30>0,D30>0)," • ","")&IF(D30>0,"Bills","")) | H30: =IF($A30="",NA(),$F30) -> 7
A31: =IF(20>$E$4,"",$B$4+20-1) -> 46039 | B31: =IF($A31="","",TEXT($A31,"ddd")) -> Sat | C31: =IF($A31="","",SUMIFS('Income Schedule'!$C:$C,'Income Schedule'!$A:$A,$A31)) -> 0 | D31: =IF($A31="","",SUMIFS('Upcoming Bills'!$C:$C,'Upcoming Bills'!$B:$B,$A31)) -> 0 | E31: =IF($A31="","",C31-D31) -> 0 | F31: =IF($A31="","",F30+E31) -> 7 | G31: =IF($A31="","",IF(C31>0,"Income","")&IF(AND(C31>0,D31>0)," • ","")&IF(D31>0,"Bills","")) | H31: =IF($A31="",NA(),$F31) -> 7
A32: =IF(21>$E$4,"",$B$4+21-1) -> 46040 | B32: =IF($A32="","",TEXT($A32,"ddd")) -> Sun | C32: =IF($A32="","",SUMIFS('Income Schedule'!$C:$C,'Income Schedule'!$A:$A,$A32)) -> 0 | D32: =IF($A32="","",SUMIFS('Upcoming Bills'!$C:$C,'Upcoming Bills'!$B:$B,$A32)) -> 0 | E32: =IF($A32="","",C32-D32) -> 0 | F32: =IF($A32="","",F31+E32) -> 7 | G32: =IF($A32="","",IF(C32>0,"Income","")&IF(AND(C32>0,D32>0)," • ","")&IF(D32>0,"Bills","")) | H32: =IF($A32="",NA(),$F32) -> 7
A33: =IF(22>$E$4,"",$B$4+22-1) -> 46041 | B33: =IF($A33="","",TEXT($A33,"ddd")) -> Mon | C33: =IF($A33="","",SUMIFS('Income Schedule'!$C:$C,'Income Schedule'!$A:$A,$A33)) -> 0 | D33: =IF($A33="","",SUMIFS('Upcoming Bills'!$C:$C,'Upcoming Bills'!$B:$B,$A33)) -> 0 | E33: =IF($A33="","",C33-D33) -> 0 | F33: =IF($A33="","",F32+E33) -> 7 | G33: =IF($A33="","",IF(C33>0,"Income","")&IF(AND(C33>0,D33>0)," • ","")&IF(D33>0,"Bills","")) | H33: =IF($A33="",NA(),$F33) -> 7
A34: =IF(23>$E$4,"",$B$4+23-1) -> 46042 | B34: =IF($A34="","",TEXT($A34,"ddd")) -> Tue | C34: =IF($A34="","",SUMIFS('Income Schedule'!$C:$C,'Income Schedule'!$A:$A,$A34)) -> 0 | D34: =IF($A34="","",SUMIFS('Upcoming Bills'!$C:$C,'Upcoming Bills'!$B:$B,$A34)) -> 0 | E34: =IF($A34="","",C34-D34) -> 0 | F34: =IF($A34="","",F33+E34) -> 7 | G34: =IF($A34="","",IF(C34>0,"Income","")&IF(AND(C34>0,D34>0)," • ","")&IF(D34>0,"Bills","")) | H34: =IF($A34="",NA(),$F34) -> 7
A35: =IF(24>$E$4,"",$B$4+24-1) -> 46043 | B35: =IF($A35="","",TEXT($A35,"ddd")) -> Wed | C35: =IF($A35="","",SUMIFS('Income Schedule'!$C:$C,'Income Schedule'!$A:$A,$A35)) -> 100 | D35: =IF($A35="","",SUMIFS('Upcoming Bills'!$C:$C,'Upcoming Bills'!$B:$B,$A35)) -> 0 | E35: =IF($A35="","",C35-D35) -> 100 | F35: =IF($A35="","",F34+E35) -> 107 | G35: =IF($A35="","",IF(C35>0,"Income","")&IF(AND(C35>0,D35>0)," • ","")&IF(D35>0,"Bills","")) -> Income | H35: =IF($A35="",NA(),$F35) -> 107
A36: =IF(25>$E$4,"",$B$4+25-1) -> 46044 | B36: =IF($A36="","",TEXT($A36,"ddd")) -> Thu | C36: =IF($A36="","",SUMIFS('Income Schedule'!$C:$C,'Income Schedule'!$A:$A,$A36)) -> 0 | D36: =IF($A36="","",SUMIFS('Upcoming Bills'!$C:$C,'Upcoming Bills'!$B:$B,$A36)) -> 0 | E36: =IF($A36="","",C36-D36) -> 0 | F36: =IF($A36="","",F35+E36) -> 107 | G36: =IF($A36="","",IF(C36>0,"Income","")&IF(AND(C36>0,D36>0)," • ","")&IF(D36>0,"Bills","")) | H36: =IF($A36="",NA(),$F36) -> 107
A37: =IF(26>$E$4,"",$B$4+26-1) -> 46045 | B37: =IF($A37="","",TEXT($A37,"ddd")) -> Fri | C37: =IF($A37="","",SUMIFS('Income Schedule'!$C:$C,'Income Schedule'!$A:$A,$A37)) -> 0 | D37: =IF($A37="","",SUMIFS('Upcoming Bills'!$C:$C,'Upcoming Bills'!$B:$B,$A37)) -> 0 | E37: =IF($A37="","",C37-D37) -> 0 | F37: =IF($A37="","",F36+E37) -> 107 | G37: =IF($A37="","",IF(C37>0,"Income","")&IF(AND(C37>0,D37>0)," • ","")&IF(D37>0,"Bills","")) | H37: =IF($A37="",NA(),$F37) -> 107
A38: =IF(27>$E$4,"",$B$4+27-1) -> 46046 | B38: =IF($A38="","",TEXT($A38,"ddd")) -> Sat | C38: =IF($A38="","",SUMIFS('Income Schedule'!$C:$C,'Income Schedule'!$A:$A,$A38)) -> 0 | D38: =IF($A38="","",SUMIFS('Upcoming Bills'!$C:$C,'Upcoming Bills'!$B:$B,$A38)) -> 0 | E38: =IF($A38="","",C38-D38) -> 0 | F38: =IF($A38="","",F37+E38) -> 107 | G38: =IF($A38="","",IF(C38>0,"Income","")&IF(AND(C38>0,D38>0)," • ","")&IF(D38>0,"Bills","")) | H38: =IF($A38="",NA(),$F38) -> 107
A39: =IF(28>$E$4,"",$B$4+28-1) -> 46047 | B39: =IF($A39="","",TEXT($A39,"ddd")) -> Sun | C39: =IF($A39="","",SUMIFS('Income Schedule'!$C:$C,'Income Schedule'!$A:$A,$A39)) -> 0 | D39: =IF($A39="","",SUMIFS('Upcoming Bills'!$C:$C,'Upcoming Bills'!$B:$B,$A39)) -> 0 | E39: =IF($A39="","",C39-D39) -> 0 | F39: =IF($A39="","",F38+E39) -> 107 | G39: =IF($A39="","",IF(C39>0,"Income","")&IF(AND(C39>0,D39>0)," • ","")&IF(D39>0,"Bills","")) | H39: =IF($A39="",NA(),$F39) -> 107
A40: =IF(29>$E$4,"",$B$4+29-1) -> 46048 | B40: =IF($A40="","",TEXT($A40,"ddd")) -> Mon | C40: =IF($A40="","",SUMIFS('Income Schedule'!$C:$C,'Income Schedule'!$A:$A,$A40)) -> 3500 | D40: =IF($A40="","",SUMIFS('Upcoming Bills'!$C:$C,'Upcoming Bills'!$B:$B,$A40)) -> 0 | E40: =IF($A40="","",C40-D40) -> 3500 | F40: =IF($A40="","",F39+E40) -> 3607 | G40: =IF($A40="","",IF(C40>0,"Income","")&IF(AND(C40>0,D40>0)," • ","")&IF(D40>0,"Bills","")) -> Income | H40: =IF($A40="",NA(),$F40) -> 3607
A41: =IF(30>$E$4,"",$B$4+30-1) -> 46049 | B41: =IF($A41="","",TEXT($A41,"ddd")) -> Tue | C41: =IF($A41="","",SUMIFS('Income Schedule'!$C:$C,'Income Schedule'!$A:$A,$A41)) -> 0 | D41: =IF($A41="","",SUMIFS('Upcoming Bills'!$C:$C,'Upcoming Bills'!$B:$B,$A41)) -> 0 | E41: =IF($A41="","",C41-D41) -> 0 | F41: =IF($A41="","",F40+E41) -> 3607 | G41: =IF($A41="","",IF(C41>0,"Income","")&IF(AND(C41>0,D41>0)," • ","")&IF(D41>0,"Bills","")) | H41: =IF($A41="",NA(),$F41) -> 3607
A42: =IF(31>$E$4,"",$B$4+31-1) | B42: =IF($A42="","",TEXT($A42,"ddd")) | C42: =IF($A42="","",SUMIFS('Income Schedule'!$C:$C,'Income Schedule'!$A:$A,$A42)) | D42: =IF($A42="","",SUMIFS('Upcoming Bills'!$C:$C,'Upcoming Bills'!$B:$B,$A42)) | E42: =IF($A42="","",C42-D42) | F42: =IF($A42="","",F41+E42) | G42: =IF($A42="","",IF(C42>0,"Income","")&IF(AND(C42>0,D42>0)," • ","")&IF(D42>0,"Bills","")) | H42: =IF($A42="",NA(),$F42) -> #N/A
A43: =IF(32>$E$4,"",$B$4+32-1) | B43: =IF($A43="","",TEXT($A43,"ddd")) | C43: =IF($A43="","",SUMIFS('Income Schedule'!$C:$C,'Income Schedule'!$A:$A,$A43)) | D43: =IF($A43="","",SUMIFS('Upcoming Bills'!$C:$C,'Upcoming Bills'!$B:$B,$A43)) | E43: =IF($A43="","",C43-D43) | F43: =IF($A43="","",F42+E43) | G43: =IF($A43="","",IF(C43>0,"Income","")&IF(AND(C43>0,D43>0)," • ","")&IF(D43>0,"Bills","")) | H43: =IF($A43="",NA(),$F43) -> #N/A
A44: =IF(33>$E$4,"",$B$4+33-1) | B44: =IF($A44="","",TEXT($A44,"ddd")) | C44: =IF($A44="","",SUMIFS('Income Schedule'!$C:$C,'Income Schedule'!$A:$A,$A44)) | D44: =IF($A44="","",SUMIFS('Upcoming Bills'!$C:$C,'Upcoming Bills'!$B:$B,$A44)) | E44: =IF($A44="","",C44-D44) | F44: =IF($A44="","",F43+E44) | G44: =IF($A44="","",IF(C44>0,"Income","")&IF(AND(C44>0,D44>0)," • ","")&IF(D44>0,"Bills","")) | H44: =IF($A44="",NA(),$F44) -> #N/A
A45: =IF(34>$E$4,"",$B$4+34-1) | B45: =IF($A45="","",TEXT($A45,"ddd")) | C45: =IF($A45="","",SUMIFS('Income Schedule'!$C:$C,'Income Schedule'!$A:$A,$A45)) | D45: =IF($A45="","",SUMIFS('Upcoming Bills'!$C:$C,'Upcoming Bills'!$B:$B,$A45)) | E45: =IF($A45="","",C45-D45) | F45: =IF($A45="","",F44+E45) | G45: =IF($A45="","",IF(C45>0,"Income","")&IF(AND(C45>0,D45>0)," • ","")&IF(D45>0,"Bills","")) | H45: =IF($A45="",NA(),$F45) -> #N/A
A46: =IF(35>$E$4,"",$B$4+35-1) | B46: =IF($A46="","",TEXT($A46,"ddd")) | C46: =IF($A46="","",SUMIFS('Income Schedule'!$C:$C,'Income Schedule'!$A:$A,$A46)) | D46: =IF($A46="","",SUMIFS('Upcoming Bills'!$C:$C,'Upcoming Bills'!$B:$B,$A46)) | E46: =IF($A46="","",C46-D46) | F46: =IF($A46="","",F45+E46) | G46: =IF($A46="","",IF(C46>0,"Income","")&IF(AND(C46>0,D46>0)," • ","")&IF(D46>0,"Bills","")) | H46: =IF($A46="",NA(),$F46) -> #N/A
A47: =IF(36>$E$4,"",$B$4+36-1) | B47: =IF($A47="","",TEXT($A47,"ddd")) | C47: =IF($A47="","",SUMIFS('Income Schedule'!$C:$C,'Income Schedule'!$A:$A,$A47)) | D47: =IF($A47="","",SUMIFS('Upcoming Bills'!$C:$C,'Upcoming Bills'!$B:$B,$A47)) | E47: =IF($A47="","",C47-D47) | F47: =IF($A47="","",F46+E47) | G47: =IF($A47="","",IF(C47>0,"Income","")&IF(AND(C47>0,D47>0)," • ","")&IF(D47>0,"Bills","")) | H47: =IF($A47="",NA(),$F47) -> #N/A
A48: =IF(37>$E$4,"",$B$4+37-1) | B48: =IF($A48="","",TEXT($A48,"ddd")) | C48: =IF($A48="","",SUMIFS('Income Schedule'!$C:$C,'Income Schedule'!$A:$A,$A48)) | D48: =IF($A48="","",SUMIFS('Upcoming Bills'!$C:$C,'Upcoming Bills'!$B:$B,$A48)) | E48: =IF($A48="","",C48-D48) | F48: =IF($A48="","",F47+E48) | G48: =IF($A48="","",IF(C48>0,"Income","")&IF(AND(C48>0,D48>0)," • ","")&IF(D48>0,"Bills","")) | H48: =IF($A48="",NA(),$F48) -> #N/A
A49: =IF(38>$E$4,"",$B$4+38-1) | B49: =IF($A49="","",TEXT($A49,"ddd")) | C49: =IF($A49="","",SUMIFS('Income Schedule'!$C:$C,'Income Schedule'!$A:$A,$A49)) | D49: =IF($A49="","",SUMIFS('Upcoming Bills'!$C:$C,'Upcoming Bills'!$B:$B,$A49)) | E49: =IF($A49="","",C49-D49) | F49: =IF($A49="","",F48+E49) | G49: =IF($A49="","",IF(C49>0,"Income","")&IF(AND(C49>0,D49>0)," • ","")&IF(D49>0,"Bills","")) | H49: =IF($A49="",NA(),$F49) -> #N/A
A50: =IF(39>$E$4,"",$B$4+39-1) | B50: =IF($A50="","",TEXT($A50,"ddd")) | C50: =IF($A50="","",SUMIFS('Income Schedule'!$C:$C,'Income Schedule'!$A:$A,$A50)) | D50: =IF($A50="","",SUMIFS('Upcoming Bills'!$C:$C,'Upcoming Bills'!$B:$B,$A50)) | E50: =IF($A50="","",C50-D50) | F50: =IF($A50="","",F49+E50) | G50: =IF($A50="","",IF(C50>0,"Income","")&IF(AND(C50>0,D50>0)," • ","")&IF(D50>0,"Bills","")) | H50: =IF($A50="",NA(),$F50) -> #N/A
A51: =IF(40>$E$4,"",$B$4+40-1) | B51: =IF($A51="","",TEXT($A51,"ddd")) | C51: =IF($A51="","",SUMIFS('Income Schedule'!$C:$C,'Income Schedule'!$A:$A,$A51)) | D51: =IF($A51="","",SUMIFS('Upcoming Bills'!$C:$C,'Upcoming Bills'!$B:$B,$A51)) | E51: =IF($A51="","",C51-D51) | F51: =IF($A51="","",F50+E51) | G51: =IF($A51="","",IF(C51>0,"Income","")&IF(AND(C51>0,D51>0)," • ","")&IF(D51>0,"Bills","")) | H51: =IF($A51="",NA(),$F51) -> #N/A
A52: =IF(41>$E$4,"",$B$4+41-1) | B52: =IF($A52="","",TEXT($A52,"ddd")) | C52: =IF($A52="","",SUMIFS('Income Schedule'!$C:$C,'Income Schedule'!$A:$A,$A52)) | D52: =IF($A52="","",SUMIFS('Upcoming Bills'!$C:$C,'Upcoming Bills'!$B:$B,$A52)) | E52: =IF($A52="","",C52-D52) | F52: =IF($A52="","",F51+E52) | G52: =IF($A52="","",IF(C52>0,"Income","")&IF(AND(C52>0,D52>0)," • ","")&IF(D52>0,"Bills","")) | H52: =IF($A52="",NA(),$F52) -> #N/A
A53: =IF(42>$E$4,"",$B$4+42-1) | B53: =IF($A53="","",TEXT($A53,"ddd")) | C53: =IF($A53="","",SUMIFS('Income Schedule'!$C:$C,'Income Schedule'!$A:$A,$A53)) | D53: =IF($A53="","",SUMIFS('Upcoming Bills'!$C:$C,'Upcoming Bills'!$B:$B,$A53)) | E53: =IF($A53="","",C53-D53) | F53: =IF($A53="","",F52+E53) | G53: =IF($A53="","",IF(C53>0,"Income","")&IF(AND(C53>0,D53>0)," • ","")&IF(D53>0,"Bills","")) | H53: =IF($A53="",NA(),$F53) -> #N/A
A54: =IF(43>$E$4,"",$B$4+43-1) | B54: =IF($A54="","",TEXT($A54,"ddd")) | C54: =IF($A54="","",SUMIFS('Income Schedule'!$C:$C,'Income Schedule'!$A:$A,$A54)) | D54: =IF($A54="","",SUMIFS('Upcoming Bills'!$C:$C,'Upcoming Bills'!$B:$B,$A54)) | E54: =IF($A54="","",C54-D54) | F54: =IF($A54="","",F53+E54) | G54: =IF($A54="","",IF(C54>0,"Income","")&IF(AND(C54>0,D54>0)," • ","")&IF(D54>0,"Bills","")) | H54: =IF($A54="",NA(),$F54) -> #N/A
A55: =IF(44>$E$4,"",$B$4+44-1) | B55: =IF($A55="","",TEXT($A55,"ddd")) | C55: =IF($A55="","",SUMIFS('Income Schedule'!$C:$C,'Income Schedule'!$A:$A,$A55)) | D55: =IF($A55="","",SUMIFS('Upcoming Bills'!$C:$C,'Upcoming Bills'!$B:$B,$A55)) | E55: =IF($A55="","",C55-D55) | F55: =IF($A55="","",F54+E55) | G55: =IF($A55="","",IF(C55>0,"Income","")&IF(AND(C55>0,D55>0)," • ","")&IF(D55>0,"Bills","")) | H55: =IF($A55="",NA(),$F55) -> #N/A
A56: =IF(45>$E$4,"",$B$4+45-1) | B56: =IF($A56="","",TEXT($A56,"ddd")) | C56: =IF($A56="","",SUMIFS('Income Schedule'!$C:$C,'Income Schedule'!$A:$A,$A56)) | D56: =IF($A56="","",SUMIFS('Upcoming Bills'!$C:$C,'Upcoming Bills'!$B:$B,$A56)) | E56: =IF($A56="","",C56-D56) | F56: =IF($A56="","",F55+E56) | G56: =IF($A56="","",IF(C56>0,"Income","")&IF(AND(C56>0,D56>0)," • ","")&IF(D56>0,"Bills","")) | H56: =IF($A56="",NA(),$F56) -> #N/A
A57: =IF(46>$E$4,"",$B$4+46-1) | B57: =IF($A57="","",TEXT($A57,"ddd")) | C57: =IF($A57="","",SUMIFS('Income Schedule'!$C:$C,'Income Schedule'!$A:$A,$A57)) | D57: =IF($A57="","",SUMIFS('Upcoming Bills'!$C:$C,'Upcoming Bills'!$B:$B,$A57)) | E57: =IF($A57="","",C57-D57) | F57: =IF($A57="","",F56+E57) | G57: =IF($A57="","",IF(C57>0,"Income","")&IF(AND(C57>0,D57>0)," • ","")&IF(D57>0,"Bills","")) | H57: =IF($A57="",NA(),$F57) -> #N/A
A58: =IF(47>$E$4,"",$B$4+47-1) | B58: =IF($A58="","",TEXT($A58,"ddd")) | C58: =IF($A58="","",SUMIFS('Income Schedule'!$C:$C,'Income Schedule'!$A:$A,$A58)) | D58: =IF($A58="","",SUMIFS('Upcoming Bills'!$C:$C,'Upcoming Bills'!$B:$B,$A58)) | E58: =IF($A58="","",C58-D58) | F58: =IF($A58="","",F57+E58) | G58: =IF($A58="","",IF(C58>0,"Income","")&IF(AND(C58>0,D58>0)," • ","")&IF(D58>0,"Bills","")) | H58: =IF($A58="",NA(),$F58) -> #N/A
A59: =IF(48>$E$4,"",$B$4+48-1) | B59: =IF($A59="","",TEXT($A59,"ddd")) | C59: =IF($A59="","",SUMIFS('Income Schedule'!$C:$C,'Income Schedule'!$A:$A,$A59)) | D59: =IF($A59="","",SUMIFS('Upcoming Bills'!$C:$C,'Upcoming Bills'!$B:$B,$A59)) | E59: =IF($A59="","",C59-D59) | F59: =IF($A59="","",F58+E59) | G59: =IF($A59="","",IF(C59>0,"Income","")&IF(AND(C59>0,D59>0)," • ","")&IF(D59>0,"Bills","")) | H59: =IF($A59="",NA(),$F59) -> #N/A
A60: =IF(49>$E$4,"",$B$4+49-1) | B60: =IF($A60="","",TEXT($A60,"ddd")) | C60: =IF($A60="","",SUMIFS('Income Schedule'!$C:$C,'Income Schedule'!$A:$A,$A60)) | D60: =IF($A60="","",SUMIFS('Upcoming Bills'!$C:$C,'Upcoming Bills'!$B:$B,$A60)) | E60: =IF($A60="","",C60-D60) | F60: =IF($A60="","",F59+E60) | G60: =IF($A60="","",IF(C60>0,"Income","")&IF(AND(C60>0,D60>0)," • ","")&IF(D60>0,"Bills","")) | H60: =IF($A60="",NA(),$F60) -> #N/A
A61: =IF(50>$E$4,"",$B$4+50-1) | B61: =IF($A61="","",TEXT($A61,"ddd")) | C61: =IF($A61="","",SUMIFS('Income Schedule'!$C:$C,'Income Schedule'!$A:$A,$A61)) | D61: =IF($A61="","",SUMIFS('Upcoming Bills'!$C:$C,'Upcoming Bills'!$B:$B,$A61)) | E61: =IF($A61="","",C61-D61) | F61: =IF($A61="","",F60+E61) | G61: =IF($A61="","",IF(C61>0,"Income","")&IF(AND(C61>0,D61>0)," • ","")&IF(D61>0,"Bills","")) | H61: =IF($A61="",NA(),$F61) -> #N/A
A62: =IF(51>$E$4,"",$B$4+51-1) | B62: =IF($A62="","",TEXT($A62,"ddd")) | C62: =IF($A62="","",SUMIFS('Income Schedule'!$C:$C,'Income Schedule'!$A:$A,$A62)) | D62: =IF($A62="","",SUMIFS('Upcoming Bills'!$C:$C,'Upcoming Bills'!$B:$B,$A62)) | E62: =IF($A62="","",C62-D62) | F62: =IF($A62="","",F61+E62) | G62: =IF($A62="","",IF(C62>0,"Income","")&IF(AND(C62>0,D62>0)," • ","")&IF(D62>0,"Bills","")) | H62: =IF($A62="",NA(),$F62) -> #N/A
A63: =IF(52>$E$4,"",$B$4+52-1) | B63: =IF($A63="","",TEXT($A63,"ddd")) | C63: =IF($A63="","",SUMIFS('Income Schedule'!$C:$C,'Income Schedule'!$A:$A,$A63)) | D63: =IF($A63="","",SUMIFS('Upcoming Bills'!$C:$C,'Upcoming Bills'!$B:$B,$A63)) | E63: =IF($A63="","",C63-D63) | F63: =IF($A63="","",F62+E63) | G63: =IF($A63="","",IF(C63>0,"Income","")&IF(AND(C63>0,D63>0)," • ","")&IF(D63>0,"Bills","")) | H63: =IF($A63="",NA(),$F63) -> #N/A
A64: =IF(53>$E$4,"",$B$4+53-1) | B64: =IF($A64="","",TEXT($A64,"ddd")) | C64: =IF($A64="","",SUMIFS('Income Schedule'!$C:$C,'Income Schedule'!$A:$A,$A64)) | D64: =IF($A64="","",SUMIFS('Upcoming Bills'!$C:$C,'Upcoming Bills'!$B:$B,$A64)) | E64: =IF($A64="","",C64-D64) | F64: =IF($A64="","",F63+E64) | G64: =IF($A64="","",IF(C64>0,"Income","")&IF(AND(C64>0,D64>0)," • ","")&IF(D64>0,"Bills","")) | H64: =IF($A64="",NA(),$F64) -> #N/A
A65: =IF(54>$E$4,"",$B$4+54-1) | B65: =IF($A65="","",TEXT($A65,"ddd")) | C65: =IF($A65="","",SUMIFS('Income Schedule'!$C:$C,'Income Schedule'!$A:$A,$A65)) | D65: =IF($A65="","",SUMIFS('Upcoming Bills'!$C:$C,'Upcoming Bills'!$B:$B,$A65)) | E65: =IF($A65="","",C65-D65) | F65: =IF($A65="","",F64+E65) | G65: =IF($A65="","",IF(C65>0,"Income","")&IF(AND(C65>0,D65>0)," • ","")&IF(D65>0,"Bills","")) | H65: =IF($A65="",NA(),$F65) -> #N/A
A66: =IF(55>$E$4,"",$B$4+55-1) | B66: =IF($A66="","",TEXT($A66,"ddd")) | C66: =IF($A66="","",SUMIFS('Income Schedule'!$C:$C,'Income Schedule'!$A:$A,$A66)) | D66: =IF($A66="","",SUMIFS('Upcoming Bills'!$C:$C,'Upcoming Bills'!$B:$B,$A66)) | E66: =IF($A66="","",C66-D66) | F66: =IF($A66="","",F65+E66) | G66: =IF($A66="","",IF(C66>0,"Income","")&IF(AND(C66>0,D66>0)," • ","")&IF(D66>0,"Bills","")) | H66: =IF($A66="",NA(),$F66) -> #N/A
A67: =IF(56>$E$4,"",$B$4+56-1) | B67: =IF($A67="","",TEXT($A67,"ddd")) | C67: =IF($A67="","",SUMIFS('Income Schedule'!$C:$C,'Income Schedule'!$A:$A,$A67)) | D67: =IF($A67="","",SUMIFS('Upcoming Bills'!$C:$C,'Upcoming Bills'!$B:$B,$A67)) | E67: =IF($A67="","",C67-D67) | F67: =IF($A67="","",F66+E67) | G67: =IF($A67="","",IF(C67>0,"Income","")&IF(AND(C67>0,D67>0)," • ","")&IF(D67>0,"Bills","")) | H67: =IF($A67="",NA(),$F67) -> #N/A
A68: =IF(57>$E$4,"",$B$4+57-1) | B68: =IF($A68="","",TEXT($A68,"ddd")) | C68: =IF($A68="","",SUMIFS('Income Schedule'!$C:$C,'Income Schedule'!$A:$A,$A68)) | D68: =IF($A68="","",SUMIFS('Upcoming Bills'!$C:$C,'Upcoming Bills'!$B:$B,$A68)) | E68: =IF($A68="","",C68-D68) | F68: =IF($A68="","",F67+E68) | G68: =IF($A68="","",IF(C68>0,"Income","")&IF(AND(C68>0,D68>0)," • ","")&IF(D68>0,"Bills","")) | H68: =IF($A68="",NA(),$F68) -> #N/A
A69: =IF(58>$E$4,"",$B$4+58-1) | B69: =IF($A69="","",TEXT($A69,"ddd")) | C69: =IF($A69="","",SUMIFS('Income Schedule'!$C:$C,'Income Schedule'!$A:$A,$A69)) | D69: =IF($A69="","",SUMIFS('Upcoming Bills'!$C:$C,'Upcoming Bills'!$B:$B,$A69)) | E69: =IF($A69="","",C69-D69) | F69: =IF($A69="","",F68+E69) | G69: =IF($A69="","",IF(C69>0,"Income","")&IF(AND(C69>0,D69>0)," • ","")&IF(D69>0,"Bills","")) | H69: =IF($A69="",NA(),$F69) -> #N/A
A70: =IF(59>$E$4,"",$B$4+59-1) | B70: =IF($A70="","",TEXT($A70,"ddd")) | C70: =IF($A70="","",SUMIFS('Income Schedule'!$C:$C,'Income Schedule'!$A:$A,$A70)) | D70: =IF($A70="","",SUMIFS('Upcoming Bills'!$C:$C,'Upcoming Bills'!$B:$B,$A70)) | E70: =IF($A70="","",C70-D70) | F70: =IF($A70="","",F69+E70) | G70: =IF($A70="","",IF(C70>0,"Income","")&IF(AND(C70>0,D70>0)," • ","")&IF(D70>0,"Bills","")) | H70: =IF($A70="",NA(),$F70) -> #N/A
A71: =IF(60>$E$4,"",$B$4+60-1) | B71: =IF($A71="","",TEXT($A71,"ddd")) | C71: =IF($A71="","",SUMIFS('Income Schedule'!$C:$C,'Income Schedule'!$A:$A,$A71)) | D71: =IF($A71="","",SUMIFS('Upcoming Bills'!$C:$C,'Upcoming Bills'!$B:$B,$A71)) | E71: =IF($A71="","",C71-D71) | F71: =IF($A71="","",F70+E71) | G71: =IF($A71="","",IF(C71>0,"Income","")&IF(AND(C71>0,D71>0)," • ","")&IF(D71>0,"Bills","")) | H71: =IF($A71="",NA(),$F71) -> #N/A
A72: =IF(61>$E$4,"",$B$4+61-1) | B72: =IF($A72="","",TEXT($A72,"ddd")) | C72: =IF($A72="","",SUMIFS('Income Schedule'!$C:$C,'Income Schedule'!$A:$A,$A72)) | D72: =IF($A72="","",SUMIFS('Upcoming Bills'!$C:$C,'Upcoming Bills'!$B:$B,$A72)) | E72: =IF($A72="","",C72-D72) | F72: =IF($A72="","",F71+E72) | G72: =IF($A72="","",IF(C72>0,"Income","")&IF(AND(C72>0,D72>0)," • ","")&IF(D72>0,"Bills","")) | H72: =IF($A72="",NA(),$F72) -> #N/A
A73: =IF(62>$E$4,"",$B$4+62-1) | B73: =IF($A73="","",TEXT($A73,"ddd")) | C73: =IF($A73="","",SUMIFS('Income Schedule'!$C:$C,'Income Schedule'!$A:$A,$A73)) | D73: =IF($A73="","",SUMIFS('Upcoming Bills'!$C:$C,'Upcoming Bills'!$B:$B,$A73)) | E73: =IF($A73="","",C73-D73) | F73: =IF($A73="","",F72+E73) | G73: =IF($A73="","",IF(C73>0,"Income","")&IF(AND(C73>0,D73>0)," • ","")&IF(D73>0,"Bills","")) | H73: =IF($A73="",NA(),$F73) -> #N/A
A74: =IF(63>$E$4,"",$B$4+63-1) | B74: =IF($A74="","",TEXT($A74,"ddd")) | C74: =IF($A74="","",SUMIFS('Income Schedule'!$C:$C,'Income Schedule'!$A:$A,$A74)) | D74: =IF($A74="","",SUMIFS('Upcoming Bills'!$C:$C,'Upcoming Bills'!$B:$B,$A74)) | E74: =IF($A74="","",C74-D74) | F74: =IF($A74="","",F73+E74) | G74: =IF($A74="","",IF(C74>0,"Income","")&IF(AND(C74>0,D74>0)," • ","")&IF(D74>0,"Bills","")) | H74: =IF($A74="",NA(),$F74) -> #N/A
A75: =IF(64>$E$4,"",$B$4+64-1) | B75: =IF($A75="","",TEXT($A75,"ddd")) | C75: =IF($A75="","",SUMIFS('Income Schedule'!$C:$C,'Income Schedule'!$A:$A,$A75)) | D75: =IF($A75="","",SUMIFS('Upcoming Bills'!$C:$C,'Upcoming Bills'!$B:$B,$A75)) | E75: =IF($A75="","",C75-D75) | F75: =IF($A75="","",F74+E75) | G75: =IF($A75="","",IF(C75>0,"Income","")&IF(AND(C75>0,D75>0)," • ","")&IF(D75>0,"Bills","")) | H75: =IF($A75="",NA(),$F75) -> #N/A
A76: =IF(65>$E$4,"",$B$4+65-1) | B76: =IF($A76="","",TEXT($A76,"ddd")) | C76: =IF($A76="","",SUMIFS('Income Schedule'!$C:$C,'Income Schedule'!$A:$A,$A76)) | D76: =IF($A76="","",SUMIFS('Upcoming Bills'!$C:$C,'Upcoming Bills'!$B:$B,$A76)) | E76: =IF($A76="","",C76-D76) | F76: =IF($A76="","",F75+E76) | G76: =IF($A76="","",IF(C76>0,"Income","")&IF(AND(C76>0,D76>0)," • ","")&IF(D76>0,"Bills","")) | H76: =IF($A76="",NA(),$F76) -> #N/A
A77: =IF(66>$E$4,"",$B$4+66-1) | B77: =IF($A77="","",TEXT($A77,"ddd")) | C77: =IF($A77="","",SUMIFS('Income Schedule'!$C:$C,'Income Schedule'!$A:$A,$A77)) | D77: =IF($A77="","",SUMIFS('Upcoming Bills'!$C:$C,'Upcoming Bills'!$B:$B,$A77)) | E77: =IF($A77="","",C77-D77) | F77: =IF($A77="","",F76+E77) | G77: =IF($A77="","",IF(C77>0,"Income","")&IF(AND(C77>0,D77>0)," • ","")&IF(D77>0,"Bills","")) | H77: =IF($A77="",NA(),$F77) -> #N/A
A78: =IF(67>$E$4,"",$B$4+67-1) | B78: =IF($A78="","",TEXT($A78,"ddd")) | C78: =IF($A78="","",SUMIFS('Income Schedule'!$C:$C,'Income Schedule'!$A:$A,$A78)) | D78: =IF($A78="","",SUMIFS('Upcoming Bills'!$C:$C,'Upcoming Bills'!$B:$B,$A78)) | E78: =IF($A78="","",C78-D78) | F78: =IF($A78="","",F77+E78) | G78: =IF($A78="","",IF(C78>0,"Income","")&IF(AND(C78>0,D78>0)," • ","")&IF(D78>0,"Bills","")) | H78: =IF($A78="",NA(),$F78) -> #N/A
A79: =IF(68>$E$4,"",$B$4+68-1) | B79: =IF($A79="","",TEXT($A79,"ddd")) | C79: =IF($A79="","",SUMIFS('Income Schedule'!$C:$C,'Income Schedule'!$A:$A,$A79)) | D79: =IF($A79="","",SUMIFS('Upcoming Bills'!$C:$C,'Upcoming Bills'!$B:$B,$A79)) | E79: =IF($A79="","",C79-D79) | F79: =IF($A79="","",F78+E79) | G79: =IF($A79="","",IF(C79>0,"Income","")&IF(AND(C79>0,D79>0)," • ","")&IF(D79>0,"Bills","")) | H79: =IF($A79="",NA(),$F79) -> #N/A
A80: =IF(69>$E$4,"",$B$4+69-1) | B80: =IF($A80="","",TEXT($A80,"ddd")) | C80: =IF($A80="","",SUMIFS('Income Schedule'!$C:$C,'Income Schedule'!$A:$A,$A80)) | D80: =IF($A80="","",SUMIFS('Upcoming Bills'!$C:$C,'Upcoming Bills'!$B:$B,$A80)) | E80: =IF($A80="","",C80-D80) | F80: =IF($A80="","",F79+E80) | G80: =IF($A80="","",IF(C80>0,"Income","")&IF(AND(C80>0,D80>0)," • ","")&IF(D80>0,"Bills","")) | H80: =IF($A80="",NA(),$F80) -> #N/A
A81: =IF(70>$E$4,"",$B$4+70-1) | B81: =IF($A81="","",TEXT($A81,"ddd")) | C81: =IF($A81="","",SUMIFS('Income Schedule'!$C:$C,'Income Schedule'!$A:$A,$A81)) | D81: =IF($A81="","",SUMIFS('Upcoming Bills'!$C:$C,'Upcoming Bills'!$B:$B,$A81)) | E81: =IF($A81="","",C81-D81) | F81: =IF($A81="","",F80+E81) | G81: =IF($A81="","",IF(C81>0,"Income","")&IF(AND(C81>0,D81>0)," • ","")&IF(D81>0,"Bills","")) | H81: =IF($A81="",NA(),$F81) -> #N/A
A82: =IF(71>$E$4,"",$B$4+71-1) | B82: =IF($A82="","",TEXT($A82,"ddd")) | C82: =IF($A82="","",SUMIFS('Income Schedule'!$C:$C,'Income Schedule'!$A:$A,$A82)) | D82: =IF($A82="","",SUMIFS('Upcoming Bills'!$C:$C,'Upcoming Bills'!$B:$B,$A82)) | E82: =IF($A82="","",C82-D82) | F82: =IF($A82="","",F81+E82) | G82: =IF($A82="","",IF(C82>0,"Income","")&IF(AND(C82>0,D82>0)," • ","")&IF(D82>0,"Bills","")) | H82: =IF($A82="",NA(),$F82) -> #N/A
A83: =IF(72>$E$4,"",$B$4+72-1) | B83: =IF($A83="","",TEXT($A83,"ddd")) | C83: =IF($A83="","",SUMIFS('Income Schedule'!$C:$C,'Income Schedule'!$A:$A,$A83)) | D83: =IF($A83="","",SUMIFS('Upcoming Bills'!$C:$C,'Upcoming Bills'!$B:$B,$A83)) | E83: =IF($A83="","",C83-D83) | F83: =IF($A83="","",F82+E83) | G83: =IF($A83="","",IF(C83>0,"Income","")&IF(AND(C83>0,D83>0)," • ","")&IF(D83>0,"Bills","")) | H83: =IF($A83="",NA(),$F83) -> #N/A
A84: =IF(73>$E$4,"",$B$4+73-1) | B84: =IF($A84="","",TEXT($A84,"ddd")) | C84: =IF($A84="","",SUMIFS('Income Schedule'!$C:$C,'Income Schedule'!$A:$A,$A84)) | D84: =IF($A84="","",SUMIFS('Upcoming Bills'!$C:$C,'Upcoming Bills'!$B:$B,$A84)) | E84: =IF($A84="","",C84-D84) | F84: =IF($A84="","",F83+E84) | G84: =IF($A84="","",IF(C84>0,"Income","")&IF(AND(C84>0,D84>0)," • ","")&IF(D84>0,"Bills","")) | H84: =IF($A84="",NA(),$F84) -> #N/A
A85: =IF(74>$E$4,"",$B$4+74-1) | B85: =IF($A85="","",TEXT($A85,"ddd")) | C85: =IF($A85="","",SUMIFS('Income Schedule'!$C:$C,'Income Schedule'!$A:$A,$A85)) | D85: =IF($A85="","",SUMIFS('Upcoming Bills'!$C:$C,'Upcoming Bills'!$B:$B,$A85)) | E85: =IF($A85="","",C85-D85) | F85: =IF($A85="","",F84+E85) | G85: =IF($A85="","",IF(C85>0,"Income","")&IF(AND(C85>0,D85>0)," • ","")&IF(D85>0,"Bills","")) | H85: =IF($A85="",NA(),$F85) -> #N/A
A86: =IF(75>$E$4,"",$B$4+75-1) | B86: =IF($A86="","",TEXT($A86,"ddd")) | C86: =IF($A86="","",SUMIFS('Income Schedule'!$C:$C,'Income Schedule'!$A:$A,$A86)) | D86: =IF($A86="","",SUMIFS('Upcoming Bills'!$C:$C,'Upcoming Bills'!$B:$B,$A86)) | E86: =IF($A86="","",C86-D86) | F86: =IF($A86="","",F85+E86) | G86: =IF($A86="","",IF(C86>0,"Income","")&IF(AND(C86>0,D86>0)," • ","")&IF(D86>0,"Bills","")) | H86: =IF($A86="",NA(),$F86) -> #N/A
A87: =IF(76>$E$4,"",$B$4+76-1) | B87: =IF($A87="","",TEXT($A87,"ddd")) | C87: =IF($A87="","",SUMIFS('Income Schedule'!$C:$C,'Income Schedule'!$A:$A,$A87)) | D87: =IF($A87="","",SUMIFS('Upcoming Bills'!$C:$C,'Upcoming Bills'!$B:$B,$A87)) | E87: =IF($A87="","",C87-D87) | F87: =IF($A87="","",F86+E87) | G87: =IF($A87="","",IF(C87>0,"Income","")&IF(AND(C87>0,D87>0)," • ","")&IF(D87>0,"Bills","")) | H87: =IF($A87="",NA(),$F87) -> #N/A
A88: =IF(77>$E$4,"",$B$4+77-1) | B88: =IF($A88="","",TEXT($A88,"ddd")) | C88: =IF($A88="","",SUMIFS('Income Schedule'!$C:$C,'Income Schedule'!$A:$A,$A88)) | D88: =IF($A88="","",SUMIFS('Upcoming Bills'!$C:$C,'Upcoming Bills'!$B:$B,$A88)) | E88: =IF($A88="","",C88-D88) | F88: =IF($A88="","",F87+E88) | G88: =IF($A88="","",IF(C88>0,"Income","")&IF(AND(C88>0,D88>0)," • ","")&IF(D88>0,"Bills","")) | H88: =IF($A88="",NA(),$F88) -> #N/A
A89: =IF(78>$E$4,"",$B$4+78-1) | B89: =IF($A89="","",TEXT($A89,"ddd")) | C89: =IF($A89="","",SUMIFS('Income Schedule'!$C:$C,'Income Schedule'!$A:$A,$A89)) | D89: =IF($A89="","",SUMIFS('Upcoming Bills'!$C:$C,'Upcoming Bills'!$B:$B,$A89)) | E89: =IF($A89="","",C89-D89) | F89: =IF($A89="","",F88+E89) | G89: =IF($A89="","",IF(C89>0,"Income","")&IF(AND(C89>0,D89>0)," • ","")&IF(D89>0,"Bills","")) | H89: =IF($A89="",NA(),$F89) -> #N/A
A90: =IF(79>$E$4,"",$B$4+79-1) | B90: =IF($A90="","",TEXT($A90,"ddd")) | C90: =IF($A90="","",SUMIFS('Income Schedule'!$C:$C,'Income Schedule'!$A:$A,$A90)) | D90: =IF($A90="","",SUMIFS('Upcoming Bills'!$C:$C,'Upcoming Bills'!$B:$B,$A90)) | E90: =IF($A90="","",C90-D90) | F90: =IF($A90="","",F89+E90) | G90: =IF($A90="","",IF(C90>0,"Income","")&IF(AND(C90>0,D90>0)," • ","")&IF(D90>0,"Bills","")) | H90: =IF($A90="",NA(),$F90) -> #N/A
A91: =IF(80>$E$4,"",$B$4+80-1) | B91: =IF($A91="","",TEXT($A91,"ddd")) | C91: =IF($A91="","",SUMIFS('Income Schedule'!$C:$C,'Income Schedule'!$A:$A,$A91)) | D91: =IF($A91="","",SUMIFS('Upcoming Bills'!$C:$C,'Upcoming Bills'!$B:$B,$A91)) | E91: =IF($A91="","",C91-D91) | F91: =IF($A91="","",F90+E91) | G91: =IF($A91="","",IF(C91>0,"Income","")&IF(AND(C91>0,D91>0)," • ","")&IF(D91>0,"Bills","")) | H91: =IF($A91="",NA(),$F91) -> #N/A
A92: =IF(81>$E$4,"",$B$4+81-1) | B92: =IF($A92="","",TEXT($A92,"ddd")) | C92: =IF($A92="","",SUMIFS('Income Schedule'!$C:$C,'Income Schedule'!$A:$A,$A92)) | D92: =IF($A92="","",SUMIFS('Upcoming Bills'!$C:$C,'Upcoming Bills'!$B:$B,$A92)) | E92: =IF($A92="","",C92-D92) | F92: =IF($A92="","",F91+E92) | G92: =IF($A92="","",IF(C92>0,"Income","")&IF(AND(C92>0,D92>0)," • ","")&IF(D92>0,"Bills","")) | H92: =IF($A92="",NA(),$F92) -> #N/A
A93: =IF(82>$E$4,"",$B$4+82-1) | B93: =IF($A93="","",TEXT($A93,"ddd")) | C93: =IF($A93="","",SUMIFS('Income Schedule'!$C:$C,'Income Schedule'!$A:$A,$A93)) | D93: =IF($A93="","",SUMIFS('Upcoming Bills'!$C:$C,'Upcoming Bills'!$B:$B,$A93)) | E93: =IF($A93="","",C93-D93) | F93: =IF($A93="","",F92+E93) | G93: =IF($A93="","",IF(C93>0,"Income","")&IF(AND(C93>0,D93>0)," • ","")&IF(D93>0,"Bills","")) | H93: =IF($A93="",NA(),$F93) -> #N/A
A94: =IF(83>$E$4,"",$B$4+83-1) | B94: =IF($A94="","",TEXT($A94,"ddd")) | C94: =IF($A94="","",SUMIFS('Income Schedule'!$C:$C,'Income Schedule'!$A:$A,$A94)) | D94: =IF($A94="","",SUMIFS('Upcoming Bills'!$C:$C,'Upcoming Bills'!$B:$B,$A94)) | E94: =IF($A94="","",C94-D94) | F94: =IF($A94="","",F93+E94) | G94: =IF($A94="","",IF(C94>0,"Income","")&IF(AND(C94>0,D94>0)," • ","")&IF(D94>0,"Bills","")) | H94: =IF($A94="",NA(),$F94) -> #N/A
A95: =IF(84>$E$4,"",$B$4+84-1) | B95: =IF($A95="","",TEXT($A95,"ddd")) | C95: =IF($A95="","",SUMIFS('Income Schedule'!$C:$C,'Income Schedule'!$A:$A,$A95)) | D95: =IF($A95="","",SUMIFS('Upcoming Bills'!$C:$C,'Upcoming Bills'!$B:$B,$A95)) | E95: =IF($A95="","",C95-D95) | F95: =IF($A95="","",F94+E95) | G95: =IF($A95="","",IF(C95>0,"Income","")&IF(AND(C95>0,D95>0)," • ","")&IF(D95>0,"Bills","")) | H95: =IF($A95="",NA(),$F95) -> #N/A
A96: =IF(85>$E$4,"",$B$4+85-1) | B96: =IF($A96="","",TEXT($A96,"ddd")) | C96: =IF($A96="","",SUMIFS('Income Schedule'!$C:$C,'Income Schedule'!$A:$A,$A96)) | D96: =IF($A96="","",SUMIFS('Upcoming Bills'!$C:$C,'Upcoming Bills'!$B:$B,$A96)) | E96: =IF($A96="","",C96-D96) | F96: =IF($A96="","",F95+E96) | G96: =IF($A96="","",IF(C96>0,"Income","")&IF(AND(C96>0,D96>0)," • ","")&IF(D96>0,"Bills","")) | H96: =IF($A96="",NA(),$F96) -> #N/A
A97: =IF(86>$E$4,"",$B$4+86-1) | B97: =IF($A97="","",TEXT($A97,"ddd")) | C97: =IF($A97="","",SUMIFS('Income Schedule'!$C:$C,'Income Schedule'!$A:$A,$A97)) | D97: =IF($A97="","",SUMIFS('Upcoming Bills'!$C:$C,'Upcoming Bills'!$B:$B,$A97)) | E97: =IF($A97="","",C97-D97) | F97: =IF($A97="","",F96+E97) | G97: =IF($A97="","",IF(C97>0,"Income","")&IF(AND(C97>0,D97>0)," • ","")&IF(D97>0,"Bills","")) | H97: =IF($A97="",NA(),$F97) -> #N/A
A98: =IF(87>$E$4,"",$B$4+87-1) | B98: =IF($A98="","",TEXT($A98,"ddd")) | C98: =IF($A98="","",SUMIFS('Income Schedule'!$C:$C,'Income Schedule'!$A:$A,$A98)) | D98: =IF($A98="","",SUMIFS('Upcoming Bills'!$C:$C,'Upcoming Bills'!$B:$B,$A98)) | E98: =IF($A98="","",C98-D98) | F98: =IF($A98="","",F97+E98) | G98: =IF($A98="","",IF(C98>0,"Income","")&IF(AND(C98>0,D98>0)," • ","")&IF(D98>0,"Bills","")) | H98: =IF($A98="",NA(),$F98) -> #N/A
A99: =IF(88>$E$4,"",$B$4+88-1) | B99: =IF($A99="","",TEXT($A99,"ddd")) | C99: =IF($A99="","",SUMIFS('Income Schedule'!$C:$C,'Income Schedule'!$A:$A,$A99)) | D99: =IF($A99="","",SUMIFS('Upcoming Bills'!$C:$C,'Upcoming Bills'!$B:$B,$A99)) | E99: =IF($A99="","",C99-D99) | F99: =IF($A99="","",F98+E99) | G99: =IF($A99="","",IF(C99>0,"Income","")&IF(AND(C99>0,D99>0)," • ","")&IF(D99>0,"Bills","")) | H99: =IF($A99="",NA(),$F99) -> #N/A
A100: =IF(89>$E$4,"",$B$4+89-1) | B100: =IF($A100="","",TEXT($A100,"ddd")) | C100: =IF($A100="","",SUMIFS('Income Schedule'!$C:$C,'Income Schedule'!$A:$A,$A100)) | D100: =IF($A100="","",SUMIFS('Upcoming Bills'!$C:$C,'Upcoming Bills'!$B:$B,$A100)) | E100: =IF($A100="","",C100-D100) | F100: =IF($A100="","",F99+E100) | G100: =IF($A100="","",IF(C100>0,"Income","")&IF(AND(C100>0,D100>0)," • ","")&IF(D100>0,"Bills","")) | H100: =IF($A100="",NA(),$F100) -> #N/A
A101: =IF(90>$E$4,"",$B$4+90-1) | B101: =IF($A101="","",TEXT($A101,"ddd")) | C101: =IF($A101="","",SUMIFS('Income Schedule'!$C:$C,'Income Schedule'!$A:$A,$A101)) | D101: =IF($A101="","",SUMIFS('Upcoming Bills'!$C:$C,'Upcoming Bills'!$B:$B,$A101)) | E101: =IF($A101="","",C101-D101) | F101: =IF($A101="","",F100+E101) | G101: =IF($A101="","",IF(C101>0,"Income","")&IF(AND(C101>0,D101>0)," • ","")&IF(D101>0,"Bills","")) | H101: =IF($A101="",NA(),$F101) -> #N/A
A102: =IF(91>$E$4,"",$B$4+91-1) | B102: =IF($A102="","",TEXT($A102,"ddd")) | C102: =IF($A102="","",SUMIFS('Income Schedule'!$C:$C,'Income Schedule'!$A:$A,$A102)) | D102: =IF($A102="","",SUMIFS('Upcoming Bills'!$C:$C,'Upcoming Bills'!$B:$B,$A102)) | E102: =IF($A102="","",C102-D102) | F102: =IF($A102="","",F101+E102) | G102: =IF($A102="","",IF(C102>0,"Income","")&IF(AND(C102>0,D102>0)," • ","")&IF(D102>0,"Bills","")) | H102: =IF($A102="",NA(),$F102) -> #N/A
A103: =IF(92>$E$4,"",$B$4+92-1) | B103: =IF($A103="","",TEXT($A103,"ddd")) | C103: =IF($A103="","",SUMIFS('Income Schedule'!$C:$C,'Income Schedule'!$A:$A,$A103)) | D103: =IF($A103="","",SUMIFS('Upcoming Bills'!$C:$C,'Upcoming Bills'!$B:$B,$A103)) | E103: =IF($A103="","",C103-D103) | F103: =IF($A103="","",F102+E103) | G103: =IF($A103="","",IF(C103>0,"Income","")&IF(AND(C103>0,D103>0)," • ","")&IF(D103>0,"Bills","")) | H103: =IF($A103="",NA(),$F103) -> #N/A
...
